Workbook
Name Actividad: #REF!
Name BASE: '[1]CONDUCTORES Y MATERIALES'!#REF!
Name BASE: '[2]CONDUCTORES Y MATERIALES'!#REF!
Name Base_de_Datos_PF: #REF!
Name BD_Servicios_CPO: #REF!
Name ESTRUCTURA: '[1]TABLA DE ESTRUCTURA'!$A$3:$K$1048576
Name ESTRUCTURA: '[2]TABLA DE ESTRUCTURA'!$A$3:$K$1048576
Name geees: #REF!
Name HOMOLOGADOS: #REF!
Name HOMOLOGADOS: #REF!
Name NO: #REF!
Name REPLANTEO: #REF!
Name SI: #REF!
Name Summary: #REF!
Name Summary: #REF!
Name ta: #REF!
Name Tb_Estructura: #REF!
Name Tb_Materiales: #REF!
Name xxxx: #REF!

Sheet peso de familias
A1: UU_TT | B1: Descripcion | C1: UNIDAD | D1: ACT_PRI | E1: peso de familias
A2: 1000568 | B2: Cobertor de Líneas MT 12.5kV MVLC 4/0 | C2: Mts. | D2: Instalación | E2: Material
A3: 1011408 | B3: Poste de madera de 60 Pies Clase 2 | C3: Und. | D3: Instalación | E3: Izaje Mt.
A4: AL-BT1 | B4: INSTALACIÓN DE LÍNEA DE BAJA TENSIÓN EN ALINEAMIENTO | C4: Und. | D4: Instalación | E4: Armado Bt.
A5: C45-MT1 | B5: INSTALACIÓN DE CRUCETA DOBLE DE ACERO PARA MEDIA TENSIÓN (C/SOPORTES A 45°) | C5: Und. | D5: Instalación | E5: Armado Mt.
A6: CA-101(465) | B6: CONEXIÓN DE CUT-OUT A 4651 | C6: Und. | D6: Instalación | E6: Armado Mt.
A7: CDA-MT11 | B7: INSTALACIÓN DE CRUCETA DOBLE DE ACERO PARA MEDIA TENSIÓN (CRUCETA DE 8') | C7: Und. | D7: Instalación | E7: Armado Mt.
A8: CSA-MT1 | B8: INSTALACIÓN DE CRUCETA SIMPLE DE ACERO PARA MEDIA TENSIÓN (CRUCETA DE 8') | C8: Und. | D8: Instalación | E8: Armado Mt.
A9: CV1-MT11 | B9: INSTALACIÓN DE CRUCETA SIMPLE DE ACERO EN VOLADIZO PARA MEDIA TENSIÓN(CRUCETA DE 8) | C9: Und. | D9: Instalación | E9: Armado Mt.
A10: CV2-MT1 | B10: INSTALACIÓN DE CRUCETA DE ACERO EN VOLADIZO PARA MEDIA TENSIÓN(2 NIVELES ) | C10: Und. | D10: Instalación | E10: Armado Mt.
A11: CV3-MT1 | B11: INSTALACIÓN DE CRUCETA DE ACERO EN VOLADIZO EN TRES NIVELES PARA MEDIA TENSION | C11: Und. | D11: Instalación | E11: Armado Mt.
A12: CV4-MT11 | B12: INSTALACIÓN DE CRUCETA DOBLE DE ACERO EN VOLADIZO PARA MEDIA TENSIÓN(CRUCETA DE 8) | C12: Und. | D12: Instalación | E12: Armado Mt.
A13: CV5-MT1(10) | B13: INSTALACIÓN DE CRUCETA DOBLE DE ACERO EN VOLADIZO PARA MEDIA TENSIÓN (2 NIVELES) | C13: Und. | D13: Instalación | E13: Armado Mt.
A14: CV6-MT1 | B14: INSTALACIÓN DE CRUCETA DE ACERO DOBLE EN VOLADIZO EN TRES NIVELES PARA MEDIA TENSION | C14: Und. | D14: Instalación | E14: Armado Mt.
A15: CV8-MT1 | B15: INSTALACIÓN DE CRUCETA DE ACERO SIMPLE EN VOLADIZO DE 10´ | C15: Und. | D15: Instalación | E15: Armado Mt.
... A210: VA-MT(T) | B210: TRANSFERENCIA DE CABLE DE VIENTO AEREO | C210: Und. | D210: Transferencia | E210: Armado Mt.

Sheet TD GENERAL
A2: MAT | B2: (Todas)
A4: ACTIVIDAD | B4: Código | C4: Descripción de la actividad | D4: UNIDAD | E4: dddd
B5: 1AC-103 | C5: INSTALACIÓN DE ACOMETIDA 120V RED ANTIFRAUDE CON BASE, DESDE LA CAJA DERIVADORA | D5: UND | E5: =+VLOOKUP($B5,Tabla3[UU_TT],1,FALSE) -> 1AC-103
B6: 1AC-104 | C6: INSTALACIÓN DE ACOMETIDA 240V RED ANTIFRAUDE CON BASE, DESDE LA CAJA DERIVADORA | D6: UND | E6: =+VLOOKUP($B6,Tabla3[UU_TT],1,FALSE) -> 1AC-104
B7: 1AC-105 | C7: INSTALACIÓN DE ACOMETIDA 120V DESDE RED ANTIFRAUDE CON SMCA CON DISPLAY, TOMACORRIENTE. | D7: UND | E7: =+VLOOKUP($B7,Tabla3[UU_TT],1,FALSE) -> 1AC-105
B8: 1AC-106 | C8: INSTALACIÓN DE ACOMETIDA 240V DESDE RED ANTIFRAUDE CON SMCA CON DISPLAY, TOMACORRIENTE. | D8: UND | E8: =+VLOOKUP($B8,Tabla3[UU_TT],1,FALSE) -> 1AC-106
B9: 1AL-BT | C9: INSTALACIÓNALACIÓN LÍNEA DE BT EN ALINEAMIENTO | D9: UND | E9: =+VLOOKUP($B9,Tabla3[UU_TT],1,FALSE) -> 1AL-BT
B10: 1AP-101 | C10: Instalación Luminaria Con Soporte de 6' en Poste de MT & BT Hasta 400 W | D10: UND | E10: =+VLOOKUP($B10,Tabla3[UU_TT],1,FALSE) -> 1AP-101
B11: 1AP-102 | C11: Instalación Luminaria Con Soporte de 12' en Poste de MT & BT Hasta 400 W | D11: UND | E11: =+VLOOKUP($B11,Tabla3[UU_TT],1,FALSE) -> 1AP-102
B12: 1AP-108 | C12: INSTALACIÓN DE BALASTRO O INGNITOR (ARRANCADOR) | D12: UND | E12: =+VLOOKUP($B12,Tabla3[UU_TT],1,FALSE) -> #N/A
B13: 1AP-109 | C13: INSTALACION DE TABLERO O CAJA DE CONTROL DE CONJUNTO DE LUMINARIAS | D13: UND | E13: =+VLOOKUP($B13,Tabla3[UU_TT],1,FALSE) -> #N/A
B14: 1AP-110 | C14: INSTALACIÓN DE CONTACTOR DE LUMINARIAS EN POSTE (RELAY) | D14: UND | E14: =+VLOOKUP($B14,Tabla3[UU_TT],1,FALSE) -> #N/A
B15: 1BCON-01 | C15: INSTALACIÓN SOPORTE DE BANCO DE CONDENSADORES. | D15: UND | E15: =+VLOOKUP($B15,Tabla3[UU_TT],1,FALSE) -> 1BCON-01
B16: 1BCON-02 | C16: INSTALACIÓN DE CONDENSADORES O CAPACITOR, NO INCLUYE PROTECCIÓN | D16: UND | E16: =+VLOOKUP($B16,Tabla3[UU_TT],1,FALSE) -> 1BCON-02
... B725: VA-MT1 | C725: INSTALACIÓN CABLE RETENIDA AEREA DE POSTE A POSTE (MT) | D725: UND | E725: =+VLOOKUP($B725,Tabla3[UU_TT],1,FALSE) -> VA-MT1
A726: REMOCION | B726: 1AC-103 | C726: INSTALACIÓN DE ACOMETIDA 120V RED ANTIFRAUDE CON BASE, DESDE LA CAJA DERIVADORA | D726: UND | E726: =+VLOOKUP($B726,Tabla3[UU_TT],1,FALSE) -> 1AC-103
A727: REMOCION | B727: 3AC-103 | C727: DESMONTAJE DE ACOMETIDA 120V RED ANTIFRAUDE CON BASE, DESDE LA CAJA DERIVADORA | D727: UND | E727: =+VLOOKUP($B727,Tabla3[UU_TT],1,FALSE) -> #N/A
A728: REMOCION | B728: 3AC-104 | C728: DESMONTAJE DE ACOMETIDA 240V RED ANTIFRAUDE CON BASE, DESDE LA CAJA DERIVADORA | D728: UND | E728: =+VLOOKUP($B728,Tabla3[UU_TT],1,FALSE) -> #N/A
A729: REMOCION | B729: 3AC-105 | C729: DESMONTAJE DE ACOMETIDA 120V DESDE RED ANTIFRAUDE CON SMCA CON DISPLAY, TOMACORRIENTE | D729: UND | E729: =+VLOOKUP($B729,Tabla3[UU_TT],1,FALSE) -> #N/A
A730: REMOCION | B730: 3AC-106 | C730: DESMONTAJE DE ACOMETIDA 240V DESDE RED ANTIFRAUDE CON SMCA CON DISPLAY, TOMACORRIENTE. | D730: UND | E730: =+VLOOKUP($B730,Tabla3[UU_TT],1,FALSE) -> #N/A
A731: REMOCION | B731: 3AL-BT | C731: DESMONTAJE LÍNEA DE BT EN ALINEAMIENTO | D731: UND | E731: =+VLOOKUP($B731,Tabla3[UU_TT],1,FALSE) -> #N/A
A732: REMOCION | B732: 3BCON-01 | C732: DESMONTAJE SOPORTE DE BANCO DE CONDENSADORES. | D732: UND | E732: =+VLOOKUP($B732,Tabla3[UU_TT],1,FALSE) -> #N/A
A733: REMOCION | B733: 3BCON-02 | C733: DESMONTAJE DE CONDENSADORES O CAPACITOR, NO INCLUYE PROTECCIÓN | D733: UND | E733: =+VLOOKUP($B733,Tabla3[UU_TT],1,FALSE) -> #N/A
A734: REMOCION | B734: 3BOM-01 | C734: Desmontaje de Bombillas Hasta 400 W | D734: UND | E734: =+VLOOKUP($B734,Tabla3[UU_TT],1,FALSE) -> #N/A
A735: REMOCION | B735: 3BOM-02 | C735: Desmontaje de Bombillas Mayor a 400 W | D735: UND | E735: =+VLOOKUP($B735,Tabla3[UU_TT],1,FALSE) -> #N/A
A736: REMOCION | B736: 3BREGU-01 | C736: DESMONTAJE DE BASE PARA BANCO DE REGULADORES/BOOSTER HASTA 3 X 75KV | D736: UND | E736: =+VLOOKUP($B736,Tabla3[UU_TT],1,FALSE) -> #N/A
A737: REMOCION | B737: 3BREGU-02 | C737: DESMONTAJE DE BASE PARA BANCO DE REGULADORES/BOOSTER HASTA 3 X 225KV | D737: UND | E737: =+VLOOKUP($B737,Tabla3[UU_TT],1,FALSE) -> #N/A
... A1570: (en blanco) | B1570: (en blanco) | C1570: (en blanco) | D1570: (en blanco) | E1570: =+VLOOKUP($B1570,Tabla3[UU_TT],1,FALSE) -> #N/A
A1571: Total general | E1571: =+VLOOKUP($B1571,Tabla3[UU_TT],1,FALSE) -> #N/A

Sheet Hoja7
B3: Código | C3: Descripción de la actividad | D3: UNIDAD
B4: 1MT-208 | C4: INSTALACIÓN LINEA 2Ø,ALINEAMIENTO CON DERIVACION 1Ø | D4: UND
B5: 1MT-209 | C5: INSTALACIÓN LINEA 2Ø,ALINEAMIENTO CON DERIVACION 2Ø
B6: 1MT-210 | C6: INSTALACIÓN FIN LINEA 2Ø, VERTICAL CON DERIVACION 1Ø
B7: 1MT-211 | C7: INSTALACIÓN FIN LINEA 2Ø, HORIZONTAL DERIVACION 1Ø

Sheet Todo los proyecto
A3: Código | B3: Descripción de la actividad
A4: ACMCA-240V1 | B4: INSTALACIÓN.ACOM.240V EN SCMA CON MED.DIPLAY Y TC. | C4: =+VLOOKUP($A4,TB_CALCULO_MAT[UU_TT],1,) -> ACMCA-240V1
A5: AL-BT1 | B5: INSTALACIÓN DE LÍNEA DE BAJA TENSIÓN EN ALINEAMIENTO | C5: =+VLOOKUP($A5,TB_CALCULO_MAT[UU_TT],1,) -> AL-BT1
A6: AL-BT3 | B6: REM. LINEA DE BT EN ALINEAMIENTO | C6: =+VLOOKUP($A6,TB_CALCULO_MAT[UU_TT],1,) -> #N/A
A7: AP-1032 | B7: TRANSFERENCIA LUMINARIA BRAZO 6' EN POSTE | C7: =+VLOOKUP($A7,TB_CALCULO_MAT[UU_TT],1,) -> #N/A
A8: AP-1033 | B8: REM LUMI. COMPL. C/SOPORTE DE 6' EN POSTE DE MT/BT | C8: =+VLOOKUP($A8,TB_CALCULO_MAT[UU_TT],1,) -> #N/A
A9: AP-LED1 | B9: INSTALACIÓN LUMINARIA TIPO LED 120W 240 V, CON SOPORTE DE 6 | C9: =+VLOOKUP($A9,TB_CALCULO_MAT[UU_TT],1,) -> AP-LED1
A10: BT-201-A1 | B10: INSTALACIÓN DE JUMPER AEREO TRIPLEX 4/0 -4/0 | C10: =+VLOOKUP($A10,TB_CALCULO_MAT[UU_TT],1,) -> BT-201-A1
A11: BT-201-B1 | B11: INSTALACIÓN DE JUMPER AEREO TRIPLEX 2/0 -2/0 | C11: =+VLOOKUP($A11,TB_CALCULO_MAT[UU_TT],1,) -> BT-201-B1
A12: BT-201-C1 | B12: INSTALACIÓN DE JUMPER AEREO TRIPLEX 4/0 -2/0 | C12: =+VLOOKUP($A12,TB_CALCULO_MAT[UU_TT],1,) -> BT-201-C1
A13: CAJ-1033 | B13: REMOCION DE CAJA DERIVADORA AF (30 SALIDAS) | C13: =+VLOOKUP($A13,TB_CALCULO_MAT[UU_TT],1,) -> #N/A
A14: CC-2/0-2/01 | B14: INSTALACIÓN DE CONEXIÓN 2/0 - 2/0 | C14: =+VLOOKUP($A14,TB_CALCULO_MAT[UU_TT],1,) -> CC-2/0-2/01
A15: CC-4/0-2/01 | B15: INSTALACIÓN DE CONEXIÓN 4/0 - 2/0 | C15: =+VLOOKUP($A15,TB_CALCULO_MAT[UU_TT],1,) -> CC-4/0-2/01
... A228: (en blanco) | B228: (en blanco) | C228: =+VLOOKUP($A228,TB_CALCULO_MAT[UU_TT],1,) -> #N/A
A229: Total general | C229: =+VLOOKUP($A229,TB_CALCULO_MAT[UU_TT],1,) -> #N/A

Sheet Completas
A1: UUTT -LOTE_18 | B1: DESCRIPCION CONTRATO | C1: Cod-Material | D1: Codigo SAP | E1: Descripcion material contrato | F1: Unidad | G1: Cantidad
A2: 1AL-BT | B2: Instalación de Línea de Baja Tensión en Alineamiento | C2: W-7A | D2: 1000050 | E2: Alambre de amarre #4 AWG solido de aluminio | F2: Mts. | G2: 1
A3: 1AL-BT | B3: Instalación de Línea de Baja Tensión en Alineamiento | C3: CP-02C | D3: 1009782 | E3: Cable de acero cobreado desnudo #2 AWG; 7 hilos | F3: Mts. | G3: 1
A4: 1AL-BT | B4: Instalación de Línea de Baja Tensión en Alineamiento | C4: AC-11A | D4: 1000000 | E4: Aislad T/Carr 3x3-1/8 76x80mm 11/16 53-2 | F4: Und. | G4: 1
A5: 1AL-BT | B5: Instalación de Línea de Baja Tensión en Alineamiento | C5: W-9C | D5: 1002185 | E5: ARANDELA CUADRADA 3" X 3'' PARA TORNILLO DE 5/8"-3/4'' | F5: Und. | G5: 1
A6: 1AL-BT | B6: Instalación de Línea de Baja Tensión en Alineamiento | C6: W-10C | D6: 1002205 | E6: ARANDELA DE PRESION P/TORNILLO 5/8'' | F6: Und. | G6: 1
A7: 1AL-BT | B7: Instalación de Línea de Baja Tensión en Alineamiento | C7: C-39C | D7: 1009963 | E7: CONECTOR CUÑA PRESION 2/0 AWG A 2 CU AWG | F7: Und. | G7: 1
A8: 1AL-BT | B8: Instalación de Línea de Baja Tensión en Alineamiento | C8: GCT-ST1 | D8: 1009789 | E8: GRAPA DE CONEXIÓN DOBLE CABLE DE TIERRA SIN TORNILLO | F8: Und. | G8: 1
A9: 1AL-BT | B9: Instalación de Línea de Baja Tensión en Alineamiento | C9: S-1D | D9: 1002349 | E9: Tornillo P/ Aislador T/ Carrete 5/8"x16" | F9: Und. | G9: 1
A10: 1CDA-MT | B10: Instalación de Cruceta Doble de Acero para Media Tensión (cruceta de 8') | C10: W-10C | D10: 1002205 | E10: ARANDELA DE PRESION P/TORNILLO 5/8'' | F10: Und. | G10: 18
A11: 1CDA-MT | B11: Instalación de Cruceta Doble de Acero para Media Tensión (cruceta de 8') | C11: W-10B | D11: 1002201 | E11: Arandela de presión para tornillo de 1/2” | F11: Und. | G11: 1
A12: 1CDA-MT | B12: Instalación de Cruceta Doble de Acero para Media Tensión (cruceta de 8') | C12: C-20D | D12: 1002083 | E12: Cruceta de acero galvanizado, perfil "L", de 3"x 3"x 1/4" x 8' | F12: Und. | G12: 2
A13: 1CDA-MT | B13: Instalación de Cruceta Doble de Acero para Media Tensión (cruceta de 8') | C13: B-1C | D13: 1002283 | E13: Tornillo de espaciamiento acero galvanizado 5/8” x 12” | F13: Und. | G13: 5
... A129: 1HA-105B | B129: Instalación de Retenida aérea simple en Media Tension | C129: E-1B | D129: 1002398 | E129: TUERCA OJO CON GUARDACABO RECTO 5/8" 55.6 KN | F129: Und. | G129: 1
A130: 1HA-105B | B130: Instalación de Retenida aérea simple en Media Tension | C130: G-2A | D130: #N/A | E130: Tornillo guardacabo recto 5/8" x 12” | F130: Und. | G130: 1
A131: 1MT-101 | B131: Instalación de Montaje 1ø Línea con Ángulo de 0º a 5º | C131: W-7A | D131: 1000050 | E131: Alambre de amarre #4 AWG solido de aluminio | F131: Mts. | G131: 2
A132: 1MT-101 | B132: Instalación de Montaje 1ø Línea con Ángulo de 0º a 5º | C132: CP-02C | D132: 1009782 | E132: Cable de acero cobreado desnudo #2 AWG; 7 hilos | F132: Mts. | G132: 1
A133: 1MT-101 | B133: Instalación de Montaje 1ø Línea con Ángulo de 0º a 5º | C133: AC-11A | D133: 1000000 | E133: Aislad T/Carr 3x3-1/8 76x80mm 11/16 53-2 | F133: Und. | G133: 1
A134: 1MT-101 | B134: Instalación de Montaje 1ø Línea con Ángulo de 0º a 5º | C134: AR-12A | D134: 1000004 | E134: Aislador Ríg T/ Esp 57-1 C/ Esp y Tuerca | F134: Und. | G134: 1
A135: 1MT-101 | B135: Instalación de Montaje 1ø Línea con Ángulo de 0º a 5º | C135: W-9c | D135: 1002185 | E135: ARANDELA CUADRADA 3" X 3'' PARA TORNILLO DE 5/8"-3/4'' | F135: Und. | G135: 3
A136: 1MT-101 | B136: Instalación de Montaje 1ø Línea con Ángulo de 0º a 5º | C136: W-10c | D136: 1002205 | E136: ARANDELA DE PRESION P/TORNILLO 5/8'' | F136: Und. | G136: 3
A137: 1MT-101 | B137: Instalación de Montaje 1ø Línea con Ángulo de 0º a 5º | C137: C-39C | D137: 1009963 | E137: CONECTOR CUÑA PRESION 2/0 AWG A 2 CU AWG | F137: Und. | G137: 1
A138: 1MT-101 | B138: Instalación de Montaje 1ø Línea con Ángulo de 0º a 5º | C138: GCT-ST1 | D138: 1009789 | E138: GRAPA DE CONEXIÓN DOBLE CABLE DE TIERRA SIN TORNILLO | F138: Und. | G138: 1
A139: 1MT-101 | B139: Instalación de Montaje 1ø Línea con Ángulo de 0º a 5º | C139: I-1A | D139: 1003156 | E139: Perno para aisladores line post 3/4" - 3/4" x 3". | F139: Und. | G139: 1
A140: 1MT-101 | B140: Instalación de Montaje 1ø Línea con Ángulo de 0º a 5º | C140: B-2D | D140: 1002329 | E140: Tornillo Máq Cab Cuad 5/8"x10" | F140: Und. | G140: 2
A141: 1MT-101 | B141: Instalación de Montaje 1ø Línea con Ángulo de 0º a 5º | C141: E-4A | D141: 1004830 | E141: Tuerca cuadrada acero galvanizado para tornillo 5/8”. | F141: Und. | G141: 1
A142: 1MT-101 | B142: Instalación de Montaje 1ø Línea con Ángulo de 0º a 5º | C142: I-2F | D142: 1004822 | E142: Espiga soporte de acero para aislador tipo line-post en punta de poste | F142: Und. | G142: 1
... A219: 1MT-307 | B219: Instalación de Montaje 3ø, (Horizontal) Fin de Linea | C219: CP-02C | D219: 1009782 | E219: Cable de acero cobreado desnudo #2 AWG; 7 hilos | F219: Mts. | G219: 0.5
A220: 1MT-307 | B220: Instalación de Montaje 3ø, (Horizontal) Fin de Linea | C220: C-15C | D220: #N/A | E220: Grapa de retención para conductores #312.8 MCM - #559 MCM | F220: Und. | G220: 3
A221: 1MT-307 | B221: Instalación de Montaje 3ø, (Horizontal) Fin de Linea | C221: AS-22D | D221: 1000005 | E221: Aislador Susp 12.5kV Polimérico | F221: Und. | G221: 3
A222: 1MT-307 | B222: Instalación de Montaje 3ø, (Horizontal) Fin de Linea | C222: W-10C | D222: 1002205 | E222: ARANDELA DE PRESION P/TORNILLO 5/8'' | F222: Und. | G222: 18
A223: 1MT-307 | B223: Instalación de Montaje 3ø, (Horizontal) Fin de Linea | C223: W-10B | D223: 1002201 | E223: Arandela de presión para tornillo de 1/2” | F223: Und. | G223: 1
A224: 1MT-307 | B224: Instalación de Montaje 3ø, (Horizontal) Fin de Linea | C224: C-20D | D224: 1002083 | E224: Cruceta de acero galvanizado, perfil "L", de 3"x 3"x 1/4" x 8' | F224: Und. | G224: 2
A225: 1MT-307 | B225: Instalación de Montaje 3ø, (Horizontal) Fin de Linea | C225: C-26A | D225: 1001892 | E225: Grapa de fijación de cable a superficie plana 1/4" p/conductor Cu 2/0-#8 AWG | F225: Und. | G225: 1
A226: 1MT-307 | B226: Instalación de Montaje 3ø, (Horizontal) Fin de Linea | C226: C-15B | D226: 1000742 | E226: GRAPA DE RETENCION DE ACERO GALVANIZ. PARA COND. DE 1/0AL-ACSR A 4/0AL ACSR | F226: Und. | G226: 1
A227: 1MT-307 | B227: Instalación de Montaje 3ø, (Horizontal) Fin de Linea | C227: B-1C | D227: 1002283 | E227: Tornillo de espaciamiento acero galvanizado 5/8” x 12” | F227: Und. | G227: 5
A228: 1MT-307 | B228: Instalación de Montaje 3ø, (Horizontal) Fin de Linea | C228: E-2A | D228: 1002390 | E228: TUERCA DE OJO OVAL PARA TORNILO DE 5/8" | F228: Und. | G228: 4
A229: 1MT-307 | B229: Instalación de Montaje 3ø, (Horizontal) Fin de Linea | C229: B-6A | D229: 1001241 | E229: Fleje plancha de acero galv. 1-7/32"x 7/32" x 28" | F229: Und. | G229: 4
A230: 1MT-307 | B230: Instalación de Montaje 3ø, (Horizontal) Fin de Linea | C230: W-10A | D230: 1002204 | E230: Arandela de presión para tornillo de 3/8” | F230: Und. | G230: 4
A231: 1MT-307 | B231: Instalación de Montaje 3ø, (Horizontal) Fin de Linea | C231: B-2B | D231: 1002308 | E231: Tornillo de máquina acero galvanizado cabeza cuadrada 1/2" x 12” | F231: Und. | G231: 1
A232: 1MT-307 | B232: Instalación de Montaje 3ø, (Horizontal) Fin de Linea | C232: B-5A | D232: 1002325 | E232: Tornillo de máquina acero galvanizado cabeza hexagonal 3/8” x 2” | F232: Und. | G232: 4
... A386: 1SECC-07 | B386: INSTALACIÓN SECCIONADOR-FUSIBLE EN POSTE 200 AMP. | C386: CP-02C | D386: 1009782 | E386: Cable de acero cobreado desnudo #2 AWG; 7 hilos | F386: Mts. | G386: 1
A387: 1SECC-07 | B387: INSTALACIÓN SECCIONADOR-FUSIBLE EN POSTE 200 AMP. | C387: CAPE | D387: #N/A | E387: Conector amovible para estribo | F387: Und. | G387: 1
A388: 1SECC-07 | B388: INSTALACIÓN SECCIONADOR-FUSIBLE EN POSTE 200 AMP. | C388: W-10B | D388: 1002201 | E388: Arandela de presión para tornillo de 1/2” | F388: Und. | G388: 1
A389: 1SECC-07 | B389: INSTALACIÓN SECCIONADOR-FUSIBLE EN POSTE 200 AMP. | C389: C-39C | D389: 1009963 | E389: CONECTOR CUÑA PRESION 2/0 AWG A 2 CU AWG | F389: Und. | G389: 1
A390: 1SECC-07 | B390: INSTALACIÓN SECCIONADOR-FUSIBLE EN POSTE 200 AMP. | C390: B-5B | D390: 1002339 | E390: Tornillo de máquina acero galvanizado cabeza hexagonal 1/2”x 2” | F390: Und. | G390: 1
A391: 1SECC-07 | B391: INSTALACIÓN SECCIONADOR-FUSIBLE EN POSTE 200 AMP. | C391: S-4 | D391: #N/A | E391: Soporte en poste doble unidad; perno 1/2" x 2" (pararrayos-seccionador) | F391: Und. | G391: 1
A392: 1SECC-07 | B392: INSTALACIÓN SECCIONADOR-FUSIBLE EN POSTE 200 AMP. | C392: SF-11A | D392: #N/A | E392: Seccionador fusible de 200 A; 15 kV | F392: Und. | G392: 1
A393: 1VA-MT | B393: Instalación de Viento aéreo (Media Tensión) | C393: CV-01C | D393: 1000130 | E393: CABLE DE VIENTO 7/16'' 76 KN | F393: Mts. | G393: 20
A394: 1VA-MT | B394: Instalación de Viento aéreo (Media Tensión) | C394: G-1B | D394: 1002020 | E394: TERMINAL PREFORMADO 7/16" | F394: Und. | G394: 2
A395: 1VA-MT | B395: Instalación de Viento aéreo (Media Tensión) | C395: E-1B | D395: 1002398 | E395: TUERCA OJO CON GUARDACABO RECTO 5/8" 55.6 KN | F395: Und. | G395: 1
A396: CV2-MTE | B396: Cruceta de acero en voladizo en dos niveles para media tension | C396: B-2D | D396: 1002329 | E396: Tornillo Máq Cab Cuad 5/8"x10" | F396: Und. | G396: 3
A397: CV2-MTE | B397: Cruceta de acero en voladizo en dos niveles para media tension | C397: B-5B | D397: 1002339 | E397: Tornillo de máquina acero galvanizado cabeza hexagonal 1/2”x 2” | F397: Und. | G397: 3
A398: CV2-MTE | B398: Cruceta de acero en voladizo en dos niveles para media tension | C398: B-7A | D398: 1001238 | E398: Fleje Diag AcerGalv1 3/4x1 3/4x3/16"x60" | F398: Und. | G398: 1
A399: CV2-MTE | B399: Cruceta de acero en voladizo en dos niveles para media tension | C399: B-10A | D399: 1001245 | E399: Fleje Vertical Acer Galv 39" 1½x1½x3/16" | F399: Und. | G399: 1
A400: CV2-MTE | B400: Cruceta de acero en voladizo en dos niveles para media tension | C400: E-4 | D400: 1004830 | E400: Tuerca cuadrada para tornillo 5/8" | F400: Und. | G400: 1
A401: CV2-MTE | B401: Cruceta de acero en voladizo en dos niveles para media tension | C401: W-9C | D401: 1002185 | E401: ARANDELA CUADRADA 3" X 3'' PARA TORNILLO DE 5/8"-3/4'' | F401: Und. | G401: 3
A402: CV2-MTE | B402: Cruceta de acero en voladizo en dos niveles para media tension | C402: W-10B | D402: 1002201 | E402: Arandela de presión para tornillo de 1/2” | F402: Und. | G402: 3
A403: CV2-MTE | B403: Cruceta de acero en voladizo en dos niveles para media tension | C403: W-10C | D403: 1002205 | E403: ARANDELA DE PRESION P/TORNILLO 5/8'' | F403: Und. | G403: 3
A404: CV2-MTE | B404: Cruceta de acero en voladizo en dos niveles para media tension | C404: C-20C1 | D404: 1010958 | E404: CRUCETA DE ACERO 3"X3" X1/4 , PERFIL L DE 6" | F404: Und. | G404: 2
... A443: SUAF-BT | B443: Instalación de Suspensión AF para Baja Tension en Cruceta | C443: E-2A | D443: 1002390 | E443: TUERCA DE OJO OVAL PARA TORNILO DE 5/8" | F443: Und. | G443: 1

Sheet Hoja2
A3: Descripción | B3: Código Material
A4: Cobertor de Líneas MT 12.5kV MVLC 4/0 | B4: 1000568
A5: CONEXIÓN DE CUT-OUT A 4651 | B5: C-40B
A6: CONEXIÓN DE CUT-OUT A 4651 | B6: CAPE
A7: CONEXIÓN DE CUT-OUT A 4651 | B7: CM-01G
A8: Cruceta de acero en semivoladizo para media tensión | B8: B-2D
A9: Cruceta de acero en semivoladizo para media tensión | B9: B-5B
A10: Cruceta de acero en semivoladizo para media tensión | B10: B-7B
A11: Cruceta de acero en semivoladizo para media tensión | B11: C-20D
A12: Cruceta de acero en semivoladizo para media tensión | B12: E-4
A13: Cruceta de acero en semivoladizo para media tensión | B13: GR-10
A14: Cruceta de acero en semivoladizo para media tensión | B14: W-10b
A15: Cruceta de acero en semivoladizo para media tensión | B15: W-10C
A16: Cruceta de acero en semivoladizo para media tensión | B16: W-9C
... A863: POSTE DE HORMIGÓN PRETENSADO VIBRADO 800 DAN-10.5 M(35’) | B863: HPV-800-10
A864: Poste de madera de 60 Pies Clase 2 | B864: 1011408
A865: Puesta a Tierra con Anillo Cerrado para Poste de Hormigon | B865: B-7Y
A866: Puesta a Tierra con Anillo Cerrado para Poste de Hormigon | B866: CP-02C
A867: Puesta a Tierra con Anillo Cerrado para Poste de Hormigon | B867: HA-1B
A868: Puesta a Tierra con Anillo Cerrado para Poste de Hormigon | B868: R-2F
A869: Puesta a Tierra con Anillo Cerrado para Poste de Hormigon | B869: TUB-4B
A870: Puesta a Tierra con Anillo Cerrado para Poste de Hormigon | B870: C-R1D
A871: Puesta a Tierra Interior en Poste de Concreto | B871: B-2O
A872: Puesta a Tierra Interior en Poste de Concreto | B872: CP-02C
A873: Puesta a Tierra Interior en Poste de Concreto | B873: R-2F
A874: Puesta a Tierra Interior en Poste de Concreto | B874: TB-02
A875: Puesta a Tierra Interior en Poste de Concreto | B875: C-R1D
A876: RECONECTADOR AUTOMATICO DE CIRCUITO RE | B876: ITC-22R1
... A892: Intalacion de luminaria led | B892: CM-22D
A893: Intalacion de luminaria led | B893: 1014667
A894: Intalacion de luminaria led | B894: F-5A
A895: INSTALACIÓN.ACOM.240V EN SCMA CON MED.DIPLAY Y TC. | B895: E-2a
A896: INSTALACIÓN.ACOM.240V EN SCMA CON MED.DIPLAY Y TC. | B896: A-5C
A897: INSTALACIÓN.ACOM.240V EN SCMA CON MED.DIPLAY Y TC. | B897: CS-33C
A898: INSTALACIÓN.ACOM.240V EN SCMA CON MED.DIPLAY Y TC. | B898: MMT-240-3H
A899: INSTALACIÓN.ACOM.240V EN SCMA CON MED.DIPLAY Y TC. | B899: MPVC-DIS-240V
A900: INSTALACIÓN.ACOM.240V EN SCMA CON MED.DIPLAY Y TC. | B900: PZ-2C
A901: INSTALACIÓN.ACOM.240V EN SCMA CON MED.DIPLAY Y TC. | B901: TC-002
A902: INSTALACIÓN DE JUMPER AEREO TRIPLEX 4/0 -4/0 | B902: C-6HC
A903: INSTALACIÓN DE JUMPER AEREO TRIPLEX 4/0 -4/0 | B903: CB-11F
A904: INSTALACIÓN DE JUMPER AEREO TRIPLEX 4/0 -4/0 | B904: C-43Z
A905: Instalación de Jumper Aereo Triplex 2/0 -2/0 | B905: C-39A
... A933: INSTALACIÓN CRUCETA DOBLE DE ACERO DE 6' PARA MT | B933: B-6
A934: INSTALACIÓN CRUCETA DOBLE DE ACERO DE 6' PARA MT | B934: 1010958
A935: INSTALACIÓN DE CUCHILLAS Y PARARRAYOS EN CRUCETAS | B935: AD-4B
A936: INSTALACIÓN DE CUCHILLAS Y PARARRAYOS EN CRUCETAS | B936: B-1C
A937: INSTALACIÓN DE CUCHILLAS Y PARARRAYOS EN CRUCETAS | B937: B-2B
A938: INSTALACIÓN DE CUCHILLAS Y PARARRAYOS EN CRUCETAS | B938: B-2J
A939: INSTALACIÓN DE CUCHILLAS Y PARARRAYOS EN CRUCETAS | B939: B-2O
A940: INSTALACIÓN DE CUCHILLAS Y PARARRAYOS EN CRUCETAS | B940: B-6A
A941: INSTALACIÓN DE CUCHILLAS Y PARARRAYOS EN CRUCETAS | B941: C-20/A1D
A942: INSTALACIÓN DE CUCHILLAS Y PARARRAYOS EN CRUCETAS | B942: C-6HF
A943: INSTALACIÓN DE CUCHILLAS Y PARARRAYOS EN CRUCETAS | B943: CM-01G
A944: INSTALACIÓN DE CUCHILLAS Y PARARRAYOS EN CRUCETAS | B944: CP-02C
A945: INSTALACIÓN DE CUCHILLAS Y PARARRAYOS EN CRUCETAS | B945: S-4
A946: INSTALACIÓN DE CUCHILLAS Y PARARRAYOS EN CRUCETAS | B946: W-10A
... A1019: INSTALACIÓN GAB. P/TELEM. 12 MED. 120/240V, EN PATX | B1019: MMC-COL
A1020: INSTALACIÓN GAB. P/TELEM. 12 MED. 120/240V, EN PATX | B1020: 1011373
A1021: INSTALACIÓN GAB. P/TELEM. 12 MED. 120/240V, EN PATX | B1021: S-4G
A1022: INSTALACIÓN GAB. P/TELEM. 12 MED. 120/240V, EN PATX | B1022: S-5P
A1023: INSTALACIÓN GAB. P/TELEM. 12 MED. 120/240V, EN PATX | B1023: TF-1B
A1024: INSTALACIÓN GAB. P/TELEM. 18 MED. 120/240V,EN PATX | B1024: B-5E
A1025: INSTALACIÓN GAB. P/TELEM. 18 MED. 120/240V,EN PATX | B1025: E-2a
A1026: INSTALACIÓN GAB. P/TELEM. 18 MED. 120/240V,EN PATX | B1026: HA-1B
A1027: INSTALACIÓN GAB. P/TELEM. 18 MED. 120/240V,EN PATX | B1027: W-10C
A1028: INSTALACIÓN GAB. P/TELEM. 18 MED. 120/240V,EN PATX | B1028: W-9C
A1029: INSTALACIÓN GAB. P/TELEM. 18 MED. 120/240V,EN PATX | B1029: B-7Z
A1030: INSTALACIÓN GAB. P/TELEM. 18 MED. 120/240V,EN PATX | B1030: C-43D
A1031: INSTALACIÓN GAB. P/TELEM. 18 MED. 120/240V,EN PATX | B1031: CON-1C
A1032: INSTALACIÓN GAB. P/TELEM. 18 MED. 120/240V,EN PATX | B1032: CRT-1
... A1038: INSTALACIÓN GAB. P/TELEM. 18 MED. 120/240V,EN PATX | B1038: TF-1B
A1039: INSTALACIÓN GAB. P/TELEM. 18 MED. 120/240V,EN PATX | B1039: 2011178
A1040: INSTALACIÓN DE RETENIDA SENCILLA DE POSTE A TIERRA EN BAJA TENSION | B1040: AH-11A
A1041: INSTALACIÓN DE RETENIDA SENCILLA DE POSTE A TIERRA EN BAJA TENSION | B1041: B-2E
A1042: INSTALACIÓN DE RETENIDA SENCILLA DE POSTE A TIERRA EN BAJA TENSION | B1042: CV-01A
A1043: INSTALACIÓN DE RETENIDA SENCILLA DE POSTE A TIERRA EN BAJA TENSION | B1043: E-3A
A1044: INSTALACIÓN DE RETENIDA SENCILLA DE POSTE A TIERRA EN BAJA TENSION | B1044: G-1A
A1045: INSTALACIÓN DE RETENIDA SENCILLA DE POSTE A TIERRA EN BAJA TENSION | B1045: R-1A
A1046: INSTALACIÓN DE RETENIDA SENCILLA DE POSTE A TIERRA EN BAJA TENSION | B1046: R-5
A1047: INSTALACIÓN DE RETENIDA SENCILLA DE POSTE A TIERRA EN BAJA TENSION | B1047: W-10C
A1048: INSTALACIÓN DE RETENIDA SENCILLA DE POSTE A TIERRA EN BAJA TENSION | B1048: W-9B
A1049: INSTALACIÓN DE RETENIDA SENCILLA DE POSTE A TIERRA EN BAJA TENSION | B1049: W-9C
A1050: INSTALACIÓN DE VIENTO DOBLE (UNA SOLA ANCLA) | B1050: AH-11A
A1051: INSTALACIÓN DE VIENTO DOBLE (UNA SOLA ANCLA) | B1051: B-2E
... A1160: INSTALACIÓN 1Ø DOBLE TERMINAL DE MEDIA TENSION | B1160: W-10C
A1161: INSTALACIÓN MONTAJE 3Ø, LINEA CON ANGULO DE 6º A 25º | B1161: 1000004
A1162: INSTALACIÓN MONTAJE 3Ø, LINEA CON ANGULO DE 6º A 25º | B1162: 1000017
A1163: INSTALACIÓN MONTAJE 3Ø, LINEA CON ANGULO DE 6º A 25º | B1163: 1001223
A1164: INSTALACIÓN MONTAJE 3Ø, LINEA CON ANGULO DE 6º A 25º | B1164: 1001242
A1165: INSTALACIÓN MONTAJE 3Ø, LINEA CON ANGULO DE 6º A 25º | B1165: 1002083
A1166: INSTALACIÓN MONTAJE 3Ø, LINEA CON ANGULO DE 6º A 25º | B1166: 1002201
A1167: INSTALACIÓN MONTAJE 3Ø, LINEA CON ANGULO DE 6º A 25º | B1167: 1002204
A1168: INSTALACIÓN MONTAJE 3Ø, LINEA CON ANGULO DE 6º A 25º | B1168: 1002205
A1169: INSTALACIÓN MONTAJE 3Ø, LINEA CON ANGULO DE 6º A 25º | B1169: 1002283
A1170: INSTALACIÓN MONTAJE 3Ø, LINEA CON ANGULO DE 6º A 25º | B1170: 1002308
A1171: INSTALACIÓN MONTAJE 3Ø, LINEA CON ANGULO DE 6º A 25º | B1171: 1002325
A1172: INSTALACIÓN 1Ø (AF) VOLAD.,ALINEAM. ANGULO DE 0ª A 5ª | B1172: AC-11A
A1173: INSTALACIÓN 1Ø (AF) VOLAD.,ALINEAM. ANGULO DE 0ª A 5ª | B1173: AR-12A
A1174: INSTALACIÓN 1Ø (AF) VOLAD.,ALINEAM. ANGULO DE 0ª A 5ª | B1174: B-2D
A1175: INSTALACIÓN 1Ø (AF) VOLAD.,ALINEAM. ANGULO DE 0ª A 5ª | B1175: B-2E
...

Sheet TBD1
E2: kkkk
A3: Actividad_Principal | B3: UUTT | C3: Descripcion | D3: Unidad | E3: Suma de Cantidad_Ejecutada
A4: INSTALACIÓN | B4: AL-BT3 | C4: Derivación cable guía Medio Vano | D4: und | E4: 71 | F4: =+VLOOKUP($B4,TB_CALCULO_MAT[UU_TT],1,) -> #N/A
A5: INSTALACIÓN | B5: AL-BT3 | C5: DOBLE TERMINAL DE BAJA TENSIÓN (CABLE NEUTRO) | D5: und | E5: 112 | F5: =+VLOOKUP($B5,TB_CALCULO_MAT[UU_TT],1,) -> #N/A
A6: INSTALACIÓN | B6: AL-BT3 | C6: INSTALACIÓN DE FIN BAJA TENSIÓN | D6: und | E6: 119 | F6: =+VLOOKUP($B6,TB_CALCULO_MAT[UU_TT],1,) -> #N/A
A7: INSTALACIÓN | B7: ART-TUB41 | C7: CONFECCION DE HOYO DE 5` EN TERRENO NORMAL | D7: und | E7: 38 | F7: =+VLOOKUP($B7,TB_CALCULO_MAT[UU_TT],1,) -> #N/A
A8: INSTALACIÓN | B8: ART-TUB41 | C8: EXCAVACIÓN EN TERRENO ROCOSO < 12M | D8: und | E8: 72 | F8: =+VLOOKUP($B8,TB_CALCULO_MAT[UU_TT],1,) -> #N/A
A9: INSTALACIÓN | B9: ART-TUB41 | C9: Excavacion para poste de 30 o vientos De roca | D9: und | E9: 67 | F9: =+VLOOKUP($B9,TB_CALCULO_MAT[UU_TT],1,) -> #N/A
A10: INSTALACIÓN | B10: ART-TUB41 | C10: Instalación de Armado y transp. tubo metalico 4" x 25' para bt | D10: und | E10: 422 | F10: =+VLOOKUP($B10,TB_CALCULO_MAT[UU_TT],1,) -> #N/A
A11: INSTALACIÓN | B11: BT-201-A1 | C11: Instalación de Conexión 4/0 - 2/0 | D11: und | E11: 29 | F11: =+VLOOKUP($B11,TB_CALCULO_MAT[UU_TT],1,) -> BT-201-A1
A12: INSTALACIÓN | B12: BT-201-A1 | C12: Instalación de Conexión 4/0 - 4/0 | D12: und | E12: 75 | F12: =+VLOOKUP($B12,TB_CALCULO_MAT[UU_TT],1,) -> BT-201-A1
A13: INSTALACIÓN | B13: BT-201-A1 | C13: Instalación de Jumper Aereo Triplex 4/0 -4/0 | D13: und | E13: 144 | F13: =+VLOOKUP($B13,TB_CALCULO_MAT[UU_TT],1,) -> BT-201-A1
A14: INSTALACIÓN | B14: BT-201-A1 | C14: INSTALACION JUMPER EN POSTE 4/0 - 4/0 | D14: und | E14: 26 | F14: =+VLOOKUP($B14,TB_CALCULO_MAT[UU_TT],1,) -> BT-201-A1
A15: INSTALACIÓN | B15: CC-4/0-2/01 | C15: Instalación de Conexión 4/0 - 2/0 | D15: und | E15: 206 | F15: =+VLOOKUP($B15,TB_CALCULO_MAT[UU_TT],1,) -> CC-4/0-2/01
... A203: TRANSFERENCIA | B203: TP-2C2 | C203: Transferencia de Tendido de Conductor Triplex 2/0 Neutro 2/0 | D203: ml | E203: 5427 | F203: =+VLOOKUP($B203,TB_CALCULO_MAT[UU_TT],1,) -> #N/A
A204: Total general | E204: 118274 | F204: =+VLOOKUP($B204,TB_CALCULO_MAT[UU_TT],1,) -> #N/A

Sheet Ejecutado
B2: 🔴 TABLA 5 — EJECUTADO DIARIO | ACTUALIZAR CADA DÍA | SOLO AGREGAR FILAS — NUNCA BORRAR
B4: ID_Registro | C4: Codigo_Poste | D4: UUTT | E4: Descripcion | F4: Unidad | G4: Cantidad_Ejecutada | H4: Fecha_Ejecucion | I4: ID_Tarea | J4: ID_Circuito | K4: Nombre_Proyecto | L4: Subestacion | M4: Coordenada_X | N4: Coordenada_Y | O4: Hasta | P4: Actividad_Principal | Q4: Nombre_Tarea | R4: Observaciones
B5: EJ04270 | C5: SPCR-68 | D5: EXC-21 | E5: EXCAVACIÓN EN TERRENO ROCOSO < 12M | F5: und | G5: 2 | H5: 45658 | I5: T441 | J5: SPCR-05 | K5: Proyectos Rehabilitacion de Redes MT-BT y Normalizacion Usuario SPCR-05 | L5: SUB Capotillo | M5: 18.455792 | N5: -69.904762 | P5: INSTALACIÓN | Q5: OBRAS CIVILES
B6: EJ04271 | C6: SPCR-89 | D6: ART-TUB41 | E6: Instalación de Armado y transp. tubo metalico 4" x 25' para bt | F6: und | G6: 2 | H6: 45663 | I6: T441 | J6: SPCR-05 | K6: Proyectos Rehabilitacion de Redes MT-BT y Normalizacion Usuario SPCR-05 | L6: SUB Capotillo | M6: 18.43819 | N6: -69.835244 | P6: INSTALACIÓN | Q6: OBRAS CIVILES
B7: EJ03396 | C7: HAIN-50 | D7: EXC-21 | E7: EXCAVACIÓN EN TERRENO ROCOSO < 12M | F7: und | G7: 1 | H7: 45664 | I7: T391 | J7: HAIN-05 | K7: Proyectos Rehabilitacion de Redes MT-BT y Normalizacion Usuario HAIN-05 | L7: SUB Capotillo | M7: 18.443049 | N7: -69.863516 | P7: INSTALACIÓN | Q7: OBRAS CIVILES
B8: EJ03096 | C8: HAIN-65 | D8: EXC-31 | E8: EXCAVACIÓN EN TERRENO ROCOSO PARA POSTE >12M | F8: und | G8: 1 | H8: 45665 | I8: T361 | J8: HAIN-02 | K8: Proyectos Rehabilitacion de Redes MT-BT y Normalizacion Usuario HAIN-02 | L8: SUB Alma Rosa | M8: 18.523869 | N8: -69.858458 | P8: INSTALACIÓN | Q8: OBRAS CIVILES
B9: EJ02517 | C9: GUAL-11 | D9: EXC-21 | E9: EXCAVACIÓN EN TERRENO ROCOSO < 12M | F9: und | G9: 5 | H9: 45666 | I9: T321 | J9: GUAL-03 | K9: Proyectos Rehabilitacion de Redes MT-BT y Normalizacion Usuario GUAL-03 | L9: SUB Villa Faro | M9: 18.519726 | N9: -69.918148 | P9: INSTALACIÓN | Q9: OBRAS CIVILES
B10: EJ02518 | C10: GUAL-54 | D10: EXC-21 | E10: EXCAVACIÓN EN TERRENO ROCOSO < 12M | F10: und | G10: 4 | H10: 45670 | I10: T321 | J10: GUAL-03 | K10: Proyectos Rehabilitacion de Redes MT-BT y Normalizacion Usuario GUAL-03 | L10: SUB Isabelita | M10: 18.517829 | N10: -69.887159 | P10: INSTALACIÓN | Q10: OBRAS CIVILES
B11: EJ04272 | C11: SPCR-10 | D11: EXC-11 | E11: Excavacion para poste de 30 o vientos De roca | F11: und | G11: 1 | H11: 45670 | I11: T441 | J11: SPCR-05 | K11: Proyectos Rehabilitacion de Redes MT-BT y Normalizacion Usuario SPCR-05 | L11: SUB Capotillo | M11: 18.503987 | N11: -69.878801 | P11: INSTALACIÓN | Q11: OBRAS CIVILES
B12: EJ03097 | C12: HAIN-54 | D12: EXC-31 | E12: EXCAVACIÓN EN TERRENO ROCOSO PARA POSTE >12M | F12: und | G12: 1 | H12: 45671 | I12: T361 | J12: HAIN-02 | K12: Proyectos Rehabilitacion de Redes MT-BT y Normalizacion Usuario HAIN-02 | L12: SUB Los Frailes | M12: 18.44163 | N12: -69.855113 | P12: INSTALACIÓN | Q12: OBRAS CIVILES
B13: EJ03397 | C13: HAIN-57 | D13: EXC-41 | E13: EXCAVACIÓN EN TERRENO ROCOSO PARA POSTE >14M | F13: und | G13: 1 | H13: 45671 | I13: T391 | J13: HAIN-05 | K13: Proyectos Rehabilitacion de Redes MT-BT y Normalizacion Usuario HAIN-05 | L13: SUB Nacional | M13: 18.495502 | N13: -69.920439 | P13: INSTALACIÓN | Q13: OBRAS CIVILES
B14: EJ03538 | C14: SPCR-50 | D14: ZURD-11 | E14: Instalación de excavacion zanja 0.8 x 2.0 m para tubos y conductores URD | F14: und | G14: 5 | H14: 45671 | I14: T401 | J14: SPCR-01 | K14: Proyectos Rehabilitacion de Redes MT-BT y Normalizacion Usuario SPCR-01 | L14: SUB Los Mina Norte | M14: 18.49136 | N14: -69.832257 | P14: INSTALACIÓN | Q14: OBRAS CIVILES
B15: EJ03887 | C15: SPCR-17 | D15: EXC-21 | E15: EXCAVACIÓN EN TERRENO ROCOSO < 12M | F15: und | G15: 2 | H15: 45671 | I15: T421 | J15: SPCR-03 | K15: Proyectos Rehabilitacion de Redes MT-BT y Normalizacion Usuario SPCR-03 | L15: SUB Villa Faro | M15: 18.436503 | N15: -69.90418 | P15: INSTALACIÓN | Q15: OBRAS CIVILES
B16: EJ03098 | C16: HAIN-32 | D16: EXC-41 | E16: EXCAVACIÓN EN TERRENO ROCOSO PARA POSTE >14M | F16: und | G16: 1 | H16: 45673 | I16: T361 | J16: HAIN-02 | K16: Proyectos Rehabilitacion de Redes MT-BT y Normalizacion Usuario HAIN-02 | L16: SUB Los Frailes | M16: 18.495849 | N16: -69.891164 | P16: INSTALACIÓN | Q16: OBRAS CIVILES
... B7112: EJ06999 | C7112: MULT-89 | D7112: PR-2011 | E7112: INSTALACION PUESTA A TIERRA EN POSTE METALICO | F7112: und | G7112: 3 | H7112: 46105 | I7112: T688 | J7112: MULTI-09 | K7112: Rehabilitacion Redes MT-BT Fondo Multilateral MULTI-09 | L7112: SUB Los Tres Brazos | M7112: 18.519066 | N7112: -69.922729 | P7112: INSTALACIÓN | Q7112: PROTECCIONES DE MT

Sheet MATERIALES GENERADOS
D2: X
A3: Código Material | B3: Descripción_MAT | C3: Unidad
A4: 1000004 | B4: Aislador Ríg T/ Esp 57-1 C/ Esp y Tuerca | C4: Und.
A5: 1000017 | B5: Aislador T/ Esp PIN CL55-5 1" | C5: Und.
A6: 1000095 | B6: CABLE COBRE URD #1/0 AISL P/ 15kV | C6: Mts.
A7: 1000411 | B7: Bombilla Sodio Alta Pres 400W 100V HPS | C7: Und.
A8: 1000434 | B8: Luminaria T/ Cobra HPS 400W | C8: Und.
A9: 1000568 | B9: Cobertor de Líneas MT 12.5kV MVLC 4/0 | C9: Mts.
A10: 1001223 | B10: Espiga Acero 3/4"x7 3/4" | C10: Und.
A11: 1001242 | B11: Fleje Plancha Acero 1 1/4x1/4"x28" | C11: Und.
A12: 1002083 | B12: Cruceta Acer 3"x3"x1/4" Perf L 8'-0" | C12: Und.
A13: 1002201 | B13: Arandela Presión P/ Tornillo 1/2'' | C13: Und.
A14: 1002204 | B14: Arandela Presión P/ Tornillo 3/8" | C14: Und.
A15: 1002205 | B15: Arandela Presión P/ Tornillo 5/8'' | C15: Und.
... A28: 2011178 | B28: Gabinete de 18 medidores con GPRS | C28: Und.
A29: B-1F | B29: TORNILLO DE ESPACIAMIENTO CON 4 TUERCAS 5/8" X 18" | C29: Und.
A30: B-2a | B30: TORNILLO DE MAQUINA ACERO GALVANIZADO CABEZA CUADRADA 1/2" X 10" | C30: Und.
A31: A-5C | B31: TARUGO-PERNO ACERADO RECUB. ZINC 5/8" X 3 3/4", PERNO DE 1/2" | C31: Und.
A32: A-5F | B32: TARUGO-PERNOACERADO RECUB.ZINC LONG 13/4",PERNO DE 1/4" | C32: Und.
A33: A-7A | B33: TARUGO PLAST. C/TORNILLO CABEZA HEXAGONAL NO.10-12, LONG. 1" DIAM. 9/32" | C33: Und.
A34: AC-11A | B34: Aislad T/Carr 3x3-1/8 76x80mm 11/16 53-2 | C34: Und.
A35: AD-4B | B35: Pararrayos de distribución de 9 kV; 12.47 kV. Estrella | C35: Und.
A36: AH-11A | B36: CONO DE ANCLAR DE CONCRETO 18" X 6" X 8" | C36: Und.
A37: AM-12C | B37: Conductor de cobre #3/0 AWG tipo THHN | C37: Mts.
A38: AM-12D | B38: Conductor de cobre #300 MCM tipo THHN | C38: Mts.
A39: AMD-01 | B39: Armario para medición industrial (con velo transparente) | C39: Und.
A40: AR-12A | B40: AISLADOR DE PORCELANA TIPO POSTE 15 KV CLASE 57-1 | C40: Und.
A41: AR-13C | B41: Aislador T/ Esp PIN CL56-3 1 3/8" 34.5kV | C41: Und.
B42: Aislador de porcelana tipo poste 35 kV Clase 57-3 | C42: Und.
A43: AS-1A | B43: Aro Seguridad para Sellos tipo Pin | C43: Und.
A44: AS-22D | B44: AISLADOR POLIMÉRICO TIPO SUSPENSIÓN 15 KV | C44: Und.
B45: AISLADOR POLIMERICO TIPO SUSPENSION, 15 KV | C45: Und.
A46: B-10A | B46: Fleje vertical de acero galv. 1-1/2" x 1-1/2" x 3/16"; longitud 39" | C46: Und.
A47: B-10D | B47: Fleje vertical de acero galv. 1-1/2" x 1-1/2" x 3/16"; longitud 54" | C47: Und.
A48: B-1C | B48: Tornillo de espaciamiento acero galvanizado 5/8” x 12” | C48: Und.
B49: TORNILLO DE ESPACIAMIENTO ACERO GALVANIZADO 5/8" X 12". | C49: Und.
A50: B-1D | B50: TORNILLO DE ESPACIAMIENTO ACERO GALVANIZADO 5/8" X 14". | C50: Und.
B51: TORNILLOS DE ESPACIAMIENTO. 4 TUERCAS CUAD.5/8" X 14"(16MMX350MM) | C51: Und.
A52: B-2B | B52: TORNILLO DE MAQUINA ACERO GALVANIZADO CABEZA CUADRADA 1/2" X 12". | C52: Und.
A53: B-2C | B53: Tornillo de máquina acero galvanizado cabeza cuadrada 5/8” x 10” | C53: Und.
A54: B-2D | B54: TORNILLO DE MAQUINA ACERO GALVANIZADO CABEZA CUADRADA 5/8" X 12". | C54: Und.
B55: Tornillo Máq Cab Cuad 5/8"x12" | C55: Und.
A56: B-2E | B56: Tornillo de máquina acero galvanizado cabeza cuadrada 5/8” x 14” | C56: Und.
A57: B-2H | B57: TORNILLO DE MAQUINA CABEZA CUADRADA 3/4'' X 12'' | C57: Und.
A58: B-2J | B58: TORNILLO DE MAQUINA CABEZA CUAD. 3/8" X 2" | C58: Und.
A59: B-2K | B59: TORNILLO DE MAQUINA CABEZA CUAD. 1/2" X 10" | C59: Und.
A60: B-2O | B60: TORNILLO DE MAQUINA CABEZA CUAD. 1/2" X 2" | C60: Und.
A61: B-2Q | B61: TORNILLO DE MAQUINA ACERO GALVANIZADO CABEZA CUADRADA 1/2" X 6" | C61: Und.
A62: B-4A | B62: Conector Perno partido 250-500 MCM | C62: Und.
A63: B-5A | B63: TORNILLO DE MAQUINA ACERO GALVANIZADO CABEZA HEXAGONAL 3/8" X 2". | C63: Und.
A64: B-5B | B64: Tornillo de máquina acero galvanizado cabeza hexagonal 1/2”x 2” | C64: Und.
A65: B-5C | B65: Tornillo de maquina acero galvanizado cabeza hexagonal 1/2" x 3”. | C65: Und.
A66: B-5E | B66: Tornillo Maquina Cabeza Hex. 5/8" X 3" | C66: Und.
A67: B-6 | B67: FLEJE DE PLANCHA DE ACERO DE 1¼" X 1/4" LONGITUD 28" | C67: Und.
... A81: C-15B | B81: GRAPA DE RETENCION DE ACERO GALVANIZ. PARA COND. DE 1/0AL-ACSR A 4/0AL ACSR | C81: Und.
B82: GRAPA DE RETENCIÓN PARA CONDUCTORES #2/0 AWG - #312.8 MCM | C82: Und.
A83: C-15C | B83: Grapa de retención para conductores #312.8 MCM - #559 MCM | C83: Und.
B84: GRAPA DE RETENCIÓN PARA CONDUCTORES #465 MCM - #465 MCM | C84: Und.
A85: C-15D | B85: GRAPA DE RETENCION DE ACERO GALVANIZ. PARA COND. DE 1/0 AL-ACSR A 636MCM AL | C85: Und.
A86: C-16 | B86: TORNILLO DE MAQUINA CABEZA CUAD. 5/8" X 12" | C86: Und.
A87: C-16H | B87: GRAPA DE DERIVACION 8 A 2/0 AWG -8 A 2/0 AWG | C87: Und.
A88: C-18B | B88: ABRAZADERA DE CONTRA PRESIÓN PARA TUBO DE ANCLAJE DE 2" | C88: Und.
A89: C-18BK | B89: Abrazadera metálica tipo omega de 3/4" | C89: Und.
A90: C-19/A1A | B90: CRUCETA DE MADERA DE 3 3/4" X 4 3/4" X 10` | C90: Und.
A91: C-20/A1D | B91: CRUCETA DE ACERO 3" X 3" X 1/4" PERFIL L 8'-0" | C91: Und.
A92: C-20/A1E | B92: CRUCETA DE ACERO 3"X3" X1/4 , PERFIL L DE 10' | C92: Und.
A93: C-20C | B93: Cruceta de acero galvanizado, perfil "L", de 3"x 3"x 1/4" x 6' | C93: Und.
A94: C-20C1 | B94: CRUCETA DE ACERO 3"X3" X1/4 , PERFIL L DE 6" | C94: Und.
A95: C-20D | B95: Cruceta de acero galvanizado, perfil "L", de 3"x 3"x 1/4" x 8' | C95: Und.
A96: C-20E | B96: CRUCETA DE ACERO GALVANIZADO, PERFIL "L", DE 3"X 3"X 1/4" X 10' | C96: Und.
... A151: CV-01C | B151: CABLE DE RETENIDA DE 7/16" | C151: Mts.
B152: CABLE DE VIENTO 7/16'' 76 KN | C152: Mts.
A153: D-1 | B153: Porta aislador en "U" de 1-1/2" x 1/8"; orificio de 11/16", pin de 5/8" | C153: Und.
A154: D-1B | B154: Porta aislador en "V"; 6 1/4" x 3 5/8" x 1 7/32 x 7/32'' | C154: Und.
A155: D-1E | B155: PORTA AISLADOR EN U PARA CRUCETA DE 6 1/4" X 3 5/8" X 1 7/32 ESPESOR 7/32 | C155: Und.
A156: DPS-25 | B156: COLLAR DE AMARRE P/ UN HAZ DE ACOM. 25MM C/TARUGO | C156: Und.
A157: E-1B | B157: TUERCA OJO CON GUARDACABO RECTO 5/8" 55.6 KN | C157: Und.
A158: E-2a | B158: TUERCA DE OJO ACERO GALVANIZADO TORNILLO 5/8". | C158: Und.
B159: TUERCA DE OJO OVAL PARA TORNILO DE 5/8" | C159: Und.
A160: E-2C | B160: TUERCA DE OJO OVAL PARA TORNILO DE 1/2" | C160: Und.
A161: E-3A | B161: TUERCA DE OJO GUARDACABO INCLINADO 45º PARA TORNILO DE 5/8" | C161: Und.
B162: TUERCA GUARDACABO INCLINADA PARA TORNILLO 5/8". | C162: Und.
A163: E-4 | B163: Tuerca cuadrada para tornillo de 5/8" | C163: Und.
A164: E-4A | B164: TUERCA CUADRADA ACERO GALVANIZADO PARA TORNILLO 5/8”. | C164: Und.
A165: F-5A | B165: Fotoceldas para Luminaria de 105-305 V. | C165: Und.
A166: F-5F | B166: FOTOCELDA DE 105-305 VOLT. MULTIRANGO NA | C166: Und.
A167: FU-11C | B167: Fusible de Expulsión 3.5 A; tipo D | C167: Und.
A168: FU-11G | B168: Fusible de Expulsión 5.2 A; tipo D | C168: Und.
A169: FU-11J | B169: Fusible de Expulsión 7 A; tipo D | C169: Und.
A170: FU-11M | B170: Fusible de Expulsión 10.4 A; tipo D | C170: Und.
A171: G-1A | B171: TERMINAL PREFORMADO 5/16" | C171: Und.
A172: G-1B | B172: TERMINAL PREFORMADO 7/16" | C172: Und.
B173: TERMINAL PREFORMADO PARA CABLE RETENIDA DE 7/16" | C173: Und.
A174: G-2A | B174: Tornillo guardacabo recto 5/8" x 12” | C174: Und.
A175: G-2B | B175: PERNO GUARDACABO PARA CABLE DE VIENTO,TORNILO 5/8 X 12" TUERCA CUAD | C175: Und.
A176: G-4B | B176: TUBO DE ANCLAJE 2" X 10' - SCHED 80 | C176: Und.
A177: GC-1K | B177: GABINETE Y CAJA DE CONTROL P/TELEM.18 MEDIDORES 120/240 V | C177: Und.
A178: GC-1M | B178: GABINETE Y CAJA DE CONTROL P/TELEM.12 MEDIDORES 120/240 V | C178: Und.
A179: GCT-ST1 | B179: GRAPA DE CONEXIÓN DOBLE A TIERRA SIN TORNILLO PARA TORNILLO 5/8" | C179: Und.
B180: GRAPA DE CONEXIÓN DOBLE CABLE DE TIERRA SIN TORNILLO | C180: Und.
...

Sheet BASE DE  CALCULO
A1: UU_TT | B1: Descripción | C1: Código Material | D1: Codigo SAP | E1: Descripción_MAT | F1: Unidad | G1: Cantidad Materiales
A2: 1000568 | B2: Cobertor de Líneas MT 12.5kV MVLC 4/0 | C2: 1000568 | D2: 1000568 | E2: Cobertor de Líneas MT 12.5kV MVLC 4/0 | F2: Mts. | G2: 1.05
A3: 1011408 | B3: Poste de madera de 60 Pies Clase 2 | C3: 1011408 | D3: 1011408 | E3: Poste de madera de 60 Pies Clase 2 | F3: Und. | G3: 1
A4: 1AC-103 | B4: INSTALACIÓN DE ACOMETIDA 120V RED ANTIFRAUDE CON BASE, DESDE LA CAJA DERIVADORA | C4: A-5C | D4: 1002233 | E4: TARUGO-PERNO ACERADO RECUB. ZINC 5/8" X 3 3/4", PERNO DE 1/2" | F4: Und. | G4: 1
A5: 1AC-103 | B5: INSTALACIÓN DE ACOMETIDA 120V RED ANTIFRAUDE CON BASE, DESDE LA CAJA DERIVADORA | C5: A-5F | D5: 1002231 | E5: TARUGO-PERNOACERADO RECUB.ZINC LONG 13/4",PERNO DE 1/4" | F5: Und. | G5: 2
A6: 1AC-103 | B6: INSTALACIÓN DE ACOMETIDA 120V RED ANTIFRAUDE CON BASE, DESDE LA CAJA DERIVADORA | C6: A-7A | D6: 1002236 | E6: TARUGO PLAST. C/TORNILLO CABEZA HEXAGONAL NO.10-12, LONG. 1" DIAM. 9/32" | F6: Und. | G6: 8
A7: 1AC-103 | B7: INSTALACIÓN DE ACOMETIDA 120V RED ANTIFRAUDE CON BASE, DESDE LA CAJA DERIVADORA | C7: AS-1A | D7: 1013657 | E7: Aro Seguridad para Sellos tipo Pin | F7: Und. | G7: 1
A8: 1AC-103 | B8: INSTALACIÓN DE ACOMETIDA 120V RED ANTIFRAUDE CON BASE, DESDE LA CAJA DERIVADORA | C8: BC-100 | D8: 1010780 | E8: Base circular de entrada de 1" para medidor socket FM 2S aluminio fundido | F8: Und. | G8: 1
A9: 1AC-103 | B9: INSTALACIÓN DE ACOMETIDA 120V RED ANTIFRAUDE CON BASE, DESDE LA CAJA DERIVADORA | C9: C-18BK | D9: 1014063 | E9: Abrazadera metálica tipo omega de 3/4" | F9: Und. | G9: 4
A10: 1AC-103 | B10: INSTALACIÓN DE ACOMETIDA 120V RED ANTIFRAUDE CON BASE, DESDE LA CAJA DERIVADORA | C10: CP-02A | D10: 1004213 | E10: Cable de acero cobreado desnudo #6 AWG; 3 hilos | F10: Mts. | G10: 2
A11: 1AC-103 | B11: INSTALACIÓN DE ACOMETIDA 120V RED ANTIFRAUDE CON BASE, DESDE LA CAJA DERIVADORA | C11: C-R1D | D11: 1001831 | E11: Conector Galv P/Varilla Tierra 1/2"-5/8" | F11: Und. | G11: 1
A12: 1AC-103 | B12: INSTALACIÓN DE ACOMETIDA 120V RED ANTIFRAUDE CON BASE, DESDE LA CAJA DERIVADORA | C12: CS-33A | D12: 1000100 | E12: CONDUCTOR CONCÉNTRICO DE ALUMINIO 2 X # 8 AWG | F12: Mts. | G12: 20
A13: 1AC-103 | B13: INSTALACIÓN DE ACOMETIDA 120V RED ANTIFRAUDE CON BASE, DESDE LA CAJA DERIVADORA | C13: DPS-25 | D13: 1000578 | E13: COLLAR DE AMARRE P/ UN HAZ DE ACOM. 25MM C/TARUGO | F13: Und. | G13: 4
A14: 1AC-103 | B14: INSTALACIÓN DE ACOMETIDA 120V RED ANTIFRAUDE CON BASE, DESDE LA CAJA DERIVADORA | C14: E-2a | D14: 1002390 | E14: TUERCA DE OJO OVAL PARA TORNILO DE 5/8" | F14: Und. | G14: 1
A15: 1AC-103 | B15: INSTALACIÓN DE ACOMETIDA 120V RED ANTIFRAUDE CON BASE, DESDE LA CAJA DERIVADORA | C15: MPLC-1A | D15: 1010783 | E15: MEDIDOR CL100,FM1S,120V,2H,MOD.COM.VIA PLC INCLUIDO | F15: Und. | G15: 1
... A40: 1AC-105 | B40: INSTALACIÓN DE ACOMETIDA 120V DESDE RED ANTIFRAUDE CON SMCA CON DISPLAY, TOMACORRIENTE. | C40: E-2a | D40: 1002390 | E40: TUERCA DE OJO OVAL PARA TORNILO DE 5/8" | F40: Und. | G40: 1
A41: 1AC-105 | B41: INSTALACIÓN DE ACOMETIDA 120V DESDE RED ANTIFRAUDE CON SMCA CON DISPLAY, TOMACORRIENTE. | C41: MPVC-120-2H | D41: 1011841 | E41: PANTALLA (DISPLAY) REPETIDORA DE MEDIDOR EN ALTURA CON TELEMEDICION. PANTALLA PARA VER CONSUMO DE CLIENTE, 120V,2 HILOS | F41: Und. | G41: 1
A42: 1AC-105 | B42: INSTALACIÓN DE ACOMETIDA 120V DESDE RED ANTIFRAUDE CON SMCA CON DISPLAY, TOMACORRIENTE. | C42: PZ-2C | D42: 1000816 | E42: Pinza de retención doble | F42: Und. | G42: 2
A43: 1AC-105 | B43: INSTALACIÓN DE ACOMETIDA 120V DESDE RED ANTIFRAUDE CON SMCA CON DISPLAY, TOMACORRIENTE. | C43: TC-002 | D43: 1010450 | E43: Tomacorriente Doble Salida, 125V para superficie | F43: Und. | G43: 1
A44: 1AC-106 | B44: INSTALACIÓN DE ACOMETIDA 240V DESDE RED ANTIFRAUDE CON SMCA CON DISPLAY, TOMACORRIENTE. | C44: A-5C | D44: 1002233 | E44: TARUGO-PERNO ACERADO RECUB. ZINC 5/8" X 3 3/4", PERNO DE 1/2" | F44: Und. | G44: 1
A45: 1AC-106 | B45: INSTALACIÓN DE ACOMETIDA 240V DESDE RED ANTIFRAUDE CON SMCA CON DISPLAY, TOMACORRIENTE. | C45: B-2E | D45: 1002331 | E45: Tornillo de máquina acero galvanizado cabeza cuadrada 5/8” x 14” | F45: Und. | G45: 2
A46: 1AC-106 | B46: INSTALACIÓN DE ACOMETIDA 240V DESDE RED ANTIFRAUDE CON SMCA CON DISPLAY, TOMACORRIENTE. | C46: CS-33C | D46: 1000102 | E46: Conductor concéntrico de Al 3 x #6 AWG | F46: Mts. | G46: 20
A47: 1AC-106 | B47: INSTALACIÓN DE ACOMETIDA 240V DESDE RED ANTIFRAUDE CON SMCA CON DISPLAY, TOMACORRIENTE. | C47: E-2a | D47: 1002390 | E47: TUERCA DE OJO OVAL PARA TORNILO DE 5/8" | F47: Und. | G47: 1
A48: 1AC-106 | B48: INSTALACIÓN DE ACOMETIDA 240V DESDE RED ANTIFRAUDE CON SMCA CON DISPLAY, TOMACORRIENTE. | C48: MPVC-240-2H | D48: 1011842 | E48: PANTALLA (DISPLAY) REPETIDORA DE MEDIDOR EN ALTURA CON TELEMEDICION. PANTALLA PARA VER CONSUMO DE CLIENTE, 240V,2 HILOS | F48: Und. | G48: 1
A49: 1AC-106 | B49: INSTALACIÓN DE ACOMETIDA 240V DESDE RED ANTIFRAUDE CON SMCA CON DISPLAY, TOMACORRIENTE. | C49: PZ-2C | D49: 1000816 | E49: Pinza de retención doble | F49: Und. | G49: 2
A50: 1AC-106 | B50: INSTALACIÓN DE ACOMETIDA 240V DESDE RED ANTIFRAUDE CON SMCA CON DISPLAY, TOMACORRIENTE. | C50: TC-002 | D50: 1010450 | E50: Tomacorriente Doble Salida, 125V para superficie | F50: Und. | G50: 1
A51: 1AL-BT | B51: Instalación de Línea de Baja Tensión en Alineamiento | C51: AC-11A | D51: 1000000 | E51: Aislad T/Carr 3x3-1/8 76x80mm 11/16 53-2 | F51: Und. | G51: 1
A52: 1AL-BT | B52: Instalación de Línea de Baja Tensión en Alineamiento | C52: C-39C | D52: 1009963 | E52: CONECTOR CUÑA PRESION 2/0 AWG A 2 CU AWG | F52: Und. | G52: 1
A53: 1AL-BT | B53: Instalación de Línea de Baja Tensión en Alineamiento | C53: CP-02C | D53: 1009782 | E53: Cable de acero cobreado desnudo #2 AWG; 7 hilos | F53: Mts. | G53: 1
A54: 1AL-BT | B54: Instalación de Línea de Baja Tensión en Alineamiento | C54: GCT-ST1 | D54: 1009789 | E54: GRAPA DE CONEXIÓN DOBLE CABLE DE TIERRA SIN TORNILLO | F54: Und. | G54: 1
A55: 1AL-BT | B55: Instalación de Línea de Baja Tensión en Alineamiento | C55: S-1D | D55: 1002349 | E55: Tornillo P/ Aislador T/ Carrete 5/8"x16" | F55: Und. | G55: 1
A56: 1AL-BT | B56: Instalación de Línea de Baja Tensión en Alineamiento | C56: W-10C | D56: 1002205 | E56: ARANDELA DE PRESION P/TORNILLO 5/8'' | F56: Und. | G56: 1
A57: 1AL-BT | B57: Instalación de Línea de Baja Tensión en Alineamiento | C57: W-7A | D57: 1000050 | E57: Alambre de amarre #4 AWG solido de aluminio | F57: Mts. | G57: 1
A58: 1AL-BT | B58: Instalación de Línea de Baja Tensión en Alineamiento | C58: W-9C | D58: 1002185 | E58: ARANDELA CUADRADA 3" X 3'' PARA TORNILLO DE 5/8"-3/4'' | F58: Und. | G58: 1
A59: 1AP-101 | B59: Instalación Luminaria Con Soporte de 6' en Poste de MT & BT Hasta 400 W | C59: 1000411 | D59: 1000411 | E59: Bombilla Sodio Alta Pres 400W 100V HPS | F59: Und. | G59: 1
A60: 1AP-101 | B60: Instalación Luminaria Con Soporte de 6' en Poste de MT & BT Hasta 400 W | C60: 1000434 | D60: 1000434 | E60: Luminaria T/ Cobra HPS 400W | F60: Und. | G60: 1
A61: 1AP-101 | B61: Instalación Luminaria Con Soporte de 6' en Poste de MT & BT Hasta 400 W | C61: BR-1A | D61: 1000413 | E61: Brazo de 6' para Luminaria de Alumbrado Público | F61: Und. | G61: 1
A62: 1AP-101 | B62: Instalación Luminaria Con Soporte de 6' en Poste de MT & BT Hasta 400 W | C62: CM-22D | D62: 1011853 | E62: Cable de control 3 conductores # 12 AWG | F62: Mts. | G62: 3.5
A63: 1AP-101 | B63: Instalación Luminaria Con Soporte de 6' en Poste de MT & BT Hasta 400 W | C63: F-5F | D63: 1000420 | E63: FOTOCELDA DE 105-305 VOLT. MULTIRANGO NA | F63: Und. | G63: 1
A64: 1AP-101 | B64: Instalación Luminaria Con Soporte de 6' en Poste de MT & BT Hasta 400 W | C64: W-10c | D64: 1002205 | E64: ARANDELA DE PRESION P/TORNILLO 5/8'' | F64: Und. | G64: 2
A65: 1AP-101 | B65: Instalación Luminaria Con Soporte de 6' en Poste de MT & BT Hasta 400 W | C65: W-9B | D65: 1002191 | E65: ARANDELA CUAD.2 1/4" X 2 1/4" ESP.3/16'' (TORN.5/8"-3/4") | F65: Und. | G65: 2
A66: 1AP-102 | B66: Instalación Luminaria Con Soporte de 12' en Poste de MT & BT Hasta 400 W | C66: 1000411 | D66: 1000411 | E66: Bombilla Sodio Alta Pres 400W 100V HPS | F66: Und. | G66: 1
A67: 1AP-102 | B67: Instalación Luminaria Con Soporte de 12' en Poste de MT & BT Hasta 400 W | C67: 1000434 | D67: 1000434 | E67: Luminaria T/ Cobra HPS 400W | F67: Und. | G67: 1
A68: 1AP-102 | B68: Instalación Luminaria Con Soporte de 12' en Poste de MT & BT Hasta 400 W | C68: BR-1A | D68: 1000414 | E68: Brazo de 6' para Luminaria de Alumbrado Público | F68: Und. | G68: 1
A69: 1AP-102 | B69: Instalación Luminaria Con Soporte de 12' en Poste de MT & BT Hasta 400 W | C69: CM-22D | D69: 1011853 | E69: Cable de control 3 conductores # 12 AWG | F69: Mts. | G69: 3.5
A70: 1AP-102 | B70: Instalación Luminaria Con Soporte de 12' en Poste de MT & BT Hasta 400 W | C70: F-5F | D70: 1000420 | E70: FOTOCELDA DE 105-305 VOLT. MULTIRANGO NA | F70: Und. | G70: 1
A71: 1AP-102 | B71: Instalación Luminaria Con Soporte de 12' en Poste de MT & BT Hasta 400 W | C71: W-10c | D71: 1002205 | E71: ARANDELA DE PRESION P/TORNILLO 5/8'' | F71: Und. | G71: 2
A72: 1AP-102 | B72: Instalación Luminaria Con Soporte de 12' en Poste de MT & BT Hasta 400 W | C72: W-9B | D72: 1002191 | E72: ARANDELA CUAD.2 1/4" X 2 1/4" ESP.3/16'' (TORN.5/8"-3/4") | F72: Und. | G72: 2
A73: 1BREGU-01 | B73: INSTALACIÓN DE BASE PARA BANCO DE REGULADORES/BOOSTER HASTA 3 X 75KV | C73: B-1F | E73: TORNILLO DE ESPACIAMIENTO CON 4 TUERCAS 5/8" X 18" | F73: Und. | G73: 12
A74: 1BREGU-01 | B74: INSTALACIÓN DE BASE PARA BANCO DE REGULADORES/BOOSTER HASTA 3 X 75KV | C74: B-2a | E74: TORNILLO DE MAQUINA ACERO GALVANIZADO CABEZA CUADRADA 1/2" X 10" | F74: Und. | G74: 22
A75: 1BREGU-01 | B75: INSTALACIÓN DE BASE PARA BANCO DE REGULADORES/BOOSTER HASTA 3 X 75KV | C75: B-2D | D75: 1002330 | E75: Tornillo Máq Cab Cuad 5/8"x12" | F75: Und. | G75: 12
A76: 1BREGU-01 | B76: INSTALACIÓN DE BASE PARA BANCO DE REGULADORES/BOOSTER HASTA 3 X 75KV | C76: B-7B | E76: Fleje diagonal de acero galv. 1-3/4" x 1-3/4" x 3/16"; longitud 84" | F76: Und. | G76: 12
A77: 1BREGU-01 | B77: INSTALACIÓN DE BASE PARA BANCO DE REGULADORES/BOOSTER HASTA 3 X 75KV | C77: C-19/A1A | E77: CRUCETA DE MADERA DE 3 3/4" X 4 3/4" X 10` | F77: Und. | G77: 32
A78: 1BREGU-01 | B78: INSTALACIÓN DE BASE PARA BANCO DE REGULADORES/BOOSTER HASTA 3 X 75KV | C78: W-10c | E78: ARANDELA DE PRESION P/TORNILLO 5/8'' | F78: Und. | G78: 60
A79: 1BREGU-01 | B79: INSTALACIÓN DE BASE PARA BANCO DE REGULADORES/BOOSTER HASTA 3 X 75KV | C79: W-9A | E79: ARANDELA CUADRADA 2X2'' PARA TORNILLO DE 1/2'' | F79: Und. | G79: 22
A80: 1BREGU-01 | B80: INSTALACIÓN DE BASE PARA BANCO DE REGULADORES/BOOSTER HASTA 3 X 75KV | C80: W-9C | E80: ARANDELA CUADRADA 3" X 3'' PARA TORNILLO DE 5/8"-3/4'' | F80: Und. | G80: 48
A81: 1BREGU-02 | B81: INSTALACIÓN DE BASE PARA BANCO DE REGULADORES/BOOSTER HASTA 3 X 225KV | C81: B-1F | E81: TORNILLO DE ESPACIAMIENTO CON 4 TUERCAS 5/8" X 18" | F81: Und. | G81: 12
A82: 1BREGU-02 | B82: INSTALACIÓN DE BASE PARA BANCO DE REGULADORES/BOOSTER HASTA 3 X 225KV | C82: B-2a | E82: TORNILLO DE MAQUINA ACERO GALVANIZADO CABEZA CUADRADA 1/2" X 10" | F82: Und. | G82: 22
A83: 1BREGU-02 | B83: INSTALACIÓN DE BASE PARA BANCO DE REGULADORES/BOOSTER HASTA 3 X 225KV | C83: B-2D | D83: 1002330 | E83: Tornillo Máq Cab Cuad 5/8"x12" | F83: Und. | G83: 12
A84: 1BREGU-02 | B84: INSTALACIÓN DE BASE PARA BANCO DE REGULADORES/BOOSTER HASTA 3 X 225KV | C84: B-7B | E84: Fleje diagonal de acero galv. 1-3/4" x 1-3/4" x 3/16"; longitud 84" | F84: Und. | G84: 12
A85: 1BREGU-02 | B85: INSTALACIÓN DE BASE PARA BANCO DE REGULADORES/BOOSTER HASTA 3 X 225KV | C85: C-19/A1A | E85: CRUCETA DE MADERA DE 3 3/4" X 4 3/4" X 10` | F85: Und. | G85: 32
A86: 1BREGU-02 | B86: INSTALACIÓN DE BASE PARA BANCO DE REGULADORES/BOOSTER HASTA 3 X 225KV | C86: W-10c | E86: ARANDELA DE PRESION P/TORNILLO 5/8'' | F86: Und. | G86: 60
A87: 1BREGU-02 | B87: INSTALACIÓN DE BASE PARA BANCO DE REGULADORES/BOOSTER HASTA 3 X 225KV | C87: W-9A | E87: ARANDELA CUADRADA 2X2'' PARA TORNILLO DE 1/2'' | F87: Und. | G87: 22
A88: 1BREGU-02 | B88: INSTALACIÓN DE BASE PARA BANCO DE REGULADORES/BOOSTER HASTA 3 X 225KV | C88: W-9C | E88: ARANDELA CUADRADA 3" X 3'' PARA TORNILLO DE 5/8"-3/4'' | F88: Und. | G88: 48
A89: 1BREGU-03 | B89: INSTALACIÓN DE BASE PARA BANCO DE REGULADORES/BOOSTER HASTA 3 X 500KV | C89: B-1F | E89: TORNILLO DE ESPACIAMIENTO CON 4 TUERCAS 5/8" X 18" | F89: Und. | G89: 16
A90: 1BREGU-03 | B90: INSTALACIÓN DE BASE PARA BANCO DE REGULADORES/BOOSTER HASTA 3 X 500KV | C90: B-2a | E90: TORNILLO DE MAQUINA ACERO GALVANIZADO CABEZA CUADRADA 1/2" X 10" | F90: Und. | G90: 26
A91: 1BREGU-03 | B91: INSTALACIÓN DE BASE PARA BANCO DE REGULADORES/BOOSTER HASTA 3 X 500KV | C91: B-2D | D91: 1002330 | E91: Tornillo Máq Cab Cuad 5/8"x12" | F91: Und. | G91: 14
A92: 1BREGU-03 | B92: INSTALACIÓN DE BASE PARA BANCO DE REGULADORES/BOOSTER HASTA 3 X 500KV | C92: B-7B | E92: Fleje diagonal de acero galv. 1-3/4" x 1-3/4" x 3/16"; longitud 84" | F92: Und. | G92: 12
A93: 1BREGU-03 | B93: INSTALACIÓN DE BASE PARA BANCO DE REGULADORES/BOOSTER HASTA 3 X 500KV | C93: C-19/A1A | E93: CRUCETA DE MADERA DE 3 3/4" X 4 3/4" X 10` | F93: Und. | G93: 36
A94: 1BREGU-03 | B94: INSTALACIÓN DE BASE PARA BANCO DE REGULADORES/BOOSTER HASTA 3 X 500KV | C94: W-10c | E94: ARANDELA DE PRESION P/TORNILLO 5/8'' | F94: Und. | G94: 66
A95: 1BREGU-03 | B95: INSTALACIÓN DE BASE PARA BANCO DE REGULADORES/BOOSTER HASTA 3 X 500KV | C95: W-9A | E95: ARANDELA CUADRADA 2X2'' PARA TORNILLO DE 1/2'' | F95: Und. | G95: 26
A96: 1BREGU-03 | B96: INSTALACIÓN DE BASE PARA BANCO DE REGULADORES/BOOSTER HASTA 3 X 500KV | C96: W-9C | E96: ARANDELA CUADRADA 3" X 3'' PARA TORNILLO DE 5/8"-3/4'' | F96: Und. | G96: 54
A97: 1BREGU-04 | B97: INSTALACIÓN DE BASE PARA BANCO DE REGULADORES/BOOSTER MAYOR A 3 X 500 KV | C97: B-1F | E97: TORNILLO DE ESPACIAMIENTO CON 4 TUERCAS 5/8" X 18" | F97: Und. | G97: 16
A98: 1BREGU-04 | B98: INSTALACIÓN DE BASE PARA BANCO DE REGULADORES/BOOSTER MAYOR A 3 X 500 KV | C98: B-2a | E98: TORNILLO DE MAQUINA ACERO GALVANIZADO CABEZA CUADRADA 1/2" X 10" | F98: Und. | G98: 26
A99: 1BREGU-04 | B99: INSTALACIÓN DE BASE PARA BANCO DE REGULADORES/BOOSTER MAYOR A 3 X 500 KV | C99: B-2D | D99: 1002330 | E99: Tornillo Máq Cab Cuad 5/8"x12" | F99: Und. | G99: 14
A100: 1BREGU-04 | B100: INSTALACIÓN DE BASE PARA BANCO DE REGULADORES/BOOSTER MAYOR A 3 X 500 KV | C100: B-7B | E100: Fleje diagonal de acero galv. 1-3/4" x 1-3/4" x 3/16"; longitud 84" | F100: Und. | G100: 12
A101: 1BREGU-04 | B101: INSTALACIÓN DE BASE PARA BANCO DE REGULADORES/BOOSTER MAYOR A 3 X 500 KV | C101: C-19/A1A | E101: CRUCETA DE MADERA DE 3 3/4" X 4 3/4" X 10` | F101: Und. | G101: 36
A102: 1BREGU-04 | B102: INSTALACIÓN DE BASE PARA BANCO DE REGULADORES/BOOSTER MAYOR A 3 X 500 KV | C102: W-10c | E102: ARANDELA DE PRESION P/TORNILLO 5/8'' | F102: Und. | G102: 66
A103: 1BREGU-04 | B103: INSTALACIÓN DE BASE PARA BANCO DE REGULADORES/BOOSTER MAYOR A 3 X 500 KV | C103: W-9A | E103: ARANDELA CUADRADA 2X2'' PARA TORNILLO DE 1/2'' | F103: Und. | G103: 26
A104: 1BREGU-04 | B104: INSTALACIÓN DE BASE PARA BANCO DE REGULADORES/BOOSTER MAYOR A 3 X 500 KV | C104: W-9C | E104: ARANDELA CUADRADA 3" X 3'' PARA TORNILLO DE 5/8"-3/4'' | F104: Und. | G104: 54
A105: 1CABT-03 | B105: INSTALACIÓN DE CAJA DERIVADORA AF (DE 16 A 30 SALIDAS) | C105: B-5C | D105: 1002312 | E105: Tornillo de maquina acero galvanizado cabeza hexagonal 1/2" x 3”. | F105: Und. | G105: 3
A106: 1CABT-03 | B106: INSTALACIÓN DE CAJA DERIVADORA AF (DE 16 A 30 SALIDAS) | C106: C-43C | D106: 1001791 | E106: CONECTOR DENTADO SIMPLE16-95/4-35 | F106: Und. | G106: 2
A107: 1CABT-03 | B107: INSTALACIÓN DE CAJA DERIVADORA AF (DE 16 A 30 SALIDAS) | C107: C-43D | D107: 1001789 | E107: Conector de perforación 1/0-300 MCM A CABLE AISL. #10-2 AWG | F107: Mts. | G107: 1
A108: 1CABT-03 | B108: INSTALACIÓN DE CAJA DERIVADORA AF (DE 16 A 30 SALIDAS) | C108: CAJ-0006 | D108: 1009926 | E108: CAJA DE DIST.DE POLIPROPILENO 3 B/RESORTE 10 TOMAS C/U | F108: Und. | G108: 1
A109: 1CABT-03 | B109: INSTALACIÓN DE CAJA DERIVADORA AF (DE 16 A 30 SALIDAS) | C109: CS-32D | D109: 1009755 | E109: Conductor concéntrico de Cu 3 x 4 AWG | F109: Mts. | G109: 1.5
A110: 1CABT-03 | B110: INSTALACIÓN DE CAJA DERIVADORA AF (DE 16 A 30 SALIDAS) | C110: E-2C | D110: 1002388 | E110: TUERCA DE OJO OVAL PARA TORNILO DE 1/2" | F110: Und. | G110: 1
A111: 1CABT-03 | B111: INSTALACIÓN DE CAJA DERIVADORA AF (DE 16 A 30 SALIDAS) | C111: S-4E | D111: 1009792 | E111: SOPORTE SIMPLE PARA CAJA DERIVADORA | F111: Und. | G111: 1
A112: 1CABT-03 | B112: INSTALACIÓN DE CAJA DERIVADORA AF (DE 16 A 30 SALIDAS) | C112: W-10b | D112: 1002201 | E112: Arandela de presión para tornillo de 1/2” | F112: Und. | G112: 3
A113: 1CABT-05 | B113: INSTALACIÓN DE DOS CAJAS DERIVADORAS EN UN MISMO PUNTO AF (30 SALIDAS) | C113: B-5C | D113: 1002312 | E113: Tornillo de maquina acero galvanizado cabeza hexagonal 1/2" x 3”. | F113: Und. | G113: 3
A114: 1CABT-05 | B114: INSTALACIÓN DE DOS CAJAS DERIVADORAS EN UN MISMO PUNTO AF (30 SALIDAS) | C114: C-43C | D114: 1001791 | E114: CONECTOR DENTADO SIMPLE16-95/4-35 | F114: Und. | G114: 2
A115: 1CABT-05 | B115: INSTALACIÓN DE DOS CAJAS DERIVADORAS EN UN MISMO PUNTO AF (30 SALIDAS) | C115: C-43D | D115: 1001789 | E115: Conector de perforación 1/0-300 MCM A CABLE AISL. #10-2 AWG | F115: Mts. | G115: 1
A116: 1CABT-05 | B116: INSTALACIÓN DE DOS CAJAS DERIVADORAS EN UN MISMO PUNTO AF (30 SALIDAS) | C116: CAJ-0006 | D116: 1009926 | E116: CAJA DE DIST.DE POLIPROPILENO 3 B/RESORTE 10 TOMAS C/U | F116: Und. | G116: 1
... A159: 1CONE-06 | B159: INSTALACIÓNALACION EMPALME AEREO MT (2/0 A 2/0) | C159: CM-01C | D159: 1000163 | E159: CONDUCTOR DESNUDO AAAC 2/0 | F159: Mts. | G159: 1.5
A160: 1CONE-08 | B160: INSTALACIÓNALACION EMPALME AEREO AISLADO PARA MT. | C160: C-3EA | E160: Cable de Cobre (URD) #4/0 al 33% Aislado para 15 kV | F160: Mts. | G160: 2
A161: 1CONE-08 | B161: INSTALACIÓNALACION EMPALME AEREO AISLADO PARA MT. | C161: C-6HC | D161: 1001757 | E161: CONECTOR TIPO CUÑA DE ALUMINO DE 4/0 DERIVACION 4/0 A 3/0 AWG | F161: Und. | G161: 2
A162: CO-URDA1 | B162: Instalación de URD 4/0 registro a registro en tubo pvc | C162: C-3EA | E162: Cable de Cobre (URD) #4/0 al 33% Aislado para 15 kV | F162: Mts. | G162: 1.05
A163: 1CO-URDB8 | B163: INSTALACIÓN METRO DE CONDUCTOR URD SOBRE TIERRA 4/0 | C163: C-3EA | D163: 1000098 | E163: Cable de Cobre (URD) #4/0 al 33% Aislado para 15 kV | F163: Mts. | G163: 1.05
A164: 1CO-URDB7 | B164: INSTALACIÓN METRO DE CONDUCTOR URD SOBRE TIERRA 2/0 | C164: C-3DC | D164: 1000097 | E164: Cable de Cobre (URD) #2/0 al 33% Aislado para 15 kV | F164: Mts. | G164: 1.05
A165: 1CO-URDB3 | B165: INSTALACIÓN METRO DE CONDUCTOR URD BAJO TIERRA 4/0 | C165: C-3EA | D165: 1000098 | E165: Cable de Cobre (URD) #4/0 al 33% Aislado para 15 kV | F165: Mts. | G165: 1.05
A166: 1CO-URDB2 | B166: INSTALACIÓN METRO DE CONDUCTOR URD BAJO TIERRA 2/0 | C166: C-3DC | D166: 1000097 | E166: Cable de Cobre (URD) #2/0 al 33% Aislado para 15 kV | F166: Mts. | G166: 1.05
...

Sheet ACTIVIADES
B1: ID | C1: Sap | D1: Descripción Materiales | E1: Cantidad | N1: Código | O1: Descripción de la actividad | P1: ACTIVIDAD2
B2: 1 | C2: 1002083 | D2: Cruceta Acer 3"x3"x1/4" Perf L 8'-0" | E2: 1 | N2: 1AC-103 | O2: INSTALACIÓN DE ACOMETIDA 120V RED ANTIFRAUDE CON BASE, DESDE LA CAJA DERIVADORA | P2: INSTALACIÓN
B3: 2 | C3: 1000091 | D3: Cable Cobre Estañado #2 AWG Desnudo | E3: 50 | N3: 1AC-104 | O3: INSTALACIÓN DE ACOMETIDA 240V RED ANTIFRAUDE CON BASE, DESDE LA CAJA DERIVADORA | P3: INSTALACIÓN
B4: 3 | C4: 1001241 | D4: Fleje Galv 1-7/32"x7/32"x28" | E4: 2 | H4: C-R1D | I4: 1001831 | J4: Conector Galv P/Varilla Tierra 1/2"-5/8" | N4: 1AC-105 | O4: INSTALACIÓN DE ACOMETIDA 120V DESDE RED ANTIFRAUDE CON SMCA CON DISPLAY, TOMACORRIENTE. | P4: INSTALACIÓN
B5: 4 | C5: 1001763 | D5: Conect Cuña P/ Cond 477 Cairo 4/0-3/0 | E5: 3 | N5: 1AC-106 | O5: INSTALACIÓN DE ACOMETIDA 240V DESDE RED ANTIFRAUDE CON SMCA CON DISPLAY, TOMACORRIENTE. | P5: INSTALACIÓN
B6: 6 | C6: 1001753 | D6: Conect Cu P/ Varilla Tierra 5/8"-1/2" | E6: 5 | N6: 1AL-BT | O6: INSTALACIÓNALACIÓN LÍNEA DE BT EN ALINEAMIENTO | P6: INSTALACIÓN
B7: 7 | C7: 1002283 | D7: Tornillo Esp 4 Tuerc Cuad 5/8"x12" | E7: 4 | N7: 1AP-101 | O7: Instalación Luminaria Con Soporte de 6' en Poste de MT & BT Hasta 400 W | P7: INSTALACIÓN
B8: 8 | C8: 1002308 | D8: Tornillo Máq Cab Cuad 1/2"x12" | E8: 2 | N8: 1AP-102 | O8: Instalación Luminaria Con Soporte de 12' en Poste de MT & BT Hasta 400 W | P8: INSTALACIÓN
B9: 9 | C9: 1002205 | D9: Arandela Presión P/ Tornillo 5/8'' | E9: 2 | N9: 1AP-108 | O9: INSTALACIÓN DE BALASTRO O INGNITOR (ARRANCADOR) | P9: INSTALACIÓN
B10: 10 | C10: 1002191 | D10: Arandela Cuad Pln 2x2"x1/4 Aguj 5/8-3/4" | E10: 2 | N10: 1AP-109 | O10: INSTALACION DE TABLERO O CAJA DE CONTROL DE CONJUNTO DE LUMINARIAS | P10: INSTALACIÓN
B11: 11 | C11: 1000553 | D11: Capacitor Monof T-P 100kVAR 19.92/34.5kV | E11: 3 | N11: 1AP-110 | O11: INSTALACIÓN DE CONTACTOR DE LUMINARIAS EN POSTE (RELAY) | P11: INSTALACIÓN
B12: 12 | C12: 1000614 | D12: Cut-Out 34.5kV 100A 170kV Pocelana | E12: 3 | N12: 1BCON-01 | O12: INSTALACIÓN SOPORTE DE BANCO DE CONDENSADORES. | P12: INSTALACIÓN
B13: 13 | C13: 1001268 | D13: Soporte Banco Capacitor Ac. Galv. 75-95 | E13: 1 | N13: 1BCON-02 | O13: INSTALACIÓN DE CONDENSADORES O CAPACITOR, NO INCLUYE PROTECCIÓN | P13: INSTALACIÓN
B14: 14 | C14: 1001319 | D14: Varilla Puesta Tierra de Cobre 5/8"x8' | E14: 5 | N14: 1BOM-01 | O14: Instalación de Bombillas Hasta 400 W | P14: INSTALACIÓN
B15: 15 | C15: 1000555 | D15: Capacitor Monof T-P 100kVAR 7.2/12.5kV | E15: 3 | N15: 1BOM-02 | O15: Instalación de Bombillas Mayor a 400 W | P15: INSTALACIÓN
N16: 1BREGU-01 | O16: INSTALACIÓN DE BASE PARA BANCO DE REGULADORES/BOOSTER HASTA 3 X 75KV | P16: INSTALACIÓN
N17: 1BREGU-02 | O17: INSTALACIÓN DE BASE PARA BANCO DE REGULADORES/BOOSTER HASTA 3 X 225KV | P17: INSTALACIÓN
N18: 1BREGU-03 | O18: INSTALACIÓN DE BASE PARA BANCO DE REGULADORES/BOOSTER HASTA 3 X 500KV | P18: INSTALACIÓN
N19: 1BREGU-04 | O19: INSTALACIÓN DE BASE PARA BANCO DE REGULADORES/BOOSTER MAYOR A 3 X 500 KV | P19: INSTALACIÓN
N20: 1CABT-03 | O20: INSTALACIÓN DE CAJA DERIVADORA AF (DE 16 A 30 SALIDAS) | P20: INSTALACIÓN
N21: 1CABT-04 | O21: INSTALACIÓN DE CAJA DERIVADORA AF (MAYOR DE 30 SALIDAS ) | P21: INSTALACIÓN
N22: 1CABT-05 | O22: INSTALACIÓN DE DOS CAJAS DERIVADORAS EN UN MISMO PUNTO AF (30 SALIDAS) | P22: INSTALACIÓN
N23: 1CABT-06 | O23: INSTALACIÓN DE DOS CAJAS DERIVADORAS EN UN MISMO PUNTO AF (40 SALIDAS) | P23: INSTALACIÓN
N24: 1CDA-MT | O24: INSTALACIÓNALACIÓN DE CRUCETA DOBLE DE ACERO PARA MEDIA TENSIÓN (CRUCETA DE 8') | P24: INSTALACIÓN
N25: 1CIRS-02 | O25: EMPALME DE URD 1Φ EN REGISTRO | P25: INSTALACIÓN
N26: 1CIRS-03 | O26: INSTALACIÓN TERMINAL EXTERIOR (CONO DE ALIVIO) MONOF. CONDUCTOR ≤ 1/0 BASE EN POSTE | P26: INSTALACIÓN
N27: 1CIRS-04 | O27: INSTALACIÓN TERMINAL EXTERIOR (CONO DE ALIVIO) MONOF. CONDUCTOR 2/0 BASE EN POSTE | P27: INSTALACIÓN
... N37: 1CIRS-14 | O37: INSTALACIÓN TERMINAL INTERIOR (CONO DE ALIVIO) MONOF. CONDUCTOR 559.5MCM | P37: INSTALACIÓN
E38: Código | F38: Descripción de la actividad | G38: UNIDAD | N38: 1CIRS-15 | O38: INSTALACIÓN TERMINAL EXTERIOR (CONO DE ALIVIO) TRIF. CONDUCTOR ≤ 1/0 BASE EN CRUCETA | P38: INSTALACIÓN
E39: 1MT-301/ST | F39: INSTALACIÓN MONTAJE 3Φ, EN ALINEAMIENTO CON ÁNGULO HASTA 5º, 34.5KV | G39: UND | N39: 1CIRS-16 | O39: INSTALACIÓN TERMINAL EXTERIOR (CONO DE ALIVIO) TRIF. CONDUCTOR 2/0 BASE EN CRUCETA | P39: INSTALACIÓN
E40: 1MT-302/ST | F40: INSTALACIÓN MONTAJE 3Φ, LÍNEA CON ÁNGULO DE 6º A 25º, 34.5KV | G40: UND | N40: 1CIRS-17 | O40: INSTALACIÓN TERMINAL EXTERIOR (CONO DE ALIVIO) TRIF. CONDUCTOR 4/0 BASE EN CRUCETA | P40: INSTALACIÓN
E41: 1MT-304-C | F41: INSTALACIÓN 3Ø, LINEA C/ANG 61º A 90º (VERTICAL), CON NEUTRO PRIMARIO | G41: UND | N41: 1CIRS-18 | O41: INSTALACIÓN TERMINAL EXTERIOR (CONO DE ALIVIO) TRIF. CONDUCTOR 465MCM BASE EN CRUCETA | P41: INSTALACIÓN
E42: 1MT-305-F | F42: INSTALACIÓN 3Ø, LINEA C/ANGULO DE 6º A 25º, CON NEUTRO PRIMARIO | G42: UND | N42: 1CIRS-19 | O42: INSTALACIÓN TERMINAL EXTERIOR (CONO DE ALIVIO) TRIF. CONDUCTOR 477MCM BASE EN CRUCETA | P42: INSTALACIÓN
E43: 1MT-307/ST | F43: INSTALACIÓN MONTAJE 3Φ, FIN DE LÍNEA HORIZONTAL, 34.5KV | G43: UND | N43: 1CIRS-20 | O43: INSTALACIÓN TERMINAL EXTERIOR (CONO DE ALIVIO) TRIF. CONDUCTOR 559.5MCM BASE EN CRUCETA | P43: INSTALACIÓN
E44: 1MT-307-F | F44: INSTALACIÓN 3Ø, LINEA C/ANG DE 26º A 60º , CON NEUTRO PRIMARIO (VERTICAL) | G44: UND | N44: 1CO-001 | O44: INSTALACIÓN TENDIDO DE LÍNEA 1/0 AL | P44: INSTALACIÓN
E45: 1MT-308-C | F45: INST 3Ø, ALINEAMIENTO C/DERIVACION 1Ø,C/NEUTRO PRI | G45: UND | N45: 1CO-002 | O45: INSTALACIÓN Tendido DE LÍNEA 2/0 AL | P45: INSTALACIÓN
E46: 1MT-308-F | F46: INST 3Ø, ALINEAM EN F CON DERIVACION 1Ø EN POSTE | G46: UND | N46: 1CO-003 | O46: INSTALACIÓN Tendido DE LÍNEA 4/0 AL | P46: INSTALACIÓN
E47: 1MT-309-C | F47: INST 3Ø,ALINEAM.C/DERIVACION 2Ø,C/NEUTRO PRIMARIO. | G47: UND | N47: 1CO-004 | O47: INSTALACIÓN Tendido DE LÍNEA 465.4 MCM AL | P47: INSTALACIÓN
E48: 1MT-309-F | F48: INSTALACION 3Ø, ALINEAMIENTO CON DERIVACION 2Ø | G48: UND | N48: 1CO-005 | O48: INSTALACIÓN DE TENDIDO DE CONDUCTOR TRIPLEX 2/0 NEUTRO 2/0 | P48: INSTALACIÓN
E49: 1MT-310-C | F49: INST 3Ø, ALINEAM. C/DERIVACION 3Ø,C/NEUTRO PRI | G49: UND | N49: 1CO-006 | O49: INSTALACIÓN DE TENDIDO DE CONDUCTOR TRIPLEX 4/0 NEUTRO 4/0 | P49: INSTALACIÓN
... E77: 1MTAF-316 | F77: INSTALACIÓN MONTAJE 3Φ, DOBLE TERMINAL (AF) | G77: UND | N77: 1EJUM-1D | O77: INSTALACIÓN EMPALME JUMPER MT EN POSTE DE 4/0 A 4/0 | P77: INSTALACIÓN
N78: 1EJUM-1E | O78: INSTALACIÓN EMPALME JUMPER MT EN POSTE DE 4/0 A 2/0 | P78: INSTALACIÓN
N79: 1EJUM-1F | O79: INSTALACIÓN EMPALME JUMPER MT EN POSTE DE 2/0 A 2/0 | P79: INSTALACIÓN
N80: 1EJUM-1J | O80: INSTALACIÓN EMPALME EN CABLE TRIPLEX 2/0. | P80: INSTALACIÓN
N81: 1EJUM-1M | O81: INSTALACIÓN EMPALME EN CABLE TRIPLEX 4/0 | P81: INSTALACIÓN
N82: 1ENPO-01 | O82: ENDEREZAR POSTE = < A 30 | P82: INSTALACIÓN
N83: 1ENPO-02 | O83: ENDEREZAR POSTE = A 35 | P83: INSTALACIÓN
N84: 1ENPO-03 | O84: ENDEREZAR POSTE = A 40 | P84: INSTALACIÓN
N85: 1ENPO-04 | O85: ENDEREZAR POSTE = > A 45 | P85: INSTALACIÓN
N86: 1EQTM-SE | O86: INSTALACIÓN Y CONEXIÓN DE EQUIPOS DE TELE MEDICION DE CIRCUITOS EN SUBESTACION | P86: INSTALACIÓN
N87: 1ETIQ-01 | O87: INSTALACIÓN ETIQUETA EN TRAFO TIPO POSTE | P87: INSTALACIÓN
N88: 1ETIQ-02 | O88: INSTALACIÓN ETIQUETA EN LUGARES DE SECCIONAMIENTO | P88: INSTALACIÓN
N89: 1EXCZ-01 | O89: EXCAVACIÓN TERRENO CAJUELA EN POSTE | P89: INSTALACIÓN
... N117: 1FUSI-03 | O117: INSTALACIÓN FUSIBLE DE EXPULSIÓN 5 A | P117: INSTALACIÓN
C118: UU_TT | D118: Descripción | E118: Código Material | F118: Codigo SAP | G118: Descripción_MAT | H118: Unidad | I118: Cantidad Materiales | N118: 1FUSI-04 | O118: INSTALACIÓN FUSIBLE DE EXPULSIÓN 7 A | P118: INSTALACIÓN
C119: 1MT-308-C | D119: INST 3Ø, ALINEAMIENTO C/DERIVACION 1Ø,C/NEUTRO PRI | N119: 1FUSI-05 | O119: INSTALACIÓN FUSIBLE DE EXPULSIÓN 10 A | P119: INSTALACIÓN
C120: 1MT-309-C | D120: INST 3Ø,ALINEAM.C/DERIVACION 2Ø,C/NEUTRO PRIMARIO. | N120: 1FUSI-06 | O120: INSTALACIÓN FUSIBLE DE EXPULSIÓN 15 A | P120: INSTALACIÓN
C121: 1MT-310-C | D121: INST 3Ø, ALINEAM. C/DERIVACION 3Ø,C/NEUTRO PRI | N121: 1FUSI-07 | O121: INSTALACIÓN FUSIBLE DE EXPULSIÓN 20 A TIPO K | P121: INSTALACIÓN
C122: 1MT-311-C | D122: INST 3Ø, FIN LINEA (VERT),C/DERIV. 1Ø,C/NEUTRO PRI | N122: 1FUSI-08 | O122: INSTALACIÓN FUSIBLE DE EXPULSIÓN 40 A TIPO K | P122: INSTALACIÓN
C123: 1MT-312-C | D123: INST 3Ø,FIN DE LINEA (VERTICAL), C/DERIVACION 2 Ø | N123: 1FUSI-09 | O123: INSTALACIÓN FUSIBLE DE EXPULSIÓN 65 A TIPO K | P123: INSTALACIÓN
C124: 1MT-313-C | D124: INST 3Ø, FIN LINEA (HORIZ)DERIV.ON 1Ø,C/NEUTRO PRI | N124: 1FV-MT1 | O124: INSTALACIÓN DE RETENIDA SENCILLO DE POSTE EN MEDIA TENSION | P124: INSTALACIÓN
C125: 1MT-314-C | D125: INST 3Ø,FIN LINEA HORIZ C/DERIV. 2Ø,C/NEUTRO PRI | N125: 1HA-100A | O125: INSTALACIÓN DE RETENIDA SENCILLA DE POSTE A TIERRA EN BAJA TENSION | P125: INSTALACIÓN
C126: 1MT-316-FV | D126: INST 3Ø DOBLE TERMINAL HORIZONTAL EN VOLADIZO | N126: 1HA-100B | O126: INSTALACIÓN DE RETENIDA SENCILLA DE POSTE A TIERRA EN MEDIA TENSION | P126: INSTALACIÓN
C127: 1MT-317-C | D127: INST 3Ø,DOBLE TERM.(VERT), C/DERIV. 3 Ø,C/NEUT PRI | N127: 1HA-105B | O127: INSTALACIÓN DE RETENIDA AÉREA SIMPLE EN MEDIA TENSION | P127: INSTALACIÓN
C128: 1MT-320-C | D128: INST 3Ø, ALINEAM.O C/ANG <= 5º EN VOLAD(V),C/N PRI | N128: 1HA-106 | O128: INSTALACIÓN DE VIENTO VERTICAL | P128: INSTALACIÓN
N129: 1HORP-01 | O129: ROMPER HORMIGONADO PARA APOYO <=> 3 KN | P129: INSTALACIÓN
N130: 1HORP-02 | O130: ROMPER HORMIGONADO PARA APOYO=> 5 KN | P130: INSTALACIÓN
N131: 1HORP-03 | O131: ROMPER HORMIGONADO PARA APOYO = < A 30' | P131: INSTALACIÓN
N132: 1HORP-04 | O132: ROMPER HORMIGONADO PARA APOYO DESDE 35' A 40' | P132: INSTALACIÓN
N133: 1HORP-05 | O133: ROMPER HORMIGONADO PARA APOYO = > A 45' | P133: INSTALACIÓN
N134: 1IMBT-01 | O134: INSTALACIÓN DE MEDIDOR 120V. | P134: INSTALACIÓN
N135: 1IMBT-02 | O135: INSTALACIÓN DE MEDIDOR 240V. | P135: INSTALACIÓN
N136: 1IM-BT120 | O136: INSTALACIÓN BASE PARA MEDIDOR BT 120V | P136: INSTALACIÓN
N137: 1IM-BT240 | O137: INSTALACIÓN BASE PARA MEDIDOR BT 240V | P137: INSTALACIÓN
N138: 1MAM-MT3A | O138: INSTALACIÓN DE MACRO MEDICIÓN 3Ø (25 - 50 / 5) | P138: INSTALACIÓN
N139: 1MAM-MT3B | O139: INSTALACIÓN DE MACRO MEDICIÓN 3Ø (75 - 150 / 5) | P139: INSTALACIÓN
N140: 1MAM-MT3D | O140: INSTALACIÓN DE MACRO MEDICIÓN 3Ø (100 - 200 / 5) | P140: INSTALACIÓN
... N1566: TR-1002 | O1566: TRANSFERENCIA TRANSFORMADOR TIPO POSTE | P1566: TRANSFERENCIA

Sheet TD_2
A3: Código Material | B3: Codigo SAP | C3: Descripción_MAT | D3: Unidad | E3: Suma de Cantidad Materiales
A4: 1000017 | B4: 1000017 | C4: Aislador T/ Esp PIN CL55-5 1" | D4: Und. | E4: 5
A5: 1000095 | B5: 1000095 | C5: CABLE COBRE URD #1/0 AISL P/ 15kV | D5: Mts. | E5: 2.1
A6: 1000411 | B6: 1000411 | C6: Bombilla Sodio Alta Pres 400W 100V HPS | D6: Und. | E6: 3
A7: 1000434 | B7: 1000434 | C7: Luminaria T/ Cobra HPS 400W | D7: Und. | E7: 3
A8: 1001223 | B8: 1001223 | C8: Espiga Acero 3/4"x7 3/4" | D8: Und. | E8: 2
A9: 1014667 | B9: 1014667 | C9: Luminaria T/Cobra LED 90W | D9: Und. | E9: 1
A10: A-5C | B10: 1002233 | C10: TARUGO-PERNO ACERADO RECUB. ZINC 5/8" X 3 3/4", PERNO DE 1/2" | D10: Und. | E10: 5
A11: A-5F | B11: 1002231 | C11: TARUGO-PERNOACERADO RECUB.ZINC LONG 13/4",PERNO DE 1/4" | D11: Und. | E11: 4
A12: A-7A | B12: 1002236 | C12: TARUGO PLAST. C/TORNILLO CABEZA HEXAGONAL NO.10-12, LONG. 1" DIAM. 9/32" | D12: Und. | E12: 16
A13: AC-11A | B13: 1000000 | C13: Aislad T/Carr 3x3-1/8 76x80mm 11/16 53-2 | D13: Und. | E13: 48
A14: AD-4B | B14: 1000807 | C14: Pararrayos de distribución de 9 kV; 12.47 kV. Estrella | D14: Und. | E14: 72
A15: AH-11A | B15: 1002077 | C15: CONO DE ANCLAR DE CONCRETO 18" X 6" X 8" | D15: Und. | E15: 7
A16: AMD-01 | B16: 1000444 | C16: Armario para medición industrial (con velo transparente) | D16: Und. | E16: 6
A17: AR-12A | B17: 1000004 | C17: AISLADOR DE PORCELANA TIPO POSTE 15 KV CLASE 57-1 | D17: Und. | E17: 166
A18: AR-13C | B18: 1000018 | C18: Aislador T/ Esp PIN CL56-3 1 3/8" 34.5kV | D18: Und. | E18: 13
A19: AS-1A | B19: 1013657 | C19: Aro Seguridad para Sellos tipo Pin | D19: Und. | E19: 2
A20: AS-22D | B20: 1000005 | C20: AISLADOR POLIMERICO TIPO SUSPENSION, 15 KV | D20: Und. | E20: 241
A21: B-10D | B21: 1001244 | C21: Fleje vertical de acero galv. 1-1/2" x 1-1/2" x 3/16"; longitud 54" | D21: Und. | E21: 9
... A51: C-25AB | B51: 1001956 | C51: TERMINAL PIN BIMETALICO PARA CONECTOR CUÑA, CAILBRE 465 MCM, 2 AGUJERO | D51: Und. | E51: 30
A52: C-25BB | B52: (en blanco) | C52: TERMINAL DE COMPRESION BIMETALICO PARA COND. #2 AWG, 1 AGUJERO | D52: Und. | E52: 3
A53: C-25D | B53: 1002008 | C53: TERMINAL DE OJO CERRADO COLOR AMARILLO 10-12 3M | D53: Und. | E53: 32
A54: C-26A | B54: 1001892 | C54: Grapa de fijación de cable a superficie plana 1/4" p/conductor Cu 2/0-#8 AWG | D54: Und. | E54: 33
A55: C-35K | B55: 1004752 | C55: CONECTOR ELÁSTICO TIPO CUÑA 4/0AWG # 2CU AWG | D55: Und. | E55: 48
A56: C-36A | B56: 1009347 | C56: Conector tipo cuña 465.4 MCM – 465.4 MCM | D56: Und. | E56: 14
A57: C-36C | B57: 1001763 | C57: Conector tipo cuña 465.4 MCM – 4/0AWG | D57: Und. | E57: 18
A58: C-36F | B58: 1001764 | C58: Conector elástico tipo cuña 465.4 MCM – 2 Cu AWG | D58: Und. | E58: 30
A59: C-39C | B59: 1009963 | C59: CONECTOR ELÁSTICO TIPO CUÑA 2/0 A #2 AL | D59: Und. | E59: 35
A60: C-39E | B60: 1004753 | C60: Conector elástico tipo cuña 2 – 2 CU AWG | D60: Und. | E60: 2
A61: C-3DC | B61: 1000097 | C61: Cable de Cobre (URD) #2/0 al 33% Aislado para 15 kV | D61: Mts. | E61: 2.1
A62: C-3EA | B62: 1000098 | C62: Cable de Cobre (URD) #4/0 al 33% Aislado para 15 kV | D62: Mts. | E62: 181.15
A63: C-40B | B63: 1001756 | C63: Conector elástico tipo cuña 465.4 MCM con estribo. | D63: Und. | E63: 2
A64: C-41A | B64: 1004345 | C64: Conector elástico tipo cuña de Cobre; varilla 5/8” – 2 AWG Cu. | D64: Und. | E64: 1
... A145: PMC-300-9 | B145: 1012341 | C145: Poste Metálico de Chapa 300 daN - 9 m (30’) | D145: Und. | E145: 6
A146: PMC-400-10 | B146: (en blanco) | C146: Poste Metálico de Chapa 400 daN - 10.5 | E146: 1
A147: PMC-500-10 | B147: 1004250 | C147: Poste Metálico de Chapa 500 daN- 10.5 m(34') | D147: Und. | E147: 3
A148: PMC-500-12 | B148: 1002101 | C148: Poste de Acero Galvanizado 40' 5.0 KN | D148: Und. | E148: 1
A149: PMC-600-12 | B149: 1002102 | C149: Poste Metálico de Chapa 600 daN - 12 m (40’) | D149: Und. | E149: 3
A150: PMC-600-14 | B150: 1002103 | C150: Poste de Acero Galvanizado 45' 6.0 KN | D150: Und. | E150: 1
A151: PMC-700-12 | B151: (en blanco) | C151: Poste Metálico de Chapa 700daN - 12 m (40’) | D151: Und. | E151: 2
A152: PMC-700-14 | B152: (en blanco) | C152: Poste de Acero Galvanizado 45' 7.0 KN | D152: Und. | E152: 1
A153: PMC-800-14 | B153: 1009796 | C153: Poste Metálico de Chapa 800 daN - 14 m (45’) | D153: Und. | E153: 2
A154: PZ-2C | B154: 1000816 | C154: Pinza de retención doble | D154: Und. | E154: 10
A155: R-1B | B155: 1001311 | C155: Varilla de anclaje de ojo doble, de 3/4" x 8' | D155: Und. | E155: 1
A156: R-1C | B156: 1011854 | C156: Varilla de anclaje de ojo simple, de 3/4" x 8' | D156: Und. | E156: 4
A157: R-2E | B157: 1001318 | C157: VARILLA DE PUESTA A TIERRA DE COBRE 1/2" X 6' | D157: Und. | E157: 2
A158: R-2F | B158: 1001319 | C158: VARILLA DE PUESTA A TIERRA DE COBRE 5/8" X 8' | D158: Und. | E158: 83
A159: R-5 | B159: 1001021 | C159: PROTECTOR PLASTICO PARA CABLE DE VIENTO | D159: Und. | E159: 9
A160: S-1C | B160: 1002347 | C160: TORNILLO PARA AISLADOR TIPO CARRETE 5/8" X 14". | D160: Und. | E160: 9
A161: S-1D | B161: 1002349 | C161: Tornillo P/ Aislador T/ Carrete 5/8"x16" | D161: Und. | E161: 16
A162: S-4 | B162: 1001271 | C162: SOPORTE DE DOBLE UNIDAD, DIST. ENTRE AGUJEROS 9" | D162: Und. | E162: 39
A163: S-4AA | B163: 1001287 | C163: SOPRTE EN POSTE, SIMPLE UNIDAD ALT. 10½", DIST A POSTE 12", ORIFICIO11/16" | D163: Und. | E163: 6
A164: S-4E | B164: 1009792 | C164: SOPORTE SIMPLE PARA CAJA DERIVADORA | D164: Und. | E164: 4
... A179: THP-004 | B179: 1009810 | C179: TAPON HEMBRA PVC PARA TUBO DE 4" | D179: Und. | E179: 1
A180: TMCMT-33H | B180: (en blanco) | C180: Módulos de Transformadores Combinados MT 3F a 12.47 KV; 25 - 50 /5A | D180: Und. | E180: 1
A181: TMCMT-33J" | B181: (en blanco) | C181: Módulos de Transformadores Combinados MT 3F a 12.47 KV; 300 - 600 /5A | D181: Und. | E181: 1
A182: TMCMT-33K | B182: (en blanco) | C182: Módulos de Transformadores Combinados MT 3F a 12.47 KV; 75 -150/5A | D182: Und. | E182: 1
A183: TMCMT-33L | B183: (en blanco) | C183: Módulos de Transformadores Combinados MT 3F a 12.47 KV; 100-200/5A | D183: Und. | E183: 1
A184: TMCMT-33N | B184: (en blanco) | C184: Módulos de Transformadores Combinados MT 3F a 12.47 KV; 200-400/5A | D184: Und. | E184: 1
A185: TPAF-AP12D | B185: 1009599 | C185: TRAF TIP POS MON 1BOR AUT ANT 12.47KV 75 | D185: Und. | E185: 2
A186: TUB-2A | B186: 1001308 | C186: Tubo flexible liquid tight de 1" galvanizado con protección PVC | D186: Mts. | E186: 16
A187: TUB-3G | B187: 1001293 | C187: TUBO ACERO GALVANIZADO 4" X 20' | D187: Und. | E187: 1
A188: TUB-4B | B188: 1002511 | C188: TUBO PVC SDR26 DE 1/2"X19' | D188: Und. | E188: 0.66
A189: W-10A | B189: 1002204 | C189: Arandela de presión para tornillo de 3/8” | D189: Und. | E189: 268
A190: W-10b | B190: 1002201 | C190: Arandela de presión para tornillo de 1/2” | D190: Und. | E190: 416
A191: W-10C | B191: 1002205 | C191: ARANDELA DE PRESION P/TORNILLO 5/8'' | D191: Und. | E191: 2229
A192: W-10D | B192: 1002203 | C192: Arandela de presión para tornillo de 3/4" | D192: Und. | E192: 154
A193: W-1J | B193: 1000898 | C193: SUJETADOR DE CABLE (TIGHT -WRAP) 15" | D193: Und. | E193: 24
A194: W-22A | B194: 1000145 | C194: CABLE DE COBRE MULTIPOLAR FLEXIBLE 7 X 12 AWG | D194: Mts. | E194: 42
A195: W-7A | B195: 1000050 | C195: Alambre de amarre #4 AWG solido de aluminio | D195: Mts. | E195: 328
A196: W-9A | B196: 1002183 | C196: ARANDELA CUADRADA 2X2'' PARA TORNILLO DE 1/2'' | D196: Und. | E196: 132
... A200: (en blanco) | B200: 10095100 | C200: Transf M 100kVA 7.2kV 120-240V CSP AF | D200: Und. | E200: 1
B201: (en blanco) | C201: Regulador Aut. Volt. 225KVA a 7.2 KV | D201: Und. | E201: 3
C202: Regulador Aut. Volt.500KVA a 7.2 KV | D202: Und. | E202: 3
C203: Regulador Aut. Volt.501KVA hasta 500KVA | D203: Und. | E203: 3
C204: TRANSFORMADOR MONOF. TIPO POSTE, 100KVA, 12.47 KV/120-240 | D204: Und. | E204: 5
C205: TRANSFORMADOR MONOF. TIPO POSTE, 37.5KVA, 12.47 KV/120-240 | D205: Und. | E205: 5
C206: TRANSFORMADOR MONOF. TIPO POSTE, 25KVA, 12.47 KV/120-240 | D206: Und. | E206: 5
C207: TRANSFORMADOR MONOF. TIPO POSTE, 15KVA, 12.47 KV/120-240 | D207: Und. | E207: 3
C208: TRANSFORMADOR MONOF. TIPO POSTE, 15KVA, 4.16 KV/120-240 | D208: Und. | E208: 5
C209: TRANSFORMADOR MONOF. TIPO POSTE, 75KVA, 4.16 KV/120-240 | D209: Und. | E209: 5
C210: TRANSFORMADOR MONOF. TIPO POSTE, 50KVA, 4.16 KV/120-240 | D210: Und. | E210: 5
C211: TRANSFORMADOR MONOF. TIPO POSTE, 25KVA, 4.16 KV/120-240 | D211: Und. | E211: 3
C212: Transf Monof 167KVA 19.2kv 120/240 V | D212: Und. | E212: 2
C213: Fusible de expulsión tipo D, 25A | D213: Und. | E213: 2
... C215: Transf Monof 300KVA 19.2kv 120/240 V | D215: Und. | E215: 2
A216: TPAF-AP12A | B216: (en blanco) | C216: Transformador tipo poste 1F CSP blindado 25 kVA; 120/240 V | D216: Und. | E216: 1
A217: I-1B | B217: 1001221 | C217: Espiga De Acero 3/4"X12 1/2"Para Cruceta De Madera | D217: Und. | E217: 14
A218: I2-D | B218: 1001232 | C218: Espiga Para Aislador En Cabeza De Poste De 24'' Long. Rosca 1-3/8''. | D218: Und. | E218: 1
A219: I-4C | B219: 1000018 | C219: Aislador T/ Esp PIN CL56-3 1 3/8" 34.5kV | D219: Und. | E219: 18
A220: B-1F | B220: 1002286 | C220: Tornillo De Espaciamiento,4 Tuercas Cuadradas, 5/8"X 18" | D220: Und. | E220: 96
A221: B-1B | B221: 1002282 | C221: Tornillos De Esp. 4 Tuercas Cuad.5/8" X 10" | D221: Und. | E221: 10
A222: C-6HA | B222: 1001759 | C222: Conector t cuña p/cond princ 4/0a1/0 deriv 2/0 a 2 | D222: Und. | E222: 3
A223: C-6L | B223: 1001752 | C223: Conector.De Comp. P/. Conductor De 500-4/0 A 500-4/0 Awg | D223: Und. | E223: 3
A224: I-4A | B224: 1000016 | C224: Aislador Tipo Espiga Clase 55-3 Orificio 1" | D224: Und. | E224: 6
A225: I-5d | B225: 1009910 | C225: Aislador Polimérico para 34.5 | D225: Und. | E225: 41
A226: B-1G | B226: 1002287 | C226: Tornillo Espac.4 Tuercas Cuad. 5/8"X20" | D226: Und. | E226: 56
A227: C-25B | B227: 1001975 | C227: Terminal Compr Cu P/ Cond #2 AWG | D227: Und. | E227: 2
A228: I-2B | B228: 1001230 | C228: Espiga Para Aislador En Cabeza De Poste 20" X 1" | D228: Und. | E228: 1
A229: URD-MAT-001 | B229: (en blanco) | C229: Conector compresión cobre (calibre según cable) | D229: Und. | E229: 1
...

Sheet BD
A3: ACTIVIDAD PRIMARIA | B3: UU_TT | C3: Descripción | D3: Código Material | E3: Codigo SAP | F3: Descripción_MAT | G3: Unidad | H3: Suma de Cantidad Materiales
A4: INSTALACION | B4: 1AC-103 | C4: INSTALACIÓN DE ACOMETIDA 120V RED ANTIFRAUDE CON BASE, DESDE LA CAJA DERIVADORA | D4: A-5C | E4: 1002233 | F4: TARUGO-PERNO ACERADO RECUB. ZINC 5/8" X 3 3/4", PERNO DE 1/2" | G4: Und. | H4: 1
A5: INSTALACION | B5: 1AC-103 | C5: INSTALACIÓN DE ACOMETIDA 120V RED ANTIFRAUDE CON BASE, DESDE LA CAJA DERIVADORA | D5: A-5F | E5: 1002231 | F5: TARUGO-PERNOACERADO RECUB.ZINC LONG 13/4",PERNO DE 1/4" | G5: Und. | H5: 2
A6: INSTALACION | B6: 1AC-103 | C6: INSTALACIÓN DE ACOMETIDA 120V RED ANTIFRAUDE CON BASE, DESDE LA CAJA DERIVADORA | D6: A-7A | E6: 1002236 | F6: TARUGO PLAST. C/TORNILLO CABEZA HEXAGONAL NO.10-12, LONG. 1" DIAM. 9/32" | G6: Und. | H6: 8
A7: INSTALACION | B7: 1AC-103 | C7: INSTALACIÓN DE ACOMETIDA 120V RED ANTIFRAUDE CON BASE, DESDE LA CAJA DERIVADORA | D7: AS-1A | E7: 1013657 | F7: Aro Seguridad para Sellos tipo Pin | G7: Und. | H7: 1
A8: INSTALACION | B8: 1AC-103 | C8: INSTALACIÓN DE ACOMETIDA 120V RED ANTIFRAUDE CON BASE, DESDE LA CAJA DERIVADORA | D8: BC-100 | E8: 1010780 | F8: Base circular de entrada de 1" para medidor socket FM 2S aluminio fundido | G8: Und. | H8: 1
A9: INSTALACION | B9: 1AC-103 | C9: INSTALACIÓN DE ACOMETIDA 120V RED ANTIFRAUDE CON BASE, DESDE LA CAJA DERIVADORA | D9: C-18BK | E9: 1014063 | F9: Abrazadera metálica tipo omega de 3/4" | G9: Und. | H9: 4
A10: INSTALACION | B10: 1AC-103 | C10: INSTALACIÓN DE ACOMETIDA 120V RED ANTIFRAUDE CON BASE, DESDE LA CAJA DERIVADORA | D10: CP-02A | E10: 1004213 | F10: Cable de acero cobreado desnudo #6 AWG; 3 hilos | G10: Mts. | H10: 2
A11: INSTALACION | B11: 1AC-103 | C11: INSTALACIÓN DE ACOMETIDA 120V RED ANTIFRAUDE CON BASE, DESDE LA CAJA DERIVADORA | D11: C-R1D | E11: 1001831 | F11: Conector Galv P/Varilla Tierra 1/2"-5/8" | G11: Und. | H11: 1
A12: INSTALACION | B12: 1AC-103 | C12: INSTALACIÓN DE ACOMETIDA 120V RED ANTIFRAUDE CON BASE, DESDE LA CAJA DERIVADORA | D12: CS-33A | E12: 1000100 | F12: CONDUCTOR CONCÉNTRICO DE ALUMINIO 2 X # 8 AWG | G12: Mts. | H12: 20
A13: INSTALACION | B13: 1AC-103 | C13: INSTALACIÓN DE ACOMETIDA 120V RED ANTIFRAUDE CON BASE, DESDE LA CAJA DERIVADORA | D13: DPS-25 | E13: 1000578 | F13: COLLAR DE AMARRE P/ UN HAZ DE ACOM. 25MM C/TARUGO | G13: Und. | H13: 4
A14: INSTALACION | B14: 1AC-103 | C14: INSTALACIÓN DE ACOMETIDA 120V RED ANTIFRAUDE CON BASE, DESDE LA CAJA DERIVADORA | D14: E-2A | E14: 1002390 | F14: TUERCA DE OJO OVAL PARA TORNILO DE 5/8" | G14: Und. | H14: 1
A15: INSTALACION | B15: 1AC-103 | C15: INSTALACIÓN DE ACOMETIDA 120V RED ANTIFRAUDE CON BASE, DESDE LA CAJA DERIVADORA | D15: MPLC-1A | E15: 1010783 | F15: MEDIDOR CL100,FM1S,120V,2H,MOD.COM.VIA PLC INCLUIDO | G15: Und. | H15: 1
... A58: INSTALACION | B58: 1AL-BT | C58: Instalación de Línea de Baja Tensión en Alineamiento | D58: W-9C | E58: 1002190 | F58: Arandela Cuad Pln 2 1/4"x2 1/4" 5/8-3/4" | G58: Und. | H58: 1
A59: INSTALACION | B59: 1AP-101 | C59: Instalación Luminaria Con Soporte de 6' en Poste de MT & BT Hasta 400 W | D59: 1000411 | E59: 1000411 | F59: Bombilla Sodio Alta Pres 400W 100V HPS | G59: Und. | H59: 1
A60: INSTALACION | B60: 1AP-101 | C60: Instalación Luminaria Con Soporte de 6' en Poste de MT & BT Hasta 400 W | D60: 1000434 | E60: 1000434 | F60: Luminaria T/ Cobra HPS 400W | G60: Und. | H60: 1
A61: INSTALACION | B61: 1AP-101 | C61: Instalación Luminaria Con Soporte de 6' en Poste de MT & BT Hasta 400 W | D61: BR-1A | E61: 1000413 | F61: Brazo de 6' para Luminaria de Alumbrado Público | G61: Und. | H61: 1
A62: INSTALACION | B62: 1AP-101 | C62: Instalación Luminaria Con Soporte de 6' en Poste de MT & BT Hasta 400 W | D62: CM-22D | E62: 1011853 | F62: Cable de control 3 conductores # 12 AWG | G62: Mts. | H62: 3.5
A63: INSTALACION | B63: 1AP-101 | C63: Instalación Luminaria Con Soporte de 6' en Poste de MT & BT Hasta 400 W | D63: F-5F | E63: 1000420 | F63: FOTOCELDA DE 105-305 VOLT. MULTIRANGO NA | G63: Und. | H63: 1
A64: INSTALACION | B64: 1AP-101 | C64: Instalación Luminaria Con Soporte de 6' en Poste de MT & BT Hasta 400 W | D64: W-10C | E64: 1002205 | F64: ARANDELA DE PRESION P/TORNILLO 5/8'' | G64: Und. | H64: 2
A65: INSTALACION | B65: 1AP-101 | C65: Instalación Luminaria Con Soporte de 6' en Poste de MT & BT Hasta 400 W | D65: W-9B | E65: 1002191 | F65: ARANDELA CUAD.2 1/4" X 2 1/4" ESP.3/16'' (TORN.5/8"-3/4") | G65: Und. | H65: 2
A66: INSTALACION | B66: 1AP-102 | C66: Instalación Luminaria Con Soporte de 12' en Poste de MT & BT Hasta 400 W | D66: 1000411 | E66: 1000411 | F66: Bombilla Sodio Alta Pres 400W 100V HPS | G66: Und. | H66: 1
A67: INSTALACION | B67: 1AP-102 | C67: Instalación Luminaria Con Soporte de 12' en Poste de MT & BT Hasta 400 W | D67: 1000434 | E67: 1000434 | F67: Luminaria T/ Cobra HPS 400W | G67: Und. | H67: 1
A68: INSTALACION | B68: 1AP-102 | C68: Instalación Luminaria Con Soporte de 12' en Poste de MT & BT Hasta 400 W | D68: BR-1A | E68: 1000413 | F68: Brazo de 6' para Luminaria de Alumbrado Público | G68: Und. | H68: 1
A69: INSTALACION | B69: 1AP-102 | C69: Instalación Luminaria Con Soporte de 12' en Poste de MT & BT Hasta 400 W | D69: CM-22D | E69: 1011853 | F69: Cable de control 3 conductores # 12 AWG | G69: Mts. | H69: 3.5
A70: INSTALACION | B70: 1AP-102 | C70: Instalación Luminaria Con Soporte de 12' en Poste de MT & BT Hasta 400 W | D70: F-5F | E70: 1000420 | F70: FOTOCELDA DE 105-305 VOLT. MULTIRANGO NA | G70: Und. | H70: 1
A71: INSTALACION | B71: 1AP-102 | C71: Instalación Luminaria Con Soporte de 12' en Poste de MT & BT Hasta 400 W | D71: W-10C | E71: 1002205 | F71: ARANDELA DE PRESION P/TORNILLO 5/8'' | G71: Und. | H71: 2
A72: INSTALACION | B72: 1AP-102 | C72: Instalación Luminaria Con Soporte de 12' en Poste de MT & BT Hasta 400 W | D72: W-9B | E72: 1002191 | F72: ARANDELA CUAD.2 1/4" X 2 1/4" ESP.3/16'' (TORN.5/8"-3/4") | G72: Und. | H72: 2
A73: INSTALACION | B73: 1BCON-01 | C73: INSTALACIÓN SOPORTE DE BANCO DE CONDENSADORES. | D73: 1000091 | E73: 1000091 | F73: Cable Cobre Estañado #2 AWG Desnudo | G73: Mts. | H73: 20
A74: INSTALACION | B74: 1BCON-01 | C74: INSTALACIÓN SOPORTE DE BANCO DE CONDENSADORES. | D74: 1000555 | E74: 1000555 | F74: Capacitor Monof T-P 100kVAR 7.2/12.5kV | G74: Und. | H74: 3
A75: INSTALACION | B75: 1BCON-01 | C75: INSTALACIÓN SOPORTE DE BANCO DE CONDENSADORES. | D75: 1001268 | E75: 1001268 | F75: Soporte Banco Capacitor Ac. Galv. 75-95 | G75: Und. | H75: 1
A76: INSTALACION | B76: 1BCON-01 | C76: INSTALACIÓN SOPORTE DE BANCO DE CONDENSADORES. | D76: AD-4B | E76: 1000807 | F76: Pararrayos de distribución de 9 kV; 12.47 kV. Estrella | G76: Und. | H76: 3
A77: INSTALACION | B77: 1BCON-01 | C77: INSTALACIÓN SOPORTE DE BANCO DE CONDENSADORES. | D77: B-2B | E77: 1002308 | F77: TORNILLO DE MAQUINA ACERO GALVANIZADO CABEZA CUADRADA 1/2" X 12". | G77: Und. | H77: 1
A78: INSTALACION | B78: 1BCON-01 | C78: INSTALACIÓN SOPORTE DE BANCO DE CONDENSADORES. | D78: B-4A | E78: 1001778 | F78: Conect Perno Part P/ Cabl No.2 al 2/0 Cu | G78: Und. | H78: 2
A79: INSTALACION | B79: 1BCON-01 | C79: INSTALACIÓN SOPORTE DE BANCO DE CONDENSADORES. | D79: B‐5A | E79: 1002325 | F79: Tornillo de máquina acero galvanizado cabeza hexagonal 3/8” x 2” | G79: Und. | H79: 2
A80: INSTALACION | B80: 1BCON-01 | C80: INSTALACIÓN SOPORTE DE BANCO DE CONDENSADORES. | D80: B-6A | E80: 1001241 | F80: Fleje plancha de acero galv. 1-7/32"x 7/32" x 28" | G80: Und. | H80: 2
A81: INSTALACION | B81: 1BCON-01 | C81: INSTALACIÓN SOPORTE DE BANCO DE CONDENSADORES. | D81: C-20D | E81: 1002083 | F81: Cruceta de acero galvanizado, perfil "L", de 3"x 3"x 1/4" x 8' | G81: Und. | H81: 1
A82: INSTALACION | B82: 1BCON-01 | C82: INSTALACIÓN SOPORTE DE BANCO DE CONDENSADORES. | D82: C-6HC | E82: 1001757 | F82: CONECTOR TIPO CUÑA DE ALUMINO DE 4/0 DERIVACION 4/0 A 3/0 AWG | G82: Und. | H82: 3
A83: INSTALACION | B83: 1BCON-01 | C83: INSTALACIÓN SOPORTE DE BANCO DE CONDENSADORES. | D83: C-R1D | E83: 1001831 | F83: Conector Galv P/Varilla Tierra 1/2"-5/8" | G83: Und. | H83: 3
A84: INSTALACION | B84: 1BCON-01 | C84: INSTALACIÓN SOPORTE DE BANCO DE CONDENSADORES. | D84: FU-12AB | E84: 1000627 | F84: Fusible 100A (10/24kV) 442mm | G84: Und. | H84: 3
A85: INSTALACION | B85: 1BCON-01 | C85: INSTALACIÓN SOPORTE DE BANCO DE CONDENSADORES. | D85: R-2F | E85: 1001319 | F85: VARILLA DE PUESTA A TIERRA DE COBRE 5/8" X 8' | G85: Und. | H85: 3
A86: INSTALACION | B86: 1BCON-01 | C86: INSTALACIÓN SOPORTE DE BANCO DE CONDENSADORES. | D86: S-4 | E86: 1001271 | F86: SOPORTE DE DOBLE UNIDAD, DIST. ENTRE AGUJEROS 9" | G86: Und. | H86: 3
A87: INSTALACION | B87: 1BCON-01 | C87: INSTALACIÓN SOPORTE DE BANCO DE CONDENSADORES. | D87: SF-11A | E87: 1000610 | F87: Cut-Out 100A 7.8/15kV 95kV BIL Porcelana | G87: Und. | H87: 3
A88: INSTALACION | B88: 1BCON-02 | C88: INSTALACIÓN DE CONDENSADORES O CAPACITOR, NO INCLUYE PROTECCIÓN | D88: 1000091 | E88: 1000091 | F88: Cable Cobre Estañado #2 AWG Desnudo | G88: Mts. | H88: 2
A89: INSTALACION | B89: 1BCON-02 | C89: INSTALACIÓN DE CONDENSADORES O CAPACITOR, NO INCLUYE PROTECCIÓN | D89: 1000555 | E89: 1000555 | F89: Capacitor Monof T-P 100kVAR 7.2/12.5kV | G89: Und. | H89: 1
A90: INSTALACION | B90: 1BCON-02 | C90: INSTALACIÓN DE CONDENSADORES O CAPACITOR, NO INCLUYE PROTECCIÓN | D90: 1001757 | E90: 1001268 | F90: Soporte Banco Capacitor Ac. Galv. 75-95 | G90: Und. | H90: 1
A91: INSTALACION | B91: 1BCON-02 | C91: INSTALACIÓN DE CONDENSADORES O CAPACITOR, NO INCLUYE PROTECCIÓN | D91: B-4A | E91: 1001778 | F91: Conect Perno Part P/ Cabl No.2 al 2/0 Cu | G91: Und. | H91: 1
A92: INSTALACION | B92: 1BCON-02 | C92: INSTALACIÓN DE CONDENSADORES O CAPACITOR, NO INCLUYE PROTECCIÓN | D92: C-6HC | E92: 1001757 | F92: CONECTOR TIPO CUÑA DE ALUMINO DE 4/0 DERIVACION 4/0 A 3/0 AWG | G92: Und. | H92: 1
A93: INSTALACION | B93: 1BCON-02 | C93: INSTALACIÓN DE CONDENSADORES O CAPACITOR, NO INCLUYE PROTECCIÓN | D93: C-R1D | E93: 1001831 | F93: Conector Galv P/Varilla Tierra 1/2"-5/8" | G93: Und. | H93: 1
A94: INSTALACION | B94: 1BCON-02 | C94: INSTALACIÓN DE CONDENSADORES O CAPACITOR, NO INCLUYE PROTECCIÓN | D94: R-2F | E94: 1001319 | F94: VARILLA DE PUESTA A TIERRA DE COBRE 5/8" X 8' | G94: Und. | H94: 1
A95: INSTALACION | B95: 1BREGU-01 | C95: INSTALACIÓN DE BASE PARA BANCO DE REGULADORES/BOOSTER HASTA 3 X 75KV | D95: B-1F | E95: 1002286 | F95: Tornillo De Espaciamiento,4 Tuercas Cuadradas, 5/8"X 18" | G95: Und. | H95: 12
A96: INSTALACION | B96: 1BREGU-01 | C96: INSTALACIÓN DE BASE PARA BANCO DE REGULADORES/BOOSTER HASTA 3 X 75KV | D96: B-2a | E96: 1002328 | F96: Tornillo De Maquina Cabeza Cuadrada 3/8"X 5" | G96: Und. | H96: 22
A97: INSTALACION | B97: 1BREGU-01 | C97: INSTALACIÓN DE BASE PARA BANCO DE REGULADORES/BOOSTER HASTA 3 X 75KV | D97: B-2D | E97: 1002329 | F97: Tornillo de máquina acero galvanizado cabeza cuadrada 5/8” x 10” | G97: Und. | H97: 12
A98: INSTALACION | B98: 1BREGU-01 | C98: INSTALACIÓN DE BASE PARA BANCO DE REGULADORES/BOOSTER HASTA 3 X 75KV | D98: B-7B | E98: 1001235 | F98: Fleje diagonal de acero galv. 1-3/4" x 1-3/4" x 3/16"; longitud 84" | G98: Und. | H98: 12
A99: INSTALACION | B99: 1BREGU-01 | C99: INSTALACIÓN DE BASE PARA BANCO DE REGULADORES/BOOSTER HASTA 3 X 75KV | D99: C-20/A1E | E99: 1004813 | F99: CRUCETA DE ACERO 3"X3" X1/4 , PERFIL L DE 10' | G99: Und. | H99: 32
A100: INSTALACION | B100: 1BREGU-01 | C100: INSTALACIÓN DE BASE PARA BANCO DE REGULADORES/BOOSTER HASTA 3 X 75KV | D100: W-10C | E100: 1002205 | F100: ARANDELA DE PRESION P/TORNILLO 5/8'' | G100: Und. | H100: 60
A101: INSTALACION | B101: 1BREGU-01 | C101: INSTALACIÓN DE BASE PARA BANCO DE REGULADORES/BOOSTER HASTA 3 X 75KV | D101: W-9A | E101: 1002183 | F101: ARANDELA CUADRADA 2X2'' PARA TORNILLO DE 1/2'' | G101: Und. | H101: 22
A102: INSTALACION | B102: 1BREGU-01 | C102: INSTALACIÓN DE BASE PARA BANCO DE REGULADORES/BOOSTER HASTA 3 X 75KV | D102: W-9C | E102: 1002190 | F102: Arandela Cuad Pln 2 1/4"x2 1/4" 5/8-3/4" | G102: Und. | H102: 48
... A166: INSTALACION | B166: 1CDA-MT | C166: Instalación de Cruceta Doble de Acero para Media Tensión (cruceta de 8') | D166: W-10C | E166: 1002205 | F166: ARANDELA DE PRESION P/TORNILLO 5/8'' | G166: Und. | H166: 18
A167: INSTALACION | B167: 1CIRS-02 | C167: EMPALME DE URD 1Φ EN REGISTRO | D167: URD-MAT-001 | E167: (en blanco) | F167: Conector compresión cobre (calibre según cable) | G167: Und. | H167: 1
A168: INSTALACION | B168: 1CIRS-02 | C168: EMPALME DE URD 1Φ EN REGISTRO | D168: URD-MAT-002 | E168: (en blanco) | F168: Kit empalme termocontráctil 1Φ 0.6/1kV | G168: Und. | H168: 1
A169: INSTALACION | B169: 1CIRS-02 | C169: EMPALME DE URD 1Φ EN REGISTRO | D169: URD-MAT-003 | E169: URD-MAT-003 | F169: Cinta autofusión (goma) | G169: Mts. | H169: 0.25
A170: INSTALACION | B170: 1CIRS-02 | C170: EMPALME DE URD 1Φ EN REGISTRO | D170: URD-MAT-004 | E170: URD-MAT-004 | F170: Cinta aislante PVC | G170: Mts. | H170: 0.25
A171: INSTALACION | B171: 1CIRS-02 | C171: EMPALME DE URD 1Φ EN REGISTRO | D171: URD-MAT-005 | E171: (en blanco) | F171: Limpiador dieléctrico | G171: Und. | H171: 0.05
A172: INSTALACION | B172: 1CIRS-02 | C172: EMPALME DE URD 1Φ EN REGISTRO | D172: URD-MAT-006 | E172: (en blanco) | F172: Lija abrasiva | G172: Und. | H172: 0.05
A173: INSTALACION | B173: 1CO-001 | C173: INSTALACIÓN TENDIDO DE LÍNEA 1/0 AL | D173: CM-01A | E173: 1000162 | F173: CONDUCTOR DESNUDO AAAC 1/0 | G173: Mts. | H173: 1.05
A174: INSTALACION | B174: 1CO-002 | C174: INSTALACIÓN Tendido DE LÍNEA 2/0 AL | D174: CM-01C | E174: 1000163 | F174: CONDUCTOR DESNUDO AAAC 2/0 | G174: Mts. | H174: 1.05
A175: INSTALACION | B175: 1CO-003 | C175: INSTALACI'ON CONDUCTOR TRIPLEX 2/0AL (BT) | D175: CB-11D | E175: 1000160 | F175: CONDUCTOR TRIPLEX DE ALUMINIO PARA BAJA TENSION # 2/0 | G175: Mts. | H175: 2.1
A176: INSTALACION | B176: 1CO-004 | C176: INSTALACIÓN Tendido DE LÍNEA 465.4 MCM AL | D176: CM-01G | E176: 1000165 | F176: Conductor AAAC 465.4 MCM (Cairo) | G176: Mts. | H176: 1.05
A177: INSTALACION | B177: 1CO-005 | C177: INSTALACIÓN DE TENDIDO DE CONDUCTOR TRIPLEX 2/0 NEUTRO 2/0 | D177: CB-11D | E177: 1000160 | F177: CONDUCTOR TRIPLEX DE ALUMINIO PARA BAJA TENSION # 2/0 | G177: Mts. | H177: 1.05
A178: INSTALACION | B178: 1CO-006 | C178: INSTALACIÓN DE TENDIDO DE CONDUCTOR TRIPLEX 4/0 NEUTRO 4/0 | D178: CB-11F | E178: 1000161 | F178: CABLE TRIPLEX AISLADO XLPE, COND DE FASE 4/0 AL, COND NEUTRO 4/0 AAAC | G178: Mts. | H178: 1.05
A179: INSTALACION | B179: 1COBT-01 | C179: INSTALACIÓN Tendido DE LÍNEA CONDUCTOR BT TRIPLEX. NO 2/ NO 4 | D179: CB-11C | E179: 1000159 | F179: CONDUCTOR TRIPLEX DE ALUMINIO PARA BAJA TENSION # 2 | G179: Mts. | H179: 1.05
A180: INSTALACION | B180: 1CONE-01 | C180: INSTALACIÓN EMPALME AEREO MT (465.4 A 465.4) | D180: C-6LA | E180: 1001762 | F180: CONECTOR TIPO CUÑA DE ALUMINIO DE 465 DERIVACIÓN 465 MCM | G180: Und. | H180: 1.5
A181: INSTALACION | B181: 1CONE-01 | C181: INSTALACIÓN EMPALME AEREO MT (465.4 A 465.4) | D181: CM-01G | E181: 1000165 | F181: Conductor AAAC 465.4 MCM (Cairo) | G181: Mts. | H181: 1.5
A182: INSTALACION | B182: 1CONE-02 | C182: INSTALACIÓN EMPALME AEREO MT (465.4 MCM A 4/0) | D182: C-36C | E182: 1001763 | F182: Conector tipo cuña 465.4 MCM – 4/0AWG | G182: Und. | H182: 1.5
A183: INSTALACION | B183: 1CONE-02 | C183: INSTALACIÓN EMPALME AEREO MT (465.4 MCM A 4/0) | D183: C-6HC | E183: 1001757 | F183: CONECTOR TIPO CUÑA DE ALUMINO DE 4/0 DERIVACION 4/0 A 3/0 AWG | G183: Und. | H183: 1
A184: INSTALACION | B184: 1CONE-02 | C184: INSTALACIÓN EMPALME AEREO MT (465.4 MCM A 4/0) | D184: CM-01E | E184: 1000164 | F184: Conductor AAAC 4/0 AWG (Alliance) | G184: Mts. | H184: 1.5
... A196: INSTALACION | B196: 1CONE-08 | C196: INSTALACIÓNALACION EMPALME AEREO AISLADO PARA MT. | D196: C-6HC | E196: 1001757 | F196: CONECTOR TIPO CUÑA DE ALUMINO DE 4/0 DERIVACION 4/0 A 3/0 AWG | G196: Und. | H196: 2
A197: INSTALACION | B197: 1CO-URDB1 | C197: INSTALACIÓN METRO DE CONDUCTOR URD BAJO TIERRA ≤ 1/0 | D197: 1000095 | E197: 1000095 | F197: CABLE COBRE URD #1/0 AISL P/ 15kV | G197: Mts. | H197: 1.05
A198: INSTALACION | B198: 1CO-URDB12 | C198: INSTALACIÓN METRO DE CONDUCTOR URD SOBRE TIERRA ≤ 1/0 | D198: 1000095 | E198: 1000095 | F198: CABLE COBRE URD #1/0 AISL P/ 15kV | G198: Mts. | H198: 1.05
A199: INSTALACION | B199: 1CO-URDB2 | C199: INSTALACIÓN METRO DE CONDUCTOR URD BAJO TIERRA 2/0 | D199: C-3DC | E199: 1000097 | F199: Cable de Cobre (URD) #2/0 al 33% Aislado para 15 kV | G199: Mts. | H199: 1.05
A200: INSTALACION | B200: 1CO-URDB3 | C200: INSTALACIÓN METRO DE CONDUCTOR URD BAJO TIERRA 4/0 | D200: C-3EA | E200: 1000098 | F200: Cable de Cobre (URD) #4/0 al 33% Aislado para 15 kV | G200: Mts. | H200: 1.05
A201: INSTALACION | B201: 1CO-URDB7 | C201: INSTALACIÓN METRO DE CONDUCTOR URD SOBRE TIERRA 2/0 | D201: C-3DC | E201: 1000097 | F201: Cable de Cobre (URD) #2/0 al 33% Aislado para 15 kV | G201: Mts. | H201: 1.05
A202: INSTALACION | B202: 1CO-URDB8 | C202: INSTALACIÓN METRO DE CONDUCTOR URD SOBRE TIERRA 4/0 | D202: C-3EA | E202: 1000098 | F202: Cable de Cobre (URD) #4/0 al 33% Aislado para 15 kV | G202: Mts. | H202: 1.05
A203: INSTALACION | B203: 1CSA-MT | C203: Instalación de Cruceta simple de Acero para Media Tensión (cruceta de 8') | D203: B-2B | E203: 1002308 | F203: TORNILLO DE MAQUINA ACERO GALVANIZADO CABEZA CUADRADA 1/2" X 12". | G203: Und. | H203: 1
A204: INSTALACION | B204: 1CSA-MT | C204: Instalación de Cruceta simple de Acero para Media Tensión (cruceta de 8') | D204: B-2D | E204: 1002329 | F204: Tornillo de máquina acero galvanizado cabeza cuadrada 5/8” x 10” | G204: Und. | H204: 1
A205: INSTALACION | B205: 1CSA-MT | C205: Instalación de Cruceta simple de Acero para Media Tensión (cruceta de 8') | D205: B-5A | E205: 1002325 | F205: Tornillo de máquina acero galvanizado cabeza hexagonal 3/8” x 2” | G205: Und. | H205: 2
A206: INSTALACION | B206: 1CSA-MT | C206: Instalación de Cruceta simple de Acero para Media Tensión (cruceta de 8') | D206: B-6A | E206: 1001241 | F206: Fleje plancha de acero galv. 1-7/32"x 7/32" x 28" | G206: Und. | H206: 2
A207: INSTALACION | B207: 1CSA-MT | C207: Instalación de Cruceta simple de Acero para Media Tensión (cruceta de 8') | D207: C-20D | E207: 1002083 | F207: Cruceta de acero galvanizado, perfil "L", de 3"x 3"x 1/4" x 8' | G207: Und. | H207: 1
A208: INSTALACION | B208: 1CSA-MT | C208: Instalación de Cruceta simple de Acero para Media Tensión (cruceta de 8') | D208: E-4 | E208: 1004830 | F208: Tuerca cuadrada acero galvanizado para tornillo 5/8” | G208: Und. | H208: 1
A209: INSTALACION | B209: 1CSA-MT | C209: Instalación de Cruceta simple de Acero para Media Tensión (cruceta de 8') | D209: GCT-ST1 | E209: 1009789 | F209: GRAPA DE CONEXIÓN DOBLE CABLE DE TIERRA SIN TORNILLO | G209: Und. | H209: 1
A210: INSTALACION | B210: 1CSA-MT | C210: Instalación de Cruceta simple de Acero para Media Tensión (cruceta de 8') | D210: W-10A | E210: 1002204 | F210: Arandela de presión para tornillo de 3/8” | G210: Und. | H210: 2
... A337: INSTALACION | B337: 1HA-100B | C337: Instalación de Retenida sencilla de poste a tierra en Media Tension | D337: W-9D | E337: 1002185 | F337: Arandela cuadrada plana de 3” x 3” para tornillo de 3/4" | G337: Und. | H337: 1
A338: INSTALACION | B338: 1HA-105B | C338: Instalación de Retenida aérea simple en Media Tension | D338: 1011855 | E338: 1011855 | F338: Tornillo Maquina Cabeza Hex. 5/8" X 3" | G338: Und. | H338: 1
A339: INSTALACION | B339: 1HA-105B | C339: Instalación de Retenida aérea simple en Media Tension | D339: CV-01C | E339: 1000130 | F339: CABLE DE VIENTO 7/16'' 76 KN | G339: Mts. | H339: 20
A340: INSTALACION | B340: 1HA-105B | C340: Instalación de Retenida aérea simple en Media Tension | D340: E-1B | E340: 1002398 | F340: TUERCA OJO CON GUARDACABO RECTO 5/8" 55.6 KN | G340: Und. | H340: 1
A341: INSTALACION | B341: 1HA-105B | C341: Instalación de Retenida aérea simple en Media Tension | D341: G-1B | E341: 1002020 | F341: TERMINAL PREFORMADO 7/16" | G341: Und. | H341: 2
A342: INSTALACION | B342: 1HA-105B | C342: Instalación de Retenida aérea simple en Media Tension | D342: G-2A | E342: 1002218 | F342: Tornillo guardacabo recto 5/8" x 12” | G342: Und. | H342: 1
A343: INSTALACION | B343: 1HA-105B | C343: Instalación de Retenida aérea simple en Media Tension | D343: W-10C | E343: 1002205 | F343: ARANDELA DE PRESION P/TORNILLO 5/8'' | G343: Und. | H343: 1
A344: INSTALACION | B344: 1HA-105B | C344: Instalación de Retenida aérea simple en Media Tension | D344: W-9C | E344: 1002190 | F344: Arandela Cuad Pln 2 1/4"x2 1/4" 5/8-3/4" | G344: Und. | H344: 1
...

Sheet UUTT2
A1: ACTIVIDAD PRIMARIA | B1: UU_TT | C1: Descripción | D1: Código Material | E1: Codigo SAP | F1: Descripción_MAT | G1: Unidad | H1: Cantidad Materiales
A2: INSTALACION | B2: 1AC-103 | C2: INSTALACIÓN DE ACOMETIDA 120V RED ANTIFRAUDE CON BASE, DESDE LA CAJA DERIVADORA | D2: A-5C | E2: 1002233 | F2: TARUGO-PERNO ACERADO RECUB. ZINC 5/8" X 3 3/4", PERNO DE 1/2" | G2: Und. | H2: 1
A3: INSTALACION | B3: 1AC-103 | C3: INSTALACIÓN DE ACOMETIDA 120V RED ANTIFRAUDE CON BASE, DESDE LA CAJA DERIVADORA | D3: A-5F | E3: 1002231 | F3: TARUGO-PERNOACERADO RECUB.ZINC LONG 13/4",PERNO DE 1/4" | G3: Und. | H3: 2
A4: INSTALACION | B4: 1AC-103 | C4: INSTALACIÓN DE ACOMETIDA 120V RED ANTIFRAUDE CON BASE, DESDE LA CAJA DERIVADORA | D4: A-7A | E4: 1002236 | F4: TARUGO PLAST. C/TORNILLO CABEZA HEXAGONAL NO.10-12, LONG. 1" DIAM. 9/32" | G4: Und. | H4: 8
A5: INSTALACION | B5: 1AC-103 | C5: INSTALACIÓN DE ACOMETIDA 120V RED ANTIFRAUDE CON BASE, DESDE LA CAJA DERIVADORA | D5: AS-1A | E5: 1013657 | F5: Aro Seguridad para Sellos tipo Pin | G5: Und. | H5: 1
A6: INSTALACION | B6: 1AC-103 | C6: INSTALACIÓN DE ACOMETIDA 120V RED ANTIFRAUDE CON BASE, DESDE LA CAJA DERIVADORA | D6: BC-100 | E6: 1010780 | F6: Base circular de entrada de 1" para medidor socket FM 2S aluminio fundido | G6: Und. | H6: 1
A7: INSTALACION | B7: 1AC-103 | C7: INSTALACIÓN DE ACOMETIDA 120V RED ANTIFRAUDE CON BASE, DESDE LA CAJA DERIVADORA | D7: C-18BK | E7: 1014063 | F7: Abrazadera metálica tipo omega de 3/4" | G7: Und. | H7: 4
A8: INSTALACION | B8: 1AC-103 | C8: INSTALACIÓN DE ACOMETIDA 120V RED ANTIFRAUDE CON BASE, DESDE LA CAJA DERIVADORA | D8: CP-02A | E8: 1004213 | F8: Cable de acero cobreado desnudo #6 AWG; 3 hilos | G8: Mts. | H8: 2
A9: INSTALACION | B9: 1AC-103 | C9: INSTALACIÓN DE ACOMETIDA 120V RED ANTIFRAUDE CON BASE, DESDE LA CAJA DERIVADORA | D9: C-R1D | E9: 1001831 | F9: Conector Galv P/Varilla Tierra 1/2"-5/8" | G9: Und. | H9: 1
A10: INSTALACION | B10: 1AC-103 | C10: INSTALACIÓN DE ACOMETIDA 120V RED ANTIFRAUDE CON BASE, DESDE LA CAJA DERIVADORA | D10: CS-33A | E10: 1000100 | F10: CONDUCTOR CONCÉNTRICO DE ALUMINIO 2 X # 8 AWG | G10: Mts. | H10: 20
A11: INSTALACION | B11: 1AC-103 | C11: INSTALACIÓN DE ACOMETIDA 120V RED ANTIFRAUDE CON BASE, DESDE LA CAJA DERIVADORA | D11: DPS-25 | E11: 1000578 | F11: COLLAR DE AMARRE P/ UN HAZ DE ACOM. 25MM C/TARUGO | G11: Und. | H11: 4
A12: INSTALACION | B12: 1AC-103 | C12: INSTALACIÓN DE ACOMETIDA 120V RED ANTIFRAUDE CON BASE, DESDE LA CAJA DERIVADORA | D12: E-2A | E12: 1002390 | F12: TUERCA DE OJO OVAL PARA TORNILO DE 5/8" | G12: Und. | H12: 1
A13: INSTALACION | B13: 1AC-103 | C13: INSTALACIÓN DE ACOMETIDA 120V RED ANTIFRAUDE CON BASE, DESDE LA CAJA DERIVADORA | D13: MPLC-1A | E13: 1010783 | F13: MEDIDOR CL100,FM1S,120V,2H,MOD.COM.VIA PLC INCLUIDO | G13: Und. | H13: 1
... A56: INSTALACION | B56: 1AL-BT | C56: Instalación de Línea de Baja Tensión en Alineamiento | D56: W-9C | E56: 1002190 | F56: Arandela Cuad Pln 2 1/4"x2 1/4" 5/8-3/4" | G56: Und. | H56: 1
A57: INSTALACION | B57: 1AP-101 | C57: Instalación Luminaria Con Soporte de 6' en Poste de MT & BT Hasta 400 W | D57: 1000411 | E57: 1000411 | F57: Bombilla Sodio Alta Pres 400W 100V HPS | G57: Und. | H57: 1
A58: INSTALACION | B58: 1AP-101 | C58: Instalación Luminaria Con Soporte de 6' en Poste de MT & BT Hasta 400 W | D58: 1000434 | E58: 1000434 | F58: Luminaria T/ Cobra HPS 400W | G58: Und. | H58: 1
A59: INSTALACION | B59: 1AP-101 | C59: Instalación Luminaria Con Soporte de 6' en Poste de MT & BT Hasta 400 W | D59: BR-1A | E59: 1000413 | F59: Brazo de 6' para Luminaria de Alumbrado Público | G59: Und. | H59: 1
A60: INSTALACION | B60: 1AP-101 | C60: Instalación Luminaria Con Soporte de 6' en Poste de MT & BT Hasta 400 W | D60: CM-22D | E60: 1011853 | F60: Cable de control 3 conductores # 12 AWG | G60: Mts. | H60: 3.5
A61: INSTALACION | B61: 1AP-101 | C61: Instalación Luminaria Con Soporte de 6' en Poste de MT & BT Hasta 400 W | D61: F-5F | E61: 1000420 | F61: FOTOCELDA DE 105-305 VOLT. MULTIRANGO NA | G61: Und. | H61: 1
A62: INSTALACION | B62: 1AP-101 | C62: Instalación Luminaria Con Soporte de 6' en Poste de MT & BT Hasta 400 W | D62: W-10C | E62: 1002205 | F62: Arandela Presión P/ Tornillo 5/8'' | G62: Und. | H62: 2
A63: INSTALACION | B63: 1AP-101 | C63: Instalación Luminaria Con Soporte de 6' en Poste de MT & BT Hasta 400 W | D63: W-9B | E63: 1002191 | F63: ARANDELA CUAD.2 1/4" X 2 1/4" ESP.3/16'' (TORN.5/8"-3/4") | G63: Und. | H63: 2
A64: INSTALACION | B64: 1AP-102 | C64: Instalación Luminaria Con Soporte de 12' en Poste de MT & BT Hasta 400 W | D64: 1000411 | E64: 1000411 | F64: Bombilla Sodio Alta Pres 400W 100V HPS | G64: Und. | H64: 1
A65: INSTALACION | B65: 1AP-102 | C65: Instalación Luminaria Con Soporte de 12' en Poste de MT & BT Hasta 400 W | D65: 1000434 | E65: 1000434 | F65: Luminaria T/ Cobra HPS 400W | G65: Und. | H65: 1
A66: INSTALACION | B66: 1AP-102 | C66: Instalación Luminaria Con Soporte de 12' en Poste de MT & BT Hasta 400 W | D66: BR-1A | E66: 1000413 | F66: Brazo de 6' para Luminaria de Alumbrado Público | G66: Und. | H66: 1
A67: INSTALACION | B67: 1AP-102 | C67: Instalación Luminaria Con Soporte de 12' en Poste de MT & BT Hasta 400 W | D67: CM-22D | E67: 1011853 | F67: Cable de control 3 conductores # 12 AWG | G67: Mts. | H67: 3.5
A68: INSTALACION | B68: 1AP-102 | C68: Instalación Luminaria Con Soporte de 12' en Poste de MT & BT Hasta 400 W | D68: F-5F | E68: 1000420 | F68: FOTOCELDA DE 105-305 VOLT. MULTIRANGO NA | G68: Und. | H68: 1
A69: INSTALACION | B69: 1AP-102 | C69: Instalación Luminaria Con Soporte de 12' en Poste de MT & BT Hasta 400 W | D69: W-10C | E69: 1002205 | F69: Arandela Presión P/ Tornillo 5/8'' | G69: Und. | H69: 2
A70: INSTALACION | B70: 1AP-102 | C70: Instalación Luminaria Con Soporte de 12' en Poste de MT & BT Hasta 400 W | D70: W-9B | E70: 1002191 | F70: ARANDELA CUAD.2 1/4" X 2 1/4" ESP.3/16'' (TORN.5/8"-3/4") | G70: Und. | H70: 2
A71: INSTALACION | B71: 1BCON-01 | C71: INSTALACIÓN SOPORTE DE BANCO DE CONDENSADORES. | D71: 1000091 | E71: 1000091 | F71: Cable Cobre Estañado #2 AWG Desnudo | G71: Mts. | H71: 20
A72: INSTALACION | B72: 1BCON-01 | C72: INSTALACIÓN SOPORTE DE BANCO DE CONDENSADORES. | D72: 1000555 | E72: 1000555 | F72: Capacitor Monof T-P 100kVAR 7.2/12.5kV | G72: Und. | H72: 3
A73: INSTALACION | B73: 1BCON-01 | C73: INSTALACIÓN SOPORTE DE BANCO DE CONDENSADORES. | D73: 1001268 | E73: 1001268 | F73: Soporte Banco Capacitor Ac. Galv. 75-95 | G73: Und. | H73: 1
A74: INSTALACION | B74: 1BCON-01 | C74: INSTALACIÓN SOPORTE DE BANCO DE CONDENSADORES. | D74: AD-4B | E74: 1000807 | F74: Pararrayos de distribución de 9 kV; 12.47 kV. Estrella | G74: Und. | H74: 3
A75: INSTALACION | B75: 1BCON-01 | C75: INSTALACIÓN SOPORTE DE BANCO DE CONDENSADORES. | D75: B-2B | E75: 1002308 | F75: Tornillo Máq Cab Cuad 1/2"x12" | G75: Und. | H75: 1
A76: INSTALACION | B76: 1BCON-01 | C76: INSTALACIÓN SOPORTE DE BANCO DE CONDENSADORES. | D76: B-4A | E76: 1001778 | F76: Conect Perno Part P/ Cabl No.2 al 2/0 Cu | G76: Und. | H76: 2
A77: INSTALACION | B77: 1BCON-01 | C77: INSTALACIÓN SOPORTE DE BANCO DE CONDENSADORES. | D77: B‐5A | E77: 1002325 | F77: Tornillo Máq Cab Cuad 3/8"x2" | G77: Und. | H77: 2
A78: INSTALACION | B78: 1BCON-01 | C78: INSTALACIÓN SOPORTE DE BANCO DE CONDENSADORES. | D78: B-6A | E78: 1001241 | F78: Fleje Plancha Acero 1 1/4x1/4"x28" | G78: Und. | H78: 2
A79: INSTALACION | B79: 1BCON-01 | C79: INSTALACIÓN SOPORTE DE BANCO DE CONDENSADORES. | D79: C-20D | E79: 1002083 | F79: Cruceta Acer 3"x3"x1/4" Perf L 8'-0" | G79: Und. | H79: 1
A80: INSTALACION | B80: 1BCON-01 | C80: INSTALACIÓN SOPORTE DE BANCO DE CONDENSADORES. | D80: C-6HC | E80: 1001757 | F80: CONECTOR TIPO CUÑA DE ALUMINO DE 4/0 DERIVACION 4/0 A 3/0 AWG | G80: Und. | H80: 3
A81: INSTALACION | B81: 1BCON-01 | C81: INSTALACIÓN SOPORTE DE BANCO DE CONDENSADORES. | D81: C-R1D | E81: 1001831 | F81: Conector Galv P/Varilla Tierra 1/2"-5/8" | G81: Und. | H81: 3
A82: INSTALACION | B82: 1BCON-01 | C82: INSTALACIÓN SOPORTE DE BANCO DE CONDENSADORES. | D82: FU-12AB | E82: 1000627 | F82: Fusible 100A (10/24kV) 442mm | G82: Und. | H82: 3
A83: INSTALACION | B83: 1BCON-01 | C83: INSTALACIÓN SOPORTE DE BANCO DE CONDENSADORES. | D83: R-2F | E83: 1001319 | F83: VARILLA DE PUESTA A TIERRA DE COBRE 5/8" X 8' | G83: Und. | H83: 3
A84: INSTALACION | B84: 1BCON-01 | C84: INSTALACIÓN SOPORTE DE BANCO DE CONDENSADORES. | D84: S-4 | E84: 1001271 | F84: SOPORTE DE DOBLE UNIDAD, DIST. ENTRE AGUJEROS 9" | G84: Und. | H84: 3
A85: INSTALACION | B85: 1BCON-01 | C85: INSTALACIÓN SOPORTE DE BANCO DE CONDENSADORES. | D85: SF-11A | E85: 1000610 | F85: Cut-Out 100A 7.8/15kV 95kV BIL Porcelana | G85: Und. | H85: 3
A86: INSTALACION | B86: 1BCON-02 | C86: INSTALACIÓN DE CONDENSADORES O CAPACITOR, NO INCLUYE PROTECCIÓN | D86: 1000091 | E86: 1000091 | F86: Cable Cobre Estañado #2 AWG Desnudo | G86: Mts. | H86: 2
A87: INSTALACION | B87: 1BCON-02 | C87: INSTALACIÓN DE CONDENSADORES O CAPACITOR, NO INCLUYE PROTECCIÓN | D87: 1000555 | E87: 1000555 | F87: Capacitor Monof T-P 100kVAR 7.2/12.5kV | G87: Und. | H87: 1
A88: INSTALACION | B88: 1BCON-02 | C88: INSTALACIÓN DE CONDENSADORES O CAPACITOR, NO INCLUYE PROTECCIÓN | D88: 1001757 | E88: 1001268 | F88: Soporte Banco Capacitor Ac. Galv. 75-95 | G88: Und. | H88: 1
A89: INSTALACION | B89: 1BCON-02 | C89: INSTALACIÓN DE CONDENSADORES O CAPACITOR, NO INCLUYE PROTECCIÓN | D89: B-4A | E89: 1001778 | F89: Conect Perno Part P/ Cabl No.2 al 2/0 Cu | G89: Und. | H89: 1
A90: INSTALACION | B90: 1BCON-02 | C90: INSTALACIÓN DE CONDENSADORES O CAPACITOR, NO INCLUYE PROTECCIÓN | D90: C-6HC | E90: 1001757 | F90: CONECTOR TIPO CUÑA DE ALUMINO DE 4/0 DERIVACION 4/0 A 3/0 AWG | G90: Und. | H90: 1
A91: INSTALACION | B91: 1BCON-02 | C91: INSTALACIÓN DE CONDENSADORES O CAPACITOR, NO INCLUYE PROTECCIÓN | D91: C-R1D | E91: 1001831 | F91: Conector Galv P/Varilla Tierra 1/2"-5/8" | G91: Und. | H91: 1
A92: INSTALACION | B92: 1BCON-02 | C92: INSTALACIÓN DE CONDENSADORES O CAPACITOR, NO INCLUYE PROTECCIÓN | D92: R-2F | E92: 1001319 | F92: VARILLA DE PUESTA A TIERRA DE COBRE 5/8" X 8' | G92: Und. | H92: 1
A93: INSTALACION | B93: 1BREGU-01 | C93: INSTALACIÓN DE BASE PARA BANCO DE REGULADORES/BOOSTER HASTA 3 X 75KV | D93: B-1F | E93: 1002286 | F93: Tornillo De Espaciamiento,4 Tuercas Cuadradas, 5/8"X 18" | G93: Und. | H93: 12
A94: INSTALACION | B94: 1BREGU-01 | C94: INSTALACIÓN DE BASE PARA BANCO DE REGULADORES/BOOSTER HASTA 3 X 75KV | D94: B-2a | E94: 1002328 | F94: Tornillo De Maquina Cabeza Cuadrada 3/8"X 5" | G94: Und. | H94: 22
A95: INSTALACION | B95: 1BREGU-01 | C95: INSTALACIÓN DE BASE PARA BANCO DE REGULADORES/BOOSTER HASTA 3 X 75KV | D95: B-2D | E95: 1002330 | F95: Tornillo Máq Cab Cuad 5/8"x12" | G95: Und. | H95: 12
A96: INSTALACION | B96: 1BREGU-01 | C96: INSTALACIÓN DE BASE PARA BANCO DE REGULADORES/BOOSTER HASTA 3 X 75KV | D96: B-7B | E96: 1001235 | F96: Fleje diagonal de acero galv. 1-3/4" x 1-3/4" x 3/16"; longitud 84" | G96: Und. | H96: 12
A97: INSTALACION | B97: 1BREGU-01 | C97: INSTALACIÓN DE BASE PARA BANCO DE REGULADORES/BOOSTER HASTA 3 X 75KV | D97: C-20/A1E | E97: 1004813 | F97: CRUCETA DE ACERO 3"X3" X1/4 , PERFIL L DE 10' | G97: Und. | H97: 32
A98: INSTALACION | B98: 1BREGU-01 | C98: INSTALACIÓN DE BASE PARA BANCO DE REGULADORES/BOOSTER HASTA 3 X 75KV | D98: W-10C | E98: 1002205 | F98: Arandela Presión P/ Tornillo 5/8'' | G98: Und. | H98: 60
A99: INSTALACION | B99: 1BREGU-01 | C99: INSTALACIÓN DE BASE PARA BANCO DE REGULADORES/BOOSTER HASTA 3 X 75KV | D99: W-9A | E99: 1002183 | F99: ARANDELA CUADRADA 2X2'' PARA TORNILLO DE 1/2'' | G99: Und. | H99: 22
A100: INSTALACION | B100: 1BREGU-01 | C100: INSTALACIÓN DE BASE PARA BANCO DE REGULADORES/BOOSTER HASTA 3 X 75KV | D100: W-9C | E100: 1002190 | F100: Arandela Cuad Pln 2 1/4"x2 1/4" 5/8-3/4" | G100: Und. | H100: 48
... A164: INSTALACION | B164: 1CDA-MT | C164: Instalación de Cruceta Doble de Acero para Media Tensión (cruceta de 8') | D164: W-10C | E164: 1002205 | F164: Arandela Presión P/ Tornillo 5/8'' | G164: Und. | H164: 18
A165: INSTALACION | B165: 1CIRS-02 | C165: EMPALME DE URD 1Φ EN REGISTRO | D165: URD-MAT-001 | F165: Conector compresión cobre (calibre según cable) | G165: Und. | H165: 1
A166: INSTALACION | B166: 1CIRS-02 | C166: EMPALME DE URD 1Φ EN REGISTRO | D166: URD-MAT-002 | F166: Kit empalme termocontráctil 1Φ 0.6/1kV | G166: Und. | H166: 1
A167: INSTALACION | B167: 1CIRS-02 | C167: EMPALME DE URD 1Φ EN REGISTRO | D167: URD-MAT-003 | E167: URD-MAT-003 | F167: Cinta autofusión (goma) | G167: Mts. | H167: 0.25
A168: INSTALACION | B168: 1CIRS-02 | C168: EMPALME DE URD 1Φ EN REGISTRO | D168: URD-MAT-004 | E168: URD-MAT-004 | F168: Cinta aislante PVC | G168: Mts. | H168: 0.25
A169: INSTALACION | B169: 1CIRS-02 | C169: EMPALME DE URD 1Φ EN REGISTRO | D169: URD-MAT-005 | F169: Limpiador dieléctrico | G169: Und. | H169: 0.05
A170: INSTALACION | B170: 1CIRS-02 | C170: EMPALME DE URD 1Φ EN REGISTRO | D170: URD-MAT-006 | F170: Lija abrasiva | G170: Und. | H170: 0.05
A171: INSTALACION | B171: 1CO-001 | C171: INSTALACIÓN TENDIDO DE LÍNEA 1/0 AL | D171: CM-01A | E171: 1000162 | F171: CONDUCTOR DESNUDO AAAC 1/0 | G171: Mts. | H171: 1.05
A172: INSTALACION | B172: 1CO-002 | C172: INSTALACIÓN Tendido DE LÍNEA 2/0 AL | D172: CM-01C | E172: 1000163 | F172: CONDUCTOR DESNUDO AAAC 2/0 | G172: Mts. | H172: 1.05
A173: INSTALACION | B173: 1CO-003 | C173: INSTALACIÓN Tendido DE LÍNEA 4/0 AL | D173: CB-11D | E173: 1000164 | F173: Conductor Aluminio 246.8 MCM 4/0 AAAC 7h | G173: Mts. | H173: 1.05
A174: INSTALACION | B174: 1CO-004 | C174: INSTALACIÓN Tendido DE LÍNEA 465.4 MCM AL | D174: CM-01G | E174: 1000165 | F174: Conductor AAAC 465.4 MCM (Cairo) | G174: Mts. | H174: 1.05
A175: INSTALACION | B175: 1CO-005 | C175: INSTALACIÓN DE TENDIDO DE CONDUCTOR TRIPLEX 2/0 NEUTRO 2/0 | D175: CB-11D | E175: 1000160 | F175: CONDUCTOR TRIPLEX DE ALUMINIO PARA BAJA TENSION # 2/0 | G175: Mts. | H175: 1.05
A176: INSTALACION | B176: 1CO-006 | C176: INSTALACIÓN DE TENDIDO DE CONDUCTOR TRIPLEX 4/0 NEUTRO 4/0 | D176: CB-11F | E176: 1000161 | F176: CABLE TRIPLEX AISLADO XLPE, COND DE FASE 4/0 AL, COND NEUTRO 4/0 AAAC | G176: Mts. | H176: 1.05
A177: INSTALACION | B177: 1COBT-01 | C177: INSTALACIÓN Tendido DE LÍNEA CONDUCTOR BT TRIPLEX. NO 2/ NO 4 | D177: CB-11C | E177: 1000159 | F177: CONDUCTOR TRIPLEX DE ALUMINIO PARA BAJA TENSION # 2 | G177: Mts. | H177: 1.05
A178: INSTALACION | B178: 1CONE-01 | C178: INSTALACIÓN EMPALME AEREO MT (465.4 A 465.4) | D178: C-6LA | E178: 1001762 | F178: CONECTOR TIPO CUÑA DE ALUMINIO DE 465 DERIVACIÓN 465 MCM | G178: Und. | H178: 1.5
A179: INSTALACION | B179: 1CONE-01 | C179: INSTALACIÓN EMPALME AEREO MT (465.4 A 465.4) | D179: CM-01G | E179: 1000165 | F179: Conductor AAAC 465.4 MCM (Cairo) | G179: Mts. | H179: 1.5
A180: INSTALACION | B180: 1CONE-02 | C180: INSTALACIÓN EMPALME AEREO MT (465.4 MCM A 4/0) | D180: C-36C | E180: 1001763 | F180: Conector tipo cuña 465.4 MCM – 4/0AWG | G180: Und. | H180: 1.5
A181: INSTALACION | B181: 1CONE-02 | C181: INSTALACIÓN EMPALME AEREO MT (465.4 MCM A 4/0) | D181: C-6HC | E181: 1001757 | F181: CONECTOR TIPO CUÑA DE ALUMINO DE 4/0 DERIVACION 4/0 A 3/0 AWG | G181: Und. | H181: 1
A182: INSTALACION | B182: 1CONE-02 | C182: INSTALACIÓN EMPALME AEREO MT (465.4 MCM A 4/0) | D182: CM-01E | E182: 1000164 | F182: Conductor AAAC 4/0 AWG (Alliance) | G182: Mts. | H182: 1.5
... A194: INSTALACION | B194: 1CONE-08 | C194: INSTALACIÓNALACION EMPALME AEREO AISLADO PARA MT. | D194: C-6HC | E194: 1001757 | F194: CONECTOR TIPO CUÑA DE ALUMINO DE 4/0 DERIVACION 4/0 A 3/0 AWG | G194: Und. | H194: 2
A195: INSTALACION | B195: 1CO-URDB1 | C195: INSTALACIÓN METRO DE CONDUCTOR URD BAJO TIERRA ≤ 1/0 | D195: 1000095 | E195: 1000095 | F195: CABLE COBRE URD #1/0 AISL P/ 15kV | G195: Mts. | H195: 1.05
A196: INSTALACION | B196: 1CO-URDB12 | C196: INSTALACIÓN METRO DE CONDUCTOR URD SOBRE TIERRA ≤ 1/0 | D196: 1000095 | E196: 1000095 | F196: CABLE COBRE URD #1/0 AISL P/ 15kV | G196: Mts. | H196: 1.05
A197: INSTALACION | B197: 1CO-URDB2 | C197: INSTALACIÓN METRO DE CONDUCTOR URD BAJO TIERRA 2/0 | D197: C-3DC | E197: 1000097 | F197: Cable de Cobre (URD) #2/0 al 33% Aislado para 15 kV | G197: Mts. | H197: 1.05
A198: INSTALACION | B198: 1CO-URDB3 | C198: INSTALACIÓN METRO DE CONDUCTOR URD BAJO TIERRA 4/0 | D198: C-3EA | E198: 1000098 | F198: Cable de Cobre (URD) #4/0 al 33% Aislado para 15 kV | G198: Mts. | H198: 1.05
A199: INSTALACION | B199: 1CO-URDB7 | C199: INSTALACIÓN METRO DE CONDUCTOR URD SOBRE TIERRA 2/0 | D199: C-3DC | E199: 1000097 | F199: Cable de Cobre (URD) #2/0 al 33% Aislado para 15 kV | G199: Mts. | H199: 1.05
A200: INSTALACION | B200: 1CO-URDB8 | C200: INSTALACIÓN METRO DE CONDUCTOR URD SOBRE TIERRA 4/0 | D200: C-3EA | E200: 1000098 | F200: Cable de Cobre (URD) #4/0 al 33% Aislado para 15 kV | G200: Mts. | H200: 1.05
A201: INSTALACION | B201: 1CSA-MT | C201: Instalación de Cruceta simple de Acero para Media Tensión (cruceta de 8') | D201: B-2B | E201: 1002308 | F201: Tornillo Máq Cab Cuad 1/2"x12" | G201: Und. | H201: 1
A202: INSTALACION | B202: 1CSA-MT | C202: Instalación de Cruceta simple de Acero para Media Tensión (cruceta de 8') | D202: B-2D | E202: 1002330 | F202: Tornillo Máq Cab Cuad 5/8"x12" | G202: Und. | H202: 1
A203: INSTALACION | B203: 1CSA-MT | C203: Instalación de Cruceta simple de Acero para Media Tensión (cruceta de 8') | D203: B-5A | E203: 1002325 | F203: Tornillo Máq Cab Cuad 3/8"x2" | G203: Und. | H203: 2
A204: INSTALACION | B204: 1CSA-MT | C204: Instalación de Cruceta simple de Acero para Media Tensión (cruceta de 8') | D204: B-6A | E204: 1001241 | F204: Fleje Plancha Acero 1 1/4x1/4"x28" | G204: Und. | H204: 2
A205: INSTALACION | B205: 1CSA-MT | C205: Instalación de Cruceta simple de Acero para Media Tensión (cruceta de 8') | D205: C-20D | E205: 1002083 | F205: Cruceta Acer 3"x3"x1/4" Perf L 8'-0" | G205: Und. | H205: 1
A206: INSTALACION | B206: 1CSA-MT | C206: Instalación de Cruceta simple de Acero para Media Tensión (cruceta de 8') | D206: E-4 | E206: 1004830 | F206: Tuerca cuadrada acero galvanizado para tornillo 5/8” | G206: Und. | H206: 1
A207: INSTALACION | B207: 1CSA-MT | C207: Instalación de Cruceta simple de Acero para Media Tensión (cruceta de 8') | D207: GCT-ST1 | E207: 1009789 | F207: GRAPA DE CONEXIÓN DOBLE CABLE DE TIERRA SIN TORNILLO | G207: Und. | H207: 1
A208: INSTALACION | B208: 1CSA-MT | C208: Instalación de Cruceta simple de Acero para Media Tensión (cruceta de 8') | D208: W-10A | E208: 1002204 | F208: Arandela Presión P/ Tornillo 3/8" | G208: Und. | H208: 2
... A339: INSTALACION | B339: 1HA-100B | C339: Instalación de Retenida sencilla de poste a tierra en Media Tension | D339: W-9D | E339: 1002185 | F339: Arandela cuadrada plana de 3” x 3” para tornillo de 3/4" | G339: Und. | H339: 1
A340: INSTALACION | B340: 1HA-105B | C340: Instalación de Retenida aérea simple en Media Tension | D340: 1011855 | E340: 1011855 | F340: Tornillo Maquina Cabeza Hex. 5/8" X 3" | G340: Und. | H340: 1
A341: INSTALACION | B341: 1HA-105B | C341: Instalación de Retenida aérea simple en Media Tension | D341: CV-01C | E341: 1000130 | F341: CABLE DE VIENTO 7/16'' 76 KN | G341: Mts. | H341: 20
A342: INSTALACION | B342: 1HA-105B | C342: Instalación de Retenida aérea simple en Media Tension | D342: E-1B | E342: 1002398 | F342: TUERCA OJO CON GUARDACABO RECTO 5/8" 55.6 KN | G342: Und. | H342: 1
A343: INSTALACION | B343: 1HA-105B | C343: Instalación de Retenida aérea simple en Media Tension | D343: G-1B | E343: 1002020 | F343: TERMINAL PREFORMADO 7/16" | G343: Und. | H343: 2
A344: INSTALACION | B344: 1HA-105B | C344: Instalación de Retenida aérea simple en Media Tension | D344: G-2A | E344: 1002218 | F344: Tornillo guardacabo recto 5/8" x 12” | G344: Und. | H344: 1
A345: INSTALACION | B345: 1HA-105B | C345: Instalación de Retenida aérea simple en Media Tension | D345: W-10C | E345: 1002205 | F345: Arandela Presión P/ Tornillo 5/8'' | G345: Und. | H345: 1
A346: INSTALACION | B346: 1HA-105B | C346: Instalación de Retenida aérea simple en Media Tension | D346: W-9C | E346: 1002190 | F346: Arandela Cuad Pln 2 1/4"x2 1/4" 5/8-3/4" | G346: Und. | H346: 1
...

Sheet Hoja4
A3: Etiquetas de fila | B3: Suma de Totales
A4: 1000000 | B4: 10
A5: 1000004 | B5: 140
A6: 1000005 | B6: 18
A7: 1000050 | B7: 220
A8: 1000738 | B8: 20
A9: 1000742 | B9: 1
A10: 1000752 | B10: 3
A11: 1001241 | B11: 94
A12: 1001263 | B12: 10
A13: 1001892 | B13: 21
A14: 1002083 | B14: 47
A15: 1002183 | B15: 25
... A30: 1009789 | B30: 10
A31: Total general | B31: 1502.5

Sheet Hoja5
A2: 1000000 | B2: =VLOOKUP(A2,[3]Hoja3!$A$2:$B$3599,2,0) -> Aislad T/Carr 3x3-1/8 76x80mm 11/16 53-2 | C2: 10 | D2: =VLOOKUP(A2,[4]Sheet1!$C$2:$J$44,2,0) -> Aislad T/Carr 3x3-1/8 76x80mm 11/16 53-2
A3: 1000004 | B3: =VLOOKUP(A3,[3]Hoja3!$A$2:$B$3599,2,0) -> Aislador Ríg T/ Esp 57-1 C/ Esp y Tuerca | C3: 140 | D3: =VLOOKUP(A3,[4]Sheet1!$C$2:$J$44,2,0) -> Aislador Ríg T/ Esp 57-1 C/ Esp y Tuerca
A4: 1000005 | B4: =VLOOKUP(A4,[3]Hoja3!$A$2:$B$3599,2,0) -> Aislador Susp 12.5kV Polimérico | C4: 18 | D4: =VLOOKUP(A4,[4]Sheet1!$C$2:$J$44,2,0) -> Aislador Susp 12.5kV Polimérico
A5: 1000050 | B5: =VLOOKUP(A5,[3]Hoja3!$A$2:$B$3599,2,0) -> Alambre #4 AWG-SDO Al P/ Ligadura | C5: 220 | D5: =VLOOKUP(A5,[4]Sheet1!$C$2:$J$44,2,0) -> Alambre #4 AWG-SDO Al P/ Ligadura
A6: 1000738 | B6: =VLOOKUP(A6,[3]Hoja3!$A$2:$B$3599,2,0) -> Grapa de Retenc Acero Galv Cond 4/0 Al | C6: 20 | D6: =VLOOKUP(A6,[4]Sheet1!$C$2:$J$44,2,0) -> #N/A
A7: 1000742 | B7: =VLOOKUP(A7,[3]Hoja3!$A$2:$B$3599,2,0) -> Grapa de Retención Term 4/0-1/0 Al-ACSR | C7: 1 | D7: =VLOOKUP(A7,[4]Sheet1!$C$2:$J$44,2,0) -> Grapa de Retención Term 4/0-1/0 Al-ACSR
A8: 1000752 | B8: =VLOOKUP(A8,[3]Hoja3!$A$2:$B$3599,2,0) -> Grapa Terminal para 465-500 MCM | C8: 3 | D8: =VLOOKUP(A8,[4]Sheet1!$C$2:$J$44,2,0) -> #N/A
A9: 1001241 | B9: =VLOOKUP(A9,[3]Hoja3!$A$2:$B$3599,2,0) -> Fleje Galv 1-7/32"x7/32"x28" | C9: 94 | D9: =VLOOKUP(A9,[4]Sheet1!$C$2:$J$44,2,0) -> Fleje Plancha Acero 1 1/4x1/4"x28"
A10: 1001263 | B10: =VLOOKUP(A10,[3]Hoja3!$A$2:$B$3599,2,0) -> Porta Aisl U:1 1/2x1/2"x1/8" Orif 11/16" | C10: 10 | D10: =VLOOKUP(A10,[4]Sheet1!$C$2:$J$44,2,0) -> #N/A
A11: 1001892 | B11: =VLOOKUP(A11,[3]Hoja3!$A$2:$B$3599,2,0) -> Grapa P/ Fijacion Cond Tierra 2/0-8 1/4" | C11: 21 | D11: =VLOOKUP(A11,[4]Sheet1!$C$2:$J$44,2,0) -> Grapa P/ Fijacion Cond Tierra 2/0-8 1/4"
A12: 1002083 | B12: =VLOOKUP(A12,[3]Hoja3!$A$2:$B$3599,2,0) -> Cruceta Acer 3"x3"x1/4" Perf L 8'-0" | C12: 47 | D12: =VLOOKUP(A12,[4]Sheet1!$C$2:$J$44,2,0) -> Cruceta Acer 3"x3"x1/4" Perf L 8'-0"
A13: 1002183 | B13: =VLOOKUP(A13,[3]Hoja3!$A$2:$B$3599,2,0) -> Arandela Cuad 2x2" P/ Tornillo 1/2" | C13: 25 | D13: =VLOOKUP(A13,[4]Sheet1!$C$2:$J$44,2,0) -> Arandela Cuad 2x2" P/ Tornillo 1/2"
... A28: 1009789 | B28: =VLOOKUP(A28,[3]Hoja3!$A$2:$B$3599,2,0) -> GRAPA CONEXIÓN DOBLE CAB TIERRA SIN TORN | C28: 10 | D28: =VLOOKUP(A28,[4]Sheet1!$C$2:$J$44,2,0) -> GRAPA CONEXIÓN DOBLE CAB TIERRA SIN TORN

Sheet Hoja1
A1: Sap | B1: Cant | C1: Totales | D1: 15 | E1: 10 | F1: 5 | G1: 1
A2: 1000004 | B2: 4 | C2: =+B2*$D$1 -> 60
A3: 1002308 | B3: 1 | C3: =+B3*$D$1 -> 15
A4: 1002329 | B4: 1 | C4: =+B4*$D$1 -> 15
A5: 1002325 | B5: 2 | C5: =+B5*$D$1 -> 30
A6: 1001241 | B6: 2 | C6: =+B6*$D$1 -> 30
A7: 1002083 | B7: 1 | C7: =+B7*$D$1 -> 15
A8: 1001892 | B8: 1 | C8: =+B8*$D$1 -> 15
A9: 1004752 | B9: 1 | C9: =+B9*$D$1 -> 15
A10: 1009782 | B10: 2 | C10: =+B10*$D$1 -> 30
A11: 1003156 | B11: 4 | C11: =+B11*$D$1 -> 60
A12: 1002204 | B12: 2 | C12: =+B12*$D$1 -> 30
A13: 1002201 | B13: 1 | C13: =+B13*$D$1 -> 15
... A17: 1002191 | B17: 1 | C17: =+B17*$D$1 -> 15
A18: 1000000 | B18: 1 | C18: =+B18*$E$1 -> 10
A19: 1000004 | B19: 8 | C19: =+B19*$E$1 -> 80
A20: 1002283 | B20: 3 | C20: =+B20*$E$1 -> 30
A21: 1002308 | B21: 1 | C21: =+B21*$E$1 -> 10
A22: 1002331 | B22: 1 | C22: =+B22*$E$1 -> 10
A23: 1002325 | B23: 4 | C23: =+B23*$E$1 -> 40
A24: 1001241 | B24: 4 | C24: =+B24*$E$1 -> 40
A25: 1002083 | B25: 2 | C25: =+B25*$E$1 -> 20
A26: 1004752 | B26: 1 | C26: =+B26*$E$1 -> 10
A27: 1009782 | B27: 1.5 | C27: =+B27*$E$1 -> 15
A28: 1001263 | B28: 1 | C28: =+B28*$E$1 -> 10
A29: 1004830 | B29: 1 | C29: =+B29*$E$1 -> 10
... A36: 1002191 | B36: 11 | C36: =+B36*$E$1 -> 110
A37: 1000005 | B37: 3 | C37: =+B37*$F$1 -> 15
A38: 1002283 | B38: 5 | C38: =+B38*$F$1 -> 25
A39: 1002308 | B39: 1 | C39: =+B39*$F$1 -> 5
A40: 1002325 | B40: 4 | C40: =+B40*$F$1 -> 20
A41: 1001241 | B41: 4 | C41: =+B41*$F$1 -> 20
A42: 1000738 | B42: 4 | C42: =+B42*$F$1 -> 20
A43: 1002083 | B43: 2 | C43: =+B43*$F$1 -> 10
A44: 1001892 | B44: 1 | C44: =+B44*$F$1 -> 5
A45: 1004752 | B45: 1 | C45: =+B45*$F$1 -> 5
A46: 1009782 | B46: 2 | C46: =+B46*$F$1 -> 10
A47: 1002390 | B47: 4 | C47: =+B47*$F$1 -> 20
A48: 1002204 | B48: 4 | C48: =+B48*$F$1 -> 20
... A50: 1002205 | B50: 18 | C50: =+B50*$F$1 -> 90
A51: 1000005 | B51: 3 | C51: =+B51*$G$1 -> 3
A52: 1002283 | B52: 5 | C52: =+B52*$G$1 -> 5
A53: 1002308 | B53: 1 | C53: =+B53*$G$1 -> 1
A54: 1002325 | B54: 4 | C54: =+B54*$G$1 -> 4
A55: 1001241 | B55: 4 | C55: =+B55*$G$1 -> 4
A56: 1000742 | B56: 1 | C56: =+B56*$G$1 -> 1
A57: 1000752 | B57: 3 | C57: =+B57*$G$1 -> 3
A58: 1002083 | B58: 2 | C58: =+B58*$G$1 -> 2
A59: 1001892 | B59: 1 | C59: =+B59*$G$1 -> 1
A60: 1004752 | B60: 1 | C60: =+B60*$G$1 -> 1
A61: 1009782 | B61: 0.5 | C61: =+B61*$G$1 -> 0.5
A62: 1002390 | B62: 4 | C62: =+B62*$G$1 -> 4
... A65: 1002205 | B65: 18 | C65: =+B65*$G$1 -> 18

Sheet obse
A1: Código Material | B1: Codigo SAP | C1: Descripción_MAT | D1: obser
A2: B-16 | B2: 1002328 | C2: Tornillo De Maquina Cabeza Cuadrada 3/8"X 5" | D2: se cambio codigo alfanumerico a B-2a
A3: B-2C | B3: 1002329 | C3: Tornillo de máquina acero galvanizado cabeza cuadrada 5/8” x 10” | D3: se cambio codigo alfanumerico a B-2d
A4: C-38B | B4: 1004752 | C4: CONECTOR ELÁSTICO TIPO CUÑA 4/0 AWG - #2 CU | D4: se cambio codigo alfanumerico a C-35K
A5: C-38D | B5: 1004752 | C5: Conector elástico tipo cuña 4/0 AWG – 2 CU AWG | D5: se cambio codigo alfanumerico a C-35K

Sheet corregidos
A1: Codigo SAP | B1: Descripción_MAT
A2: 100000 | B2: SALES DE GEM
A3: 100001 | B3: SAL EN GRANO
A4: 100002 | B4: TIERRA NEGRA
A5: 1000000 | B5: Aislad T/Carr 3x3-1/8 76x80mm 11/16 53-2
A6: 1000004 | B6: AISLADOR DE PORCELANA TIPO POSTE 15 KV CLASE 57-1
A7: 1000005 | B7: AISLADOR POLIMERICO TIPO SUSPENSION, 15 KV
A8: 1000015 | B8: Aislador T/ Esp PIN CL52-3 1 3/8" 34.5kV
A9: 1000016 | B9: Aislador Tipo Espiga Clase 55-3 Orificio 1"
A10: 1000017 | B10: Aislador T/ Esp PIN CL55-5 1"
A11: 1000018 | B11: Aislador de espiga clase 56-3, Orificio 1 13/8", 34.5KV
B12: Aislador T/ Esp PIN CL56-3 1 3/8" 34.5kV
A13: 1000050 | B13: Alambre de amarre #4 AWG solido de aluminio
A14: 1000091 | B14: Cable Cobre Estañado #2 AWG Desnudo
A15: 1000095 | B15: CABLE COBRE URD #1/0 AISL P/ 15kV
A16: 1000097 | B16: Cable de Cobre (URD) #2/0 al 33% Aislado para 15 kV
A17: 1000098 | B17: Cable de Cobre (URD) #4/0 al 33% Aislado para 15 kV
A18: 1000100 | B18: CONDUCTOR CONCÉNTRICO DE ALUMINIO 2 X # 8 AWG
A19: 1000102 | B19: Conductor concéntrico de Al 3 x #6 AWG
A20: 1000129 | B20: CABLE DE VIENTO 5/16'' 44 KN
A21: 1000130 | B21: CABLE DE VIENTO 7/16'' 76 KN
A22: 1000144 | B22: CABLE FLEXIBLE DE CONTROL AWG, 5 CONDUCTORES, # 14 AWG
A23: 1000145 | B23: CABLE DE COBRE MULTIPOLAR FLEXIBLE 7 X 12 AWG
A24: 1000159 | B24: CONDUCTOR TRIPLEX DE ALUMINIO PARA BAJA TENSION # 2
... A80: 1001308 | B80: Tubo flexible liquid tight de 1" galvanizado con protección PVC
B81: TUBO LIQUID TIGHT DE 1"
A82: 1001311 | B82: Varilla de anclaje de ojo doble, de 3/4" x 8'
A83: 1001318 | B83: VARILLA DE PUESTA A TIERRA DE COBRE 1/2" X 6'
A84: 1001319 | B84: VARILLA DE PUESTA A TIERRA DE COBRE 5/8" X 8'
A85: 1001711 | B85: Conector recto tubería flexible liquid tight 1”
A86: 1001752 | B86: Conector.De Comp. P/. Conductor De 500-4/0 A 500-4/0 Awg
A87: 1001755 | B87: CONECTOR TIPO CUÑA CON ESTRIBO 4/0-2/0 ESTRIBO 2/0
A88: 1001756 | B88: Conector elástico tipo cuña 465.4 MCM con estribo.
A89: 1001757 | B89: Conect Cuña P/ Cond 4/0 Deriv 4/0-3/0
B90: CONECTOR TIPO CUÑA DE ALUMINO DE 4/0 DERIVACION 4/0 A 3/0 AWG
A91: 1001758 | B91: CONECTOR CUÑA PRESION 4/0 AWG A 2/0 AWG
B92: CONECTOR TIPO CUÑA DE ALUMINIO DE 4/0 A 1/0 DERIVACION 2/0A1/0 AWG
A93: 1001759 | B93: Conector t cuña p/cond princ 4/0a1/0 deriv 2/0 a 2
A94: 1001760 | B94: Conector Elást Cuña 465-2/0 AWG
B95: CONECTOR T. CUÑA P/COND PRINCIPAL 465 CAIRO 3/0 A 2/0
A96: 1001762 | B96: CONECTOR TIPO CUÑA DE ALUMINIO DE 465 DERIVACIÓN 465 MCM
A97: 1001763 | B97: Conector tipo cuña 465.4 MCM – 4/0AWG
A98: 1001764 | B98: Conector elástico tipo cuña 465.4 MCM – 2 Cu AWG
A99: 1001767 | B99: CONECTOR DENTADOIMPLE 25/150-25/150 MM²(3-300 A 3-300 AWG)
A100: 1001768 | B100: CONECTOR DENTADO DOBLE 50/150-50/150 MM² 1/0-300 A 1/0-300 AWG
A101: 1001778 | B101: Conect Perno Part P/ Cabl No.2 al 2/0 Cu
A102: 1001789 | B102: Conector de perforación 1/0-300 MCM A CABLE AISL. #10-2 AWG
A103: 1001791 | B103: CONECTOR DENTADO SIMPLE16-95/4-35
A104: 1001831 | B104: Conector Galv P/Varilla Tierra 1/2"-5/8"
A105: 1001892 | B105: Grapa de fijación de cable a superficie plana 1/4" p/conductor Cu 2/0-#8 AWG
A106: 1001894 | B106: HEBILLA ACERO INOXIDABLE DE 20MM ZHE 20 (COD.738)
A107: 1001956 | B107: TERMINAL PIN BIMETALICO PARA CONECTOR CUÑA, CAILBRE 465 MCM, 2 AGUJERO
... A135: 1002185 | B135: ARANDELA CUADRADA PLANA DE 2 1/4" X 2 1/4" PARA TORNILLO DE 5/8"
B136: Arandela cuadrada plana de 3” x 3” para tornillo de 3/4"
A137: 1002190 | B137: Arandela Cuad Pln 2 1/4"x2 1/4" 5/8-3/4"
A138: 1002191 | B138: ARANDELA CUAD.2 1/4" X 2 1/4" ESP.3/16'' (TORN.5/8"-3/4")
A139: 1002201 | B139: Arandela de presión para tornillo de 1/2”
A140: 1002203 | B140: Arandela de presión para tornillo de 3/4"
A141: 1002204 | B141: ARANDELA DE PRESION P/TORNILLO 3/8
B142: Arandela de presión para tornillo de 3/8”
A143: 1002205 | B143: ARANDELA DE PRESION P/TORNILLO 5/8''
A144: 1002218 | B144: PERNO GUARDACABO PARA CABLE DE VIENTO,TORNILO 5/8 X 12" TUERCA CUAD
B145: Tornillo guardacabo recto 5/8" x 12”
A146: 1002225 | B146: Perno de seguridad serie E4
A147: 1002231 | B147: TARUGO-PERNOACERADO RECUB.ZINC LONG 13/4",PERNO DE 1/4"
A148: 1002233 | B148: TARUGO-PERNO ACERADO RECUB. ZINC 5/8" X 3 3/4", PERNO DE 1/2"
A149: 1002236 | B149: TARUGO PLAST. C/TORNILLO CABEZA HEXAGONAL NO.10-12, LONG. 1" DIAM. 9/32"
A150: 1002282 | B150: Tornillos De Esp. 4 Tuercas Cuad.5/8" X 10"
A151: 1002283 | B151: Tornillo Esp 4 Tuerc Cuad 5/8"x12"
A152: 1002284 | B152: TORNILLOS DE ESPACIAMIENTO. 4 TUERCAS CUAD.5/8" X 14"(16MMX350MM)
A153: 1002286 | B153: Tornillo De Espaciamiento,4 Tuercas Cuadradas, 5/8"X 18"
A154: 1002287 | B154: Tornillo Espac.4 Tuercas Cuad. 5/8"X20"
A155: 1002306 | B155: Tornillo de seguridad cabeza magnética de 1/4"
A156: 1002307 | B156: TORNILLO DE MAQUINA ACERO GALVANIZADO CABEZA CUADRADA 1/2" X 10"
B157: TORNILLO DE MAQUINA CABEZA CUAD. 1/2" X 10"
A158: 1002308 | B158: TORNILLO DE MAQUINA ACERO GALVANIZADO CABEZA CUADRADA 1/2" X 12".
A159: 1002311 | B159: TORNILLO DE MAQUINA CABEZA CUAD. 1/2" X 2"
A160: 1002312 | B160: Tornillo de maquina acero galvanizado cabeza hexagonal 1/2" x 3”.
A161: 1002313 | B161: TORNILLO DE MAQUINA ACERO GALVANIZADO CABEZA CUADRADA 1/2" X 6"
A162: 1002318 | B162: Tornillo Máq Cab Cuad 3/4"x12"
A163: 1002325 | B163: TORNILLO DE MAQUINA ACERO GALVANIZADO CABEZA HEXAGONAL 3/8" X 2".
B164: Tornillo de máquina acero galvanizado cabeza hexagonal 3/8” x 2”
A165: 1002328 | B165: Tornillo De Maquina Cabeza Cuadrada 3/8"X 5"
A166: 1002329 | B166: Tornillo de máquina acero galvanizado cabeza cuadrada 5/8” x 10”
A167: 1002330 | B167: Tornillo Máq Cab Cuad 5/8"x12"
A168: 1002331 | B168: Tornillo de espaciamiento acero galvanizado 5/8” x 14”
B169: Tornillo de máquina acero galvanizado cabeza cuadrada 5/8” x 14”
A170: 1002339 | B170: Tornillo Máq Cab Hex 1/2"x2"
A171: 1002347 | B171: TORNILLO PARA AISLADOR TIPO CARRETE 5/8" X 14".
A172: 1002349 | B172: Tornillo P/ Aislador T/ Carrete 5/8"x16"
A173: 1002388 | B173: TUERCA DE OJO OVAL PARA TORNILO DE 1/2"
A174: 1002390 | B174: TUERCA DE OJO OVAL PARA TORNILO DE 5/8"
A175: 1002395 | B175: TUERCA DE OJO GUARDACABO INCLINADO 45º PARA TORNILO DE 5/8"
A176: 1002398 | B176: TUERCA OJO CON GUARDACABO RECTO 5/8" 55.6 KN
A177: 1002400 | B177: TRANSF.DE CORRIENTE T/DONUT 200/5 A,CLASE 0.5%,600V
A178: 1002447 | B178: Transformador de corriente de Baja Tensión 600 V; Relación 300 / 5 A
A179: 1002450 | B179: Transformador de corriente de Baja Tensión 600 V; Relación 400 / 5 A
A180: 1002464 | B180: TRANSFORMADOR DE CORRIENTE DE BAJA TENSIÓN Relación de Transformación 100/5 A , 600V
A181: 1002511 | B181: TUBO PVC SDR26 DE 1/2"X19'
... A197: 1004752 | B197: CONECTOR ELÁSTICO TIPO CUÑA 4/0 AWG - #2 CU
...

Sheet Hoja3
C5: Código Material | D5: Codigo SAP
C6: AC-11A | D6: 1000000
C7: AR-12A | D7: 1000004
C8: AS-22D | D8: 1000005
C9: W-7A | D9: 1000050
C10: CP-02A | D10: 1000103
C11: CV-01A | D11: 1000129
C12: CV-01C | D12: 1000130
C13: CB-11D | D13: 1000160
C14: CM-01C | D14: 1000163
C15: 1000568 | D15: 1000568
C16: C-15A | D16: 1000734
C17: C-15B | D17: 1000742
C18: R-5 | D18: 1001021
C19: N-3 | D19: 1001204
C20: B-7B | D20: 1001235
C21: B-7A | D21: 1001238
C22: B-6A | D22: 1001241
C23: B-10D | D23: 1001244
C24: B-10A | D24: 1001245
C25: D-1 | D25: 1001263
C26: R-1A | D26: 1001312
C27: R-2F | D27: 1001319
... C72: C-20C1 | D72: 1010958
C73: 1011408 | D73: 1011408
C74: R-1C | D74: 1011854
C75: B-5E | D75: 1011855

Sheet PU_EDE
A1: CODE | B1: DESCRIPCION DE MATERIALES | C1: UNIDAD | D1: EDEESTE
A2: 1000568 | B2: Cobertor de Líneas MT 12.5kV MVLC 4/0 | C2: Mts. | D2: 42.25
A3: 1011408 | B3: Poste de madera de 60 Pies Clase 2 | C3: Und. | D3: 891.04
A4: AC-11A | B4: AISLADOR DE PORCELANA TIPO CARRETE CLASE 53-2 | C4: Und. | D4: 0.8
A5: AD-4B | B5: Pararrayos de distribución de 9 kV; 12.47 kV | C5: Und. | D5: 22.05
A6: AD-4E | B6: PARARRAYO 10KV OXIDO METÁLICO | C6: Und. | D6: 0
A7: AH-11A | B7: Ancla de hormigón para retenidas | C7: Und. | D7: 7.15
A8: AR-12A | B8: AISLADOR DE PORCELANA TIPO POSTE 15 KV CLASE 57-1 | C8: Und. | D8: 15.6
A9: AS-22D | B9: AISLADOR POLIMÉRICO TIPO SUSPENSIÓN 15 KV | C9: Und. | D9: 10.9
A10: B-10A | B10: FLEJE VERTICAL DE ACERO GALV. 1-1/2" X 1-1/2" X 3/16"; LONGITUD 39" | C10: Und. | D10: 0
A11: B-10B | B11: FLEJE VERTICAL DE ACERO GALV. 1-1/2" X 1-1/2" X 3/16"; LONGITUD 75" | C11: Und. | D11: 0
A12: B-10D | B12: Fleje vertical de acero galv. 1-1/2" x 1-1/2" x 3/16"; longitud 54" | C12: Und. | D12: 25.65
A13: B-13 | B13: TERMINAL DEL CABLE PARA USO EXTERIOR (URD) | C13: Und. | D13: 0
A14: B-1C | B14: Tornillo de espaciamiento acero galvanizado 5/8” x 12” | C14: Und. | D14: 2.95
A15: B-1D | B15: TORNILLO DE ESPACIAMIENTO ACERO GALVANIZADO 5/8" X 14". | C15: Und. | D15: 3.55
... A123: W-9d | B123: Arandela cuadrada plana de 3” x 3” para tornillo de 3/4" | C123: Und. | D123: 1.35

Sheet PU_ESD
A1: CODE | B1: DESCRIPCION DE MATERIALES | C1: UNIDAD | D1: ESD
A2: 1000568 | B2: Cobertor de Líneas MT 12.5kV MVLC 4/0 | C2: Mts. | D2: 0
A3: 1011408 | B3: Poste de madera de 60 Pies Clase 2 | C3: Und. | D3: 0
A4: AC-11A | B4: AISLADOR DE PORCELANA TIPO CARRETE CLASE 53-2 | C4: Und. | D4: 0.8
A5: AD-4B | B5: Pararrayos de distribución de 9 kV; 12.47 kV | C5: Und. | D5: 0
A6: AD-4E | B6: PARARRAYO 10KV OXIDO METÁLICO | C6: Und. | D6: 25.91
A7: AH-11A | B7: Ancla de hormigón para retenidas | C7: Und. | D7: 7.15
A8: AR-12A | B8: AISLADOR DE PORCELANA TIPO POSTE 15 KV CLASE 57-1 | C8: Und. | D8: 15.6
A9: AS-22D | B9: AISLADOR POLIMÉRICO TIPO SUSPENSIÓN 15 KV | C9: Und. | D9: 10.9
A10: B-10A | B10: FLEJE VERTICAL DE ACERO GALV. 1-1/2" X 1-1/2" X 3/16"; LONGITUD 39" | C10: Und. | D10: 14.76
A11: B-10B | B11: FLEJE VERTICAL DE ACERO GALV. 1-1/2" X 1-1/2" X 3/16"; LONGITUD 75" | C11: Und. | D11: 36.55
A12: B-10D | B12: Fleje vertical de acero galv. 1-1/2" x 1-1/2" x 3/16"; longitud 54" | C12: Und. | D12: 0
A13: B-13 | B13: TERMINAL DEL CABLE PARA USO EXTERIOR (URD) | C13: Und. | D13: 48.24
A14: B-1C | B14: Tornillo de espaciamiento acero galvanizado 5/8” x 12” | C14: Und. | D14: 2.95
A15: B-1D | B15: TORNILLO DE ESPACIAMIENTO ACERO GALVANIZADO 5/8" X 14". | C15: Und. | D15: 3.55
... A123: W-9d | B123: Arandela cuadrada plana de 3” x 3” para tornillo de 3/4" | C123: Und. | D123: 1.35

Sheet PU_KEPCO
A1: CODE | B1: DESCRIPCION DE MATERIALES | C1: UNIDAD | D1: REPLANTEO_KEPCO
A2: 1000568 | B2: Cobertor de Líneas MT 12.5kV MVLC 4/0 | C2: Mts. | D2: 0
A3: 1011408 | B3: Poste de madera de 60 Pies Clase 2 | C3: Und. | D3: 0
A4: AC-11A | B4: AISLADOR DE PORCELANA TIPO CARRETE CLASE 53-2 | C4: Und. | D4: 0.8
A5: AD-4B | B5: Pararrayos de distribución de 9 kV; 12.47 kV | C5: Und. | D5: 0
A6: AD-4E | B6: PARARRAYO 10KV OXIDO METÁLICO | C6: Und. | D6: 25.91
A7: AH-11A | B7: Ancla de hormigón para retenidas | C7: Und. | D7: 7.15
A8: AR-12A | B8: AISLADOR DE PORCELANA TIPO POSTE 15 KV CLASE 57-1 | C8: Und. | D8: 15.6
A9: AS-22D | B9: AISLADOR POLIMÉRICO TIPO SUSPENSIÓN 15 KV | C9: Und. | D9: 10.9
A10: B-10A | B10: FLEJE VERTICAL DE ACERO GALV. 1-1/2" X 1-1/2" X 3/16"; LONGITUD 39" | C10: Und. | D10: 14.76
A11: B-10B | B11: FLEJE VERTICAL DE ACERO GALV. 1-1/2" X 1-1/2" X 3/16"; LONGITUD 75" | C11: Und. | D11: 36.55
A12: B-10D | B12: Fleje vertical de acero galv. 1-1/2" x 1-1/2" x 3/16"; longitud 54" | C12: Und. | D12: 0
A13: B-13 | B13: TERMINAL DEL CABLE PARA USO EXTERIOR (URD) | C13: Und. | D13: 0
A14: B-1C | B14: Tornillo de espaciamiento acero galvanizado 5/8” x 12” | C14: Und. | D14: 2.95
A15: B-1D | B15: TORNILLO DE ESPACIAMIENTO ACERO GALVANIZADO 5/8" X 14". | C15: Und. | D15: 3.55
... A123: W-9d | B123: Arandela cuadrada plana de 3” x 3” para tornillo de 3/4" | C123: Und. | D123: 1.35

Sheet MAT_FAMILIA
A1: CODE | B1: DESCRIPCION DE MATERIALES | C1: UNIDAD | D1: Famili_Mat | G1: Código Material | H1: Descripción_MAT | I1: Unidad | J1: CATEGORIAS | K1: Columna1
A2: 1000568 | B2: Cobertor de Líneas MT 12.5kV MVLC 4/0 | C2: Mts. | D2: HERRAJES | G2: C-18B | H2: ABRAZADERA DE CONTRA PRESIÓN PARA TUBO DE ANCLAJE DE 2" | I2: Und. | J2: ABRAZADERAS | K2: ABRAZADERAS | L2: =VLOOKUP(Tabla12[[#This Row],[Código Material]],'BASE DE CALCULO'!$C$2:$G$379,7,) -> #REF!
A3: 1011408 | B3: Poste de madera de 60 Pies Clase 2 | C3: Und. | D3: POSTES Y ANCLAS | G3: N-3 | H3: Abrazadera perno de 5/8” | I3: Und. | J3: ABRAZADERAS | K3: ABRAZADERAS | L3: =VLOOKUP(Tabla12[[#This Row],[Código Material]],'BASE DE CALCULO'!$C$2:$G$379,7,) -> #REF!
A4: AC-11A | B4: AISLADOR DE PORCELANA TIPO CARRETE CLASE 53-2 | C4: Und. | D4: AISLADOR | G4: AR-12A | H4: AISLADOR DE PORCELANA TIPO POSTE 15 KV CLASE 57-1 | I4: Und. | J4: AISLADORES | K4: AISLADOR | L4: =VLOOKUP(Tabla12[[#This Row],[Código Material]],'BASE DE CALCULO'!$C$2:$G$379,7,) -> #REF!
A5: AD-4B | B5: Pararrayos de distribución de 9 kV; 12.47 kV | C5: Und. | D5: PROTECCIONES DE MT | G5: AS-22D | H5: AISLADOR POLIMÉRICO TIPO SUSPENSIÓN 15 KV | I5: Und. | J5: AISLADORES | K5: AISLADOR | L5: =VLOOKUP(Tabla12[[#This Row],[Código Material]],'BASE DE CALCULO'!$C$2:$G$379,7,) -> #REF!
A6: AH-11A | B6: Ancla de hormigón para retenidas | C6: Und. | D6: POSTES Y ANCLAS | G6: AC-11A | H6: AISLADOR DE PORCELANA TIPO CARRETE CLASE 53-2 | I6: Und. | J6: AISLADORES | K6: #N/A | L6: =VLOOKUP(Tabla12[[#This Row],[Código Material]],'BASE DE CALCULO'!$C$2:$G$379,7,) -> #REF!
A7: AR-12A | B7: AISLADOR DE PORCELANA TIPO POSTE 15 KV CLASE 57-1 | C7: Und. | D7: AISLADOR | G7: W-7A | H7: ALAMBRE # 4 AWG-SDO ALUMINIO PARA LIGADURA | I7: Mts. | J7: ALAMBRE DE LIGADURA | K7: ALAMBRE DE LIGADURA | L7: =VLOOKUP(Tabla12[[#This Row],[Código Material]],'BASE DE CALCULO'!$C$2:$G$379,7,) -> #REF!
A8: AS-22D | B8: AISLADOR POLIMÉRICO TIPO SUSPENSIÓN 15 KV | C8: Und. | D8: AISLADOR | G8: AH-11A | H8: Ancla de hormigón para retenidas | I8: Und. | J8: ANCLAS | K8: ANCLA | L8: =VLOOKUP(Tabla12[[#This Row],[Código Material]],'BASE DE CALCULO'!$C$2:$G$379,7,) -> #REF!
A9: B-10D | B9: Fleje vertical de acero galv. 1-1/2" x 1-1/2" x 3/16"; longitud 54" | C9: Und. | D9: HERRAJES | G9: W-10A | H9: ARANDELA DE PRESIÓN PARA TORNILLO DE 3/8" | I9: Und. | J9: ARANDELAS | K9: ARANDELA | L9: =VLOOKUP(Tabla12[[#This Row],[Código Material]],'BASE DE CALCULO'!$C$2:$G$379,7,) -> #REF!
A10: B-1C | B10: Tornillo de espaciamiento acero galvanizado 5/8” x 12” | C10: Und. | D10: HERRAJES | G10: W-10B | H10: ARANDELA DE PRESIÓN PARA TORNILLO DE 1/2" | I10: Und. | J10: ARANDELAS | K10: ARANDELA | L10: =VLOOKUP(Tabla12[[#This Row],[Código Material]],'BASE DE CALCULO'!$C$2:$G$379,7,) -> #REF!
A11: B-1D | B11: TORNILLO DE ESPACIAMIENTO ACERO GALVANIZADO 5/8" X 14". | C11: Und. | D11: HERRAJES | G11: W-10C | H11: ARANDELA DE PRESIÓN PARA TORNILLO DE 5/8" | I11: Und. | J11: ARANDELAS | K11: ARANDELA | L11: =VLOOKUP(Tabla12[[#This Row],[Código Material]],'BASE DE CALCULO'!$C$2:$G$379,7,) -> #REF!
A12: B-2B | B12: TORNILLO DE MAQUINA ACERO GALVANIZADO CABEZA CUADRADA 1/2" X 12". | C12: Und. | D12: HERRAJES | G12: W-9A | H12: ARANDELA CUADRADA PLANA DE 2" X 2" PARA TORNILLO DE 1/2" | I12: Und. | J12: ARANDELAS | K12: ARANDELA | L12: =VLOOKUP(Tabla12[[#This Row],[Código Material]],'BASE DE CALCULO'!$C$2:$G$379,7,) -> #REF!
A13: B-2C | B13: Tornillo de máquina acero galvanizado cabeza cuadrada 5/8” x 10” | C13: Und. | D13: HERRAJES | G13: W-9B | H13: ARANDELA CUAD.2 1/4" X 2 1/4" ESP.3/16'' (TORN.5/8"-3/4") | I13: Und. | J13: ARANDELAS | K13: ARANDELA | L13: =VLOOKUP(Tabla12[[#This Row],[Código Material]],'BASE DE CALCULO'!$C$2:$G$379,7,) -> #REF!
A14: B-2d | B14: TORNILLO DE MAQUINA ACERO GALVANIZADO CABEZA CUADRADA 5/8" X 12". | C14: Und. | D14: HERRAJES | G14: W-9C | H14: ARANDELA CUADRADA PLANA DE 2 1/4" X 2 1/4" PARA TORNILLO DE 5/8" | I14: Und. | J14: ARANDELAS | K14: ARANDELA | L14: =VLOOKUP(Tabla12[[#This Row],[Código Material]],'BASE DE CALCULO'!$C$2:$G$379,7,) -> #REF!
A15: B-2E | B15: TORNILLO DE MAQUINA CABEZA CUAD. 5/8" X 12" | C15: Und. | D15: HERRAJES | G15: W-9d | H15: Arandela cuadrada plana de 3” x 3” para tornillo de 3/4" | I15: Und. | J15: ARANDELAS | K15: ARANDELA | L15: =VLOOKUP(Tabla12[[#This Row],[Código Material]],'BASE DE CALCULO'!$C$2:$G$379,7,) -> #REF!
A16: B-2O | B16: TORNILLO DE MAQUINA CABEZA CUAD. 1/2" X 2" | C16: Und. | D16: HERRAJES | G16: CV-01C | H16: CABLE DE RETENIDA DE 7/16" | I16: Mts. | J16: CABLE DE RETENIDA | K16: CABLE DE RETENIDA | L16: =VLOOKUP(Tabla12[[#This Row],[Código Material]],'BASE DE CALCULO'!$C$2:$G$379,7,) -> #REF!
A17: B-4A | B17: CONECTOR PERNO PARTIDO PARA CABLE 2 AWG | C17: Und. | D17: HERRAJES | G17: CV-01B | H17: CABLE DE RETENIDA DE 3/8" | I17: Mts. | J17: CABLE DE RETENIDA | K17: #N/A | L17: =VLOOKUP(Tabla12[[#This Row],[Código Material]],'BASE DE CALCULO'!$C$2:$G$379,7,) -> #N/A
A18: B-5A | B18: TORNILLO DE MAQUINA ACERO GALVANIZADO CABEZA HEXAGONAL 3/8" X 2". | C18: Und. | D18: HERRAJES | G18: 1000568 | H18: Cobertor de Líneas MT 12.5kV MVLC 4/0 | I18: Mts. | J18: COBERTOR | K18: #N/A | L18: =VLOOKUP(Tabla12[[#This Row],[Código Material]],'BASE DE CALCULO'!$C$2:$G$379,7,) -> #REF!
A19: B-5B | B19: TORNILLO DE MAQUINA ACERO GALVANIZADO CABEZA HEXAGONAL 1/2"X 2". | C19: Und. | D19: HERRAJES | G19: R-5 | H19: Protector plástico amarillo para cable de viento de PVC 8' | I19: Und. | J19: COBERTOR | K19: COBERTOR | L19: =VLOOKUP(Tabla12[[#This Row],[Código Material]],'BASE DE CALCULO'!$C$2:$G$379,7,) -> #REF!
A20: B-5E | B20: Tornillo de maquina acero galvanizado cabeza hexagonal 5/8” x 3”. | C20: Und. | D20: HERRAJES | G20: CB-11F | H20: CONDUCTOR TRIPLEX DE ALUMINIO AAC 4/0 CON NEUTRO AAAC 4/0 AWG | I20: Mts. | J20: CONDUCTOR BT. | K20: CONDUCTOR MT. | L20: =VLOOKUP(Tabla12[[#This Row],[Código Material]],'BASE DE CALCULO'!$C$2:$G$379,7,) -> #REF!
A21: B-6A | B21: FLEJE PLANCHA DE ACERO GALV. 1-7/32"X 7/32" X 28" | C21: Und. | D21: HERRAJES | G21: CM-01C | H21: CONDUCTOR DESNUDO AAAC 2/0 MCM (AZUZA) | I21: Mts. | J21: CONDUCTOR MT. | K21: CONDUCTOR MT. | L21: =VLOOKUP(Tabla12[[#This Row],[Código Material]],'BASE DE CALCULO'!$C$2:$G$379,7,) -> #REF!
A22: B-7B | B22: FLEJE DIAGONAL DE ACERO GALV. 1-3/4" X 1-3/4" X 3/16"; LONGITUD 84" | C22: Und. | D22: HERRAJES | G22: CM-01E | H22: CONDUCTOR AAAC 4/0 AWG (ALLIANCE) | I22: Mts. | J22: CONDUCTOR MT. | K22: CONDUCTOR MT. | L22: =VLOOKUP(Tabla12[[#This Row],[Código Material]],'BASE DE CALCULO'!$C$2:$G$379,7,) -> #REF!
A23: B-7C | B23: FLEJE DIAGONAL DE ACERO GALV. 1-3/4" X 1-3/4" X 3/16"; LONGITUD 120" (PLAN DE AGUJERO EJECUTADO) | C23: Und. | D23: HERRAJES | G23: CM-01G | H23: Conductor AAAC 465.4 MCM (Cairo) | I23: Mts. | J23: CONDUCTOR MT. | K23: CONDUCTOR MT. | L23: =VLOOKUP(Tabla12[[#This Row],[Código Material]],'BASE DE CALCULO'!$C$2:$G$379,7,) -> #REF!
A24: B-7Y | B24: FLEJE DE SUJECIÓN 12.7MM X 0.4MM | C24: Und. | D24: HERRAJES | G24: CP-02C | H24: Cable de acero cobreado desnudo #2 AWG; 7 hilos | I24: Mts. | J24: CONDUCTOR MT. | K24: CONDUCTOR MT. | L24: =VLOOKUP(Tabla12[[#This Row],[Código Material]],'BASE DE CALCULO'!$C$2:$G$379,7,) -> #REF!
A25: B-9 | B25: Soporte en poste simple unidad; perno 1/2" x 1-1/2" (seccionador) | C25: Und. | D25: HERRAJES | G25: C-3DB | H25: CABLE DE COBRE (URD) # 2 AL 33% AISLADO PARA 15 KV | I25: Mts. | J25: CONDUCTOR MT. | K25: #N/A | L25: =VLOOKUP(Tabla12[[#This Row],[Código Material]],'BASE DE CALCULO'!$C$2:$G$379,7,) -> #N/A
A26: C-15D | B26: GRAPA DE RETENCION DE ACERO GALVANIZ. PARA COND. DE 1/0 AL-ACSR A 636MCM AL | C26: Und. | D26: HERRAJES | G26: URD-MT | H26: CABLE URD 15 KV, 4/0 AWG, ALUMINIO, TR-XLPE, CONCÉNTRICO | I26: Mts. | J26: CONDUCTOR MT. | K26: #N/A | L26: =VLOOKUP(Tabla12[[#This Row],[Código Material]],'BASE DE CALCULO'!$C$2:$G$379,7,) -> #N/A
A27: C-18B | B27: ABRAZADERA DE CONTRA PRESIÓN PARA TUBO DE ANCLAJE DE 2" | C27: Und. | D27: HERRAJES | G27: B-4A | H27: CONECTOR PERNO PARTIDO PARA CABLE 2 AWG | I27: Und. | J27: CONECTORES | K27: CONECTORES | L27: =VLOOKUP(Tabla12[[#This Row],[Código Material]],'BASE DE CALCULO'!$C$2:$G$379,7,) -> #N/A
A28: C-20D | B28: CRUCETA DE ACERO GALVANIZADO, PERFIL "L", DE 3"X 3"X 1/4" X 8' | C28: Und. | D28: CRUCETAS | G28: C-35K | H28: CONECTOR ELÁSTICO TIPO CUÑA 4/0AWG # 2CU AWG | I28: Und. | J28: CONECTORES | K28: CONECTORES | L28: =VLOOKUP(Tabla12[[#This Row],[Código Material]],'BASE DE CALCULO'!$C$2:$G$379,7,) -> #N/A
A29: C-20E | B29: CRUCETA DE ACERO GALVANIZADO, PERFIL "L", DE 3"X 3"X 1/4" X 10' | C29: Und. | D29: CRUCETAS | G29: C-36A | H29: CONECTOR ELÁSTICO TIPO CUÑA 465 MCM – 465 MCM | I29: Und. | J29: CONECTORES | K29: CONECTORES | L29: =VLOOKUP(Tabla12[[#This Row],[Código Material]],'BASE DE CALCULO'!$C$2:$G$379,7,) -> #N/A
A30: C-20I | B30: CRUCETA DE ACERO GALVANIZADO, PERFIL L, DE 3" X 3" X 1/4" X 8` (C/SOPORTES A 45°) | C30: Und. | D30: CRUCETAS | G30: C-36C | H30: CONECTOR ELÁSTICO TIPO CUÑA 465 MCM – 4/0 MCM | I30: Und. | J30: CONECTORES | K30: CONECTORES | L30: =VLOOKUP(Tabla12[[#This Row],[Código Material]],'BASE DE CALCULO'!$C$2:$G$379,7,) -> #REF!
A31: C-26A | B31: Grapa de fijación de cable a superficie plana 1/4" p/conductor Cu 2/0-#8 AWG | C31: Und. | D31: HERRAJES | G31: C-36D | H31: CONECTOR ELÁSTICO TIPO CUÑA 4665 MCM - 2/0 AWG | I31: Und. | J31: CONECTORES | K31: CONECTORES | L31: =VLOOKUP(Tabla12[[#This Row],[Código Material]],'BASE DE CALCULO'!$C$2:$G$379,7,) -> #N/A
A32: C-35K | B32: CONECTOR ELÁSTICO TIPO CUÑA 4/0AWG # 2CU AWG | C32: Und. | D32: CONECTOR | G32: C-38A | H32: CONECTOR ELÁSTICO TIPO CUÑA 4/0 AWG – 4/0 AWG | I32: Und. | J32: CONECTORES | K32: CONECTORES | L32: =VLOOKUP(Tabla12[[#This Row],[Código Material]],'BASE DE CALCULO'!$C$2:$G$379,7,) -> #REF!
A33: C-36A | B33: CONECTOR ELÁSTICO TIPO CUÑA 465 MCM – 465 MCM | C33: Und. | D33: CONECTOR | G33: C-38B | H33: CONECTOR ELÁSTICO TIPO CUÑA 4/0 AWG - #2 CU | I33: Und. | J33: CONECTORES | K33: #N/A | L33: =VLOOKUP(Tabla12[[#This Row],[Código Material]],'BASE DE CALCULO'!$C$2:$G$379,7,) -> #N/A
A34: C-36C | B34: CONECTOR ELÁSTICO TIPO CUÑA 465 MCM – 4/0 MCM | C34: Und. | D34: CONECTOR | G34: C-38D | H34: Conector tipo cuña 4/0 AWG – 2 CU AWG | I34: Und. | J34: CONECTORES | K34: CONECTORES | L34: =VLOOKUP(Tabla12[[#This Row],[Código Material]],'BASE DE CALCULO'!$C$2:$G$379,7,) -> #N/A
A35: C-36D | B35: CONECTOR ELÁSTICO TIPO CUÑA 4665 MCM - 2/0 AWG | C35: Und. | D35: CONECTOR | G35: C-39A | H35: Conector tipo cuña 2/0 AWG – 2/0 AWG | I35: Und. | J35: CONECTORES | K35: CONECTORES | L35: =VLOOKUP(Tabla12[[#This Row],[Código Material]],'BASE DE CALCULO'!$C$2:$G$379,7,) -> #N/A
A36: C-38A | B36: CONECTOR ELÁSTICO TIPO CUÑA 4/0 AWG – 4/0 AWG | C36: Und. | D36: CONECTOR | G36: C-39E | H36: CONECTOR ELASTICO TIPO CUÑA #2 CU - #2 CU AWG | I36: Und. | J36: CONECTORES | K36: CONECTORES | L36: =VLOOKUP(Tabla12[[#This Row],[Código Material]],'BASE DE CALCULO'!$C$2:$G$379,7,) -> #N/A
A37: C-38D | B37: Conector tipo cuña 4/0 AWG – 2 CU AWG | C37: Und. | D37: CONECTOR | G37: C-40B | H37: Conector elástico tipo cuña 465.4 MCM con estribo. | I37: Und. | J37: CONECTORES | K37: CONECTORES | L37: =VLOOKUP(Tabla12[[#This Row],[Código Material]],'BASE DE CALCULO'!$C$2:$G$379,7,) -> #N/A
A38: C-39A | B38: Conector tipo cuña 2/0 AWG – 2/0 AWG | C38: Und. | D38: CONECTOR | G38: C-40D | H38: CONECTOR ELÁSTICO TIPO CUÑA 4/0 AWG CON ESTRIBO. | I38: Und. | J38: CONECTORES | K38: #N/A | L38: =VLOOKUP(Tabla12[[#This Row],[Código Material]],'BASE DE CALCULO'!$C$2:$G$379,7,) -> #N/A
A39: C-39E | B39: CONECTOR ELASTICO TIPO CUÑA #2 CU - #2 CU AWG | C39: Und. | D39: CONECTOR | G39: C-6HC | H39: CONECTOR TIPO CUÑA DE ALUMINO DE 4/0 DERIVACION 4/0 A 3/0 AWG | I39: Und. | J39: CONECTORES | K39: CONECTORES | L39: =VLOOKUP(Tabla12[[#This Row],[Código Material]],'BASE DE CALCULO'!$C$2:$G$379,7,) -> #REF!
A40: C-40B | B40: Conector elástico tipo cuña 465.4 MCM con estribo. | C40: Und. | D40: CONECTOR | G40: C-7N | H40: Terminal de compresión calibre 4/0; 1 agujero | I40: Und. | J40: CONECTORES | K40: #N/A | L40: =VLOOKUP(Tabla12[[#This Row],[Código Material]],'BASE DE CALCULO'!$C$2:$G$379,7,) -> #REF!
A41: C-6HC | B41: CONECTOR TIPO CUÑA DE ALUMINO DE 4/0 DERIVACION 4/0 A 3/0 AWG | C41: Und. | D41: CONECTOR | G41: CAPE | H41: Conector amovible para estribo | I41: Und. | J41: CONECTORES | K41: CONECTORES | L41: =VLOOKUP(Tabla12[[#This Row],[Código Material]],'BASE DE CALCULO'!$C$2:$G$379,7,) -> #N/A
A42: CAPE | B42: Conector amovible para estribo | C42: Und. | D42: CONECTOR | G42: C-R1D | H42: CONECTOR PARA VARILLA DE TIERRA 5/8 (ATORNILLADO) | I42: Und. | J42: CONECTORES | K42: CONECTORES | L42: =VLOOKUP(Tabla12[[#This Row],[Código Material]],'BASE DE CALCULO'!$C$2:$G$379,7,) -> #REF!
A43: CB-11F | B43: CONDUCTOR TRIPLEX DE ALUMINIO AAC 4/0 CON NEUTRO AAAC 4/0 AWG | C43: Mts. | D43: ALAMBRES, CABLES Y CONDUCTORES | G43: B-13 | H43: TERMINAL DEL CABLE PARA USO EXTERIOR (URD) | I43: Und. | J43: CONECTORES | K43: #N/A | L43: =VLOOKUP(Tabla12[[#This Row],[Código Material]],'BASE DE CALCULO'!$C$2:$G$379,7,) -> #N/A
A44: CM-01C | B44: CONDUCTOR DESNUDO AAAC 2/0 MCM (AZUZA) | C44: Mts. | D44: ALAMBRES, CABLES Y CONDUCTORES | G44: C-20C | H44: CRUCETA DE ACERO GALVANIZADO, PERFIL "L", DE 3"X 3"X 1/4" X 6' | I44: Und. | J44: CRUCETAS | K44: #N/A | L44: =VLOOKUP(Tabla12[[#This Row],[Código Material]],'BASE DE CALCULO'!$C$2:$G$379,7,) -> #N/A
A45: CM-01E | B45: CONDUCTOR AAAC 4/0 AWG (ALLIANCE) | C45: Mts. | D45: ALAMBRES, CABLES Y CONDUCTORES | G45: C-20D | H45: CRUCETA DE ACERO GALVANIZADO, PERFIL "L", DE 3"X 3"X 1/4" X 8' | I45: Und. | J45: CRUCETAS | K45: CRUCETA | L45: =VLOOKUP(Tabla12[[#This Row],[Código Material]],'BASE DE CALCULO'!$C$2:$G$379,7,) -> #REF!
A46: CM-01G | B46: Conductor AAAC 465.4 MCM (Cairo) | C46: Mts. | D46: ALAMBRES, CABLES Y CONDUCTORES | G46: C-20E | H46: CRUCETA DE ACERO GALVANIZADO, PERFIL "L", DE 3"X 3"X 1/4" X 10' | I46: Und. | J46: CRUCETAS | K46: CRUCETA | L46: =VLOOKUP(Tabla12[[#This Row],[Código Material]],'BASE DE CALCULO'!$C$2:$G$379,7,) -> #N/A
A47: CP-02C | B47: Cable de acero cobreado desnudo #2 AWG; 7 hilos | C47: Mts. | D47: ALAMBRES, CABLES Y CONDUCTORES | G47: C-20H | H47: CRUCETA DE ACERO GALVANIZADO, PERFIL L, DE 3" X 3" X 1/4" X 8` (C/SOPORTES A 45°) | I47: Und. | J47: CRUCETAS | K47: #N/A | L47: =VLOOKUP(Tabla12[[#This Row],[Código Material]],'BASE DE CALCULO'!$C$2:$G$379,7,) -> #N/A
A48: C-R1D | B48: CONECTOR PARA VARILLA DE TIERRA 5/8 (ATORNILLADO) | C48: Und. | D48: CONECTOR | G48: C-20I | H48: CRUCETA DE ACERO GALVANIZADO, PERFIL L, DE 3" X 3" X 1/4" X 8` (C/SOPORTES A 45°) | I48: Und. | J48: CRUCETAS | K48: CRUCETA | L48: =VLOOKUP(Tabla12[[#This Row],[Código Material]],'BASE DE CALCULO'!$C$2:$G$379,7,) -> #N/A
A49: CV-01C | B49: CABLE DE RETENIDA DE 7/16" | C49: Mts. | D49: ALAMBRES, CABLES Y CONDUCTORES | G49: L-1 | H49: ESLABON DE ENGANCHE EN 8 | I49: Und. | J49: ESLABON | K49: #N/A | L49: =VLOOKUP(Tabla12[[#This Row],[Código Material]],'BASE DE CALCULO'!$C$2:$G$379,7,) -> #REF!
A50: D-1 | B50: Porta aislador en "U" de 1-1/2" x 1/8"; orificio de 11/16", pin de 5/8" | C50: Und. | D50: HERRAJES | G50: B-10A | H50: FLEJE VERTICAL DE ACERO GALV. 1-1/2" X 1-1/2" X 3/16"; LONGITUD 39" | I50: Und. | J50: FLEJES | K50: #N/A | L50: =VLOOKUP(Tabla12[[#This Row],[Código Material]],'BASE DE CALCULO'!$C$2:$G$379,7,) -> #N/A
A51: D-1B | B51: Porta aislador en "V"; 6 1/4" x 3 5/8" x 1 7/32 x 7/32'' | C51: Und. | D51: HERRAJES | G51: B-10B | H51: FLEJE VERTICAL DE ACERO GALV. 1-1/2" X 1-1/2" X 3/16"; LONGITUD 75" | I51: Und. | J51: FLEJES | K51: #N/A | L51: =VLOOKUP(Tabla12[[#This Row],[Código Material]],'BASE DE CALCULO'!$C$2:$G$379,7,) -> #N/A
A52: E-1B | B52: TUERCA GUARDACABO RECTO PARA TORNILLO 5/8”. | C52: Und. | D52: HERRAJES | G52: B-10D | H52: Fleje vertical de acero galv. 1-1/2" x 1-1/2" x 3/16"; longitud 54" | I52: Und. | J52: FLEJES | K52: FLEJES | L52: =VLOOKUP(Tabla12[[#This Row],[Código Material]],'BASE DE CALCULO'!$C$2:$G$379,7,) -> #REF!
A53: E-2A | B53: TUERCA DE OJO ACERO GALVANIZADO TORNILLO 5/8". | C53: Und. | D53: HERRAJES | G53: B-6A | H53: FLEJE PLANCHA DE ACERO GALV. 1-7/32"X 7/32" X 28" | I53: Und. | J53: FLEJES | K53: FLEJES | L53: =VLOOKUP(Tabla12[[#This Row],[Código Material]],'BASE DE CALCULO'!$C$2:$G$379,7,) -> #REF!
A54: E-3A | B54: Tuerca guardacabo inclinada para tornillo 5/8” | C54: Und. | D54: HERRAJES | G54: B-7A | H54: FLEJE DIAGONAL DE ACERO GALV. 1-3/4" X 1-3/4" X 3/16"; LONGITUD 60" | I54: Und. | J54: FLEJES | K54: #N/A | L54: =VLOOKUP(Tabla12[[#This Row],[Código Material]],'BASE DE CALCULO'!$C$2:$G$379,7,) -> #N/A
A55: E-4 | B55: Tuerca cuadrada para tornillo de 5/8" | C55: Und. | D55: HERRAJES | G55: B-7B | H55: FLEJE DIAGONAL DE ACERO GALV. 1-3/4" X 1-3/4" X 3/16"; LONGITUD 84" | I55: Und. | J55: FLEJES | K55: FLEJES | L55: =VLOOKUP(Tabla12[[#This Row],[Código Material]],'BASE DE CALCULO'!$C$2:$G$379,7,) -> #REF!
A56: E-4A | B56: TUERCA CUADRADA ACERO GALVANIZADO PARA TORNILLO 5/8”. | C56: Und. | D56: HERRAJES | G56: B-7C | H56: FLEJE DIAGONAL DE ACERO GALV. 1-3/4" X 1-3/4" X 3/16"; LONGITUD 120" (PLAN DE AGUJERO EJECUTADO) | I56: Und. | J56: FLEJES | K56: FLEJES | L56: =VLOOKUP(Tabla12[[#This Row],[Código Material]],'BASE DE CALCULO'!$C$2:$G$379,7,) -> #N/A
A57: G-1B | B57: TERMINAL PREFORMADO PARA CABLE RETENIDA DE 7/16" | C57: Und. | D57: HERRAJES | G57: B-7Y | H57: FLEJE DE SUJECIÓN 12.7MM X 0.4MM | I57: Und. | J57: FLEJES | K57: FLEJES | L57: =VLOOKUP(Tabla12[[#This Row],[Código Material]],'BASE DE CALCULO'!$C$2:$G$379,7,) -> #N/A
A58: G-4B | B58: TUBO DE ANCLAJE ACERO GALVANIZADO DE 2" X 5' | C58: Und. | D58: TUBERIAS | G58: B-7Z | H58: FLEJE PARA SUJECION 20 mm x 0.7 mm | I58: Und. | J58: FLEJES | K58: #N/A | L58: =VLOOKUP(Tabla12[[#This Row],[Código Material]],'BASE DE CALCULO'!$C$2:$G$379,7,) -> #REF!
A59: GCT-ST1 | B59: GRAPA DE CONEXIÓN DOBLE A TIERRA SIN TORNILLO PARA TORNILLO 5/8" | C59: Und. | D59: HERRAJES | G59: FU-11A | H59: FUSIBLE DE EXPULSIÓN 1.4 A TIPO DOBLE ELEMENTO. | I59: Und. | J59: FUSIBLES | K59: #N/A | L59: =VLOOKUP(Tabla12[[#This Row],[Código Material]],'BASE DE CALCULO'!$C$2:$G$379,7,) -> #N/A
A60: GR-10 | B60: GRAPA DE CONEXIÓN DOBLE A TIERRA SIN TORNILLO PARA TORNILLO DE 1/2" | C60: Und. | D60: HERRAJES | G60: C-15D | H60: GRAPA DE RETENCION DE ACERO GALVANIZ. PARA COND. DE 1/0 AL-ACSR A 636MCM AL | I60: Und. | J60: GRAPAS | K60: GRAPAS | L60: =VLOOKUP(Tabla12[[#This Row],[Código Material]],'BASE DE CALCULO'!$C$2:$G$379,7,) -> #REF!
A61: HA-1B | B61: Hebilla para fleje de sujeción de 20.0mm | C61: Und. | D61: HERRAJES | G61: C-26A | H61: Grapa de fijación de cable a superficie plana 1/4" p/conductor Cu 2/0-#8 AWG | I61: Und. | J61: GRAPAS | K61: GRAPAS | L61: =VLOOKUP(Tabla12[[#This Row],[Código Material]],'BASE DE CALCULO'!$C$2:$G$379,7,) -> #N/A
A62: HPV-500-10 | B62: POSTE DE HORMIGÓN PRETENSADO VIBRADO 500 DAN–10.5 M(35’) | C62: Und. | D62: POSTES Y ANCLAS | G62: GCT-ST1 | H62: GRAPA DE CONEXIÓN DOBLE A TIERRA SIN TORNILLO PARA TORNILLO 5/8" | I62: Und. | J62: GRAPAS | K62: GRAPAS | L62: =VLOOKUP(Tabla12[[#This Row],[Código Material]],'BASE DE CALCULO'!$C$2:$G$379,7,) -> #REF!
A63: HPV-500-12 | B63: POSTE DE HORMIGÓN PRETENSADO VIBRADO 500 DAN – 12 M (40’) | C63: Und. | D63: POSTES Y ANCLAS | G63: GR-10 | H63: GRAPA DE CONEXIÓN DOBLE A TIERRA SIN TORNILLO PARA TORNILLO DE 1/2" | I63: Und. | J63: GRAPAS | K63: GRAPAS | L63: =VLOOKUP(Tabla12[[#This Row],[Código Material]],'BASE DE CALCULO'!$C$2:$G$379,7,) -> #N/A
A64: HPV-800-10 | B64: POSTE DE HORMIGÓN PRETENSADO VIBRADO 800 DAN-10.5 M(35’) | C64: Und. | D64: POSTES Y ANCLAS | G64: C-17A | H64: SOPORTE TERMINAR DE CABLE 3Ø (BAJADA SOTERRADA) | I64: Und. | J64: SOPORTES | K64: #N/A | L64: =VLOOKUP(Tabla12[[#This Row],[Código Material]],'BASE DE CALCULO'!$C$2:$G$379,7,) -> #N/A
A65: HPV-800-12 | B65: POSTE DE HORMIGÓN PRETENSADO VIBRADO 800 DAN – 12 M (40’) | C65: Und. | D65: POSTES Y ANCLAS | G65: C-15A | H65: GRAPA DE RETENCIÓN PARA CONDUCTORES #6 AWG - #2/0 AWG | I65: Und. | J65: GRAPAS | K65: #N/A | L65: =VLOOKUP(Tabla12[[#This Row],[Código Material]],'BASE DE CALCULO'!$C$2:$G$379,7,) -> #N/A
A66: HPV-800-14 | B66: Poste de Hormigón Pretensado Vibrado 800 daN – 14 m (45’) | C66: Und. | D66: POSTES Y ANCLAS | G66: C-15B | H66: GRAPA DE RETENCIÓN PARA CONDUCTORES #2/0 AWG - #312.8 MCM | I66: Und. | J66: GRAPAS | K66: #N/A | L66: =VLOOKUP(Tabla12[[#This Row],[Código Material]],'BASE DE CALCULO'!$C$2:$G$379,7,) -> #REF!
A67: I-1A | B67: Perno para aisladores line post 3/4" - 3/4" x 3". | C67: Und. | D67: HERRAJES | G67: C-15C | H67: GRAPA DE RETENCIÓN PARA CONDUCTORES #312.8 MCM - #559 MCM | I67: Und. | J67: GRAPAS | K67: #N/A | L67: =VLOOKUP(Tabla12[[#This Row],[Código Material]],'BASE DE CALCULO'!$C$2:$G$379,7,) -> #N/A
A68: I-2F | B68: SOPORTE DE ACERO PARA AISLADOR RIGIDO EN CABEZA DE POSTE | C68: Und. | D68: HERRAJES | G68: HA-1B | H68: Hebilla para fleje de sujeción de 20.0mm | I68: Und. | J68: HEBILLAS | K68: HEBILLAS | L68: =VLOOKUP(Tabla12[[#This Row],[Código Material]],'BASE DE CALCULO'!$C$2:$G$379,7,) -> #REF!
A69: ITC-22 | B69: RECONECTADOR AUTOMATICO DE CIRCUITO | C69: Und. | D69: RECONECTADOR | G69: I-2F | H69: SOPORTE DE ACERO PARA AISLADOR RIGIDO EN CABEZA DE POSTE | I69: Und. | J69: SOPORTES | K69: HERRAJES | L69: =VLOOKUP(Tabla12[[#This Row],[Código Material]],'BASE DE CALCULO'!$C$2:$G$379,7,) -> #REF!
A70: ITC-22R1 | B70: RECONECTADOR AUTOMATICO DE CIRCUITO RE | C70: Und. | D70: RECONECTADOR | G70: AD-4B | H70: Pararrayos de distribución de 9 kV; 12.47 kV | I70: Und. | J70: PARARRAYO | K70: #N/A | L70: =VLOOKUP(Tabla12[[#This Row],[Código Material]],'BASE DE CALCULO'!$C$2:$G$379,7,) -> #N/A
A71: ITC-22S1 | B71: RECONECTADOR AUTOMATICO DE CIRCUITO SW ROJO | C71: Und. | D71: RECONECTADOR | G71: AD-4E | H71: PARARRAYO 10KV OXIDO METÁLICO | I71: Und. | J71: PARARRAYO | K71: #N/A | L71: =VLOOKUP(Tabla12[[#This Row],[Código Material]],'BASE DE CALCULO'!$C$2:$G$379,7,) -> #N/A
A72: N-3 | B72: Abrazadera perno de 5/8” | C72: Und. | D72: HERRAJES | G72: D-1 | H72: Porta aislador en "U" de 1-1/2" x 1/8"; orificio de 11/16", pin de 5/8" | I72: Und. | J72: PORTA AISLADOR | K72: PORTA AISLADOR | L72: =VLOOKUP(Tabla12[[#This Row],[Código Material]],'BASE DE CALCULO'!$C$2:$G$379,7,) -> #N/A
A73: P-1B | B73: Soporte para tubo de anclaje de 2" | C73: Und. | D73: HERRAJES | G73: D-1B | H73: Porta aislador en "V"; 6 1/4" x 3 5/8" x 1 7/32 x 7/32'' | I73: Und. | J73: PORTA AISLADOR | K73: PORTA AISLADOR | L73: =VLOOKUP(Tabla12[[#This Row],[Código Material]],'BASE DE CALCULO'!$C$2:$G$379,7,) -> #N/A
A74: R-1C | B74: Varilla de anclaje de ojo simple, de 3/4" x 8' | C74: Und. | D74: HERRAJES | G74: D-1E | H74: PORTA AISLADOR EN"V" 6 1/4" X 3 5/8" X 1 7/32 X 7/32'' | I74: Und. | J74: PORTA AISLADOR | K74: #N/A | L74: =VLOOKUP(Tabla12[[#This Row],[Código Material]],'BASE DE CALCULO'!$C$2:$G$379,7,) -> #N/A
A75: R-2F | B75: VARILLA DE PUESTA A TIERRA DE COBRE DE 5/8" X 8' | C75: Und. | D75: HERRAJES | G75: HPV-300-9 | H75: POSTE DE HORMIGÓN PRETENSADO DE 300 DAN; 9 M. | I75: Und. | J75: POSTE DE HORMIGÓN BT. | K75: #N/A | L75: =VLOOKUP(Tabla12[[#This Row],[Código Material]],'BASE DE CALCULO'!$C$2:$G$379,7,) -> #N/A
A76: R-5 | B76: Protector plástico amarillo para cable de viento de PVC 8' | C76: Und. | D76: TUBERIAS | G76: HPV-500-10 | H76: POSTE DE HORMIGÓN PRETENSADO VIBRADO 500 DAN–10.5 M(35’) | I76: Und. | J76: POSTE DE HORMIGÓN MT. | K76: POSTE DE HORMIGÓN MT. | L76: =VLOOKUP(Tabla12[[#This Row],[Código Material]],'BASE DE CALCULO'!$C$2:$G$379,7,) -> #N/A
A77: S-1C | B77: TORNILLO PARA AISLADOR TIPO CARRETE 5/8" X 14". | C77: Und. | D77: HERRAJES | G77: HPV-500-12 | H77: POSTE DE HORMIGÓN PRETENSADO VIBRADO 500 DAN – 12 M (40’) | I77: Und. | J77: POSTE DE HORMIGÓN MT. | K77: POSTE DE HORMIGÓN MT. | L77: =VLOOKUP(Tabla12[[#This Row],[Código Material]],'BASE DE CALCULO'!$C$2:$G$379,7,) -> #N/A
A78: S-1D | B78: Tornillo para aislador tipo carrete 5/8" x 16" | C78: Und. | D78: HERRAJES | G78: HPV-800-10 | H78: POSTE DE HORMIGÓN PRETENSADO VIBRADO 800 DAN-10.5 M(35’) | I78: Und. | J78: POSTE DE HORMIGÓN MT. | K78: POSTE DE HORMIGÓN MT. | L78: =VLOOKUP(Tabla12[[#This Row],[Código Material]],'BASE DE CALCULO'!$C$2:$G$379,7,) -> #N/A
A79: S-4 | B79: Soporte en poste doble unidad; perno 1/2" x 2" (pararrayos-seccionador) | C79: Und. | D79: HERRAJES | G79: HPV-800-12 | H79: POSTE DE HORMIGÓN PRETENSADO VIBRADO 800 DAN – 12 M (40’) | I79: Und. | J79: POSTE DE HORMIGÓN MT. | K79: POSTE DE HORMIGÓN MT. | L79: =VLOOKUP(Tabla12[[#This Row],[Código Material]],'BASE DE CALCULO'!$C$2:$G$379,7,) -> #N/A
A80: SF-11A | B80: Seccionador fusible de 100 A; 15 kV | C80: Und. | D80: PROTECCIONES DE MT | G80: HPV-800-14 | H80: Poste de Hormigón Pretensado Vibrado 800 daN – 14 m (45’) | I80: Und. | J80: POSTE DE HORMIGÓN MT. | K80: POSTE DE HORMIGÓN MT. | L80: =VLOOKUP(Tabla12[[#This Row],[Código Material]],'BASE DE CALCULO'!$C$2:$G$379,7,) -> #N/A
A81: TUB-4B | B81: TUBO PVC SDR26 DE 1/2"X19' | C81: Und. | D81: TUBERIAS | G81: HPV-500-14 | H81: POSTE DE HORMIGÓN PRETENSADO VIBRADO 500 DAN – 14 M (45’) | I81: Und. | J81: POSTE DE HORMIGÓN MT. | K81: #N/A | L81: =VLOOKUP(Tabla12[[#This Row],[Código Material]],'BASE DE CALCULO'!$C$2:$G$379,7,) -> #N/A
A82: W-10A | B82: ARANDELA DE PRESIÓN PARA TORNILLO DE 3/8" | C82: Und. | D82: HERRAJES | G82: 1011408 | H82: Poste de madera de 60 Pies Clase 2 | I82: Und. | J82: POSTE DE MADERA MT. | K82: #N/A | L82: =VLOOKUP(Tabla12[[#This Row],[Código Material]],'BASE DE CALCULO'!$C$2:$G$379,7,) -> #REF!
A83: W-10B | B83: ARANDELA DE PRESIÓN PARA TORNILLO DE 1/2" | C83: Und. | D83: HERRAJES | G83: MA-60 | H83: POSTE DE MADERA- 18 M (55´) | I83: Und. | J83: POSTE DE MADERA MT. | K83: #N/A | L83: =VLOOKUP(Tabla12[[#This Row],[Código Material]],'BASE DE CALCULO'!$C$2:$G$379,7,) -> #N/A
A84: W-10C | B84: ARANDELA DE PRESIÓN PARA TORNILLO DE 5/8" | C84: Und. | D84: HERRAJES | G84: PMC-1200-18 | H84: INSTALACIÓN DE POSTE DE METAL DE 1200KN DE 18 M | I84: Und. | J84: POSTE DE METAL MT. | K84: #N/A | L84: =VLOOKUP(Tabla12[[#This Row],[Código Material]],'BASE DE CALCULO'!$C$2:$G$379,7,) -> #N/A
A85: W-7A | B85: ALAMBRE # 4 AWG-SDO ALUMINIO PARA LIGADURA | C85: Mts. | D85: ALAMBRES, CABLES Y CONDUCTORES | G85: PMC-1200-20 | H85: INSTALACION DE POSTE DE METAL DE 1200 daN – 20 m (60’) | I85: Und. | J85: POSTE DE METAL MT. | K85: #N/A | L85: =VLOOKUP(Tabla12[[#This Row],[Código Material]],'BASE DE CALCULO'!$C$2:$G$379,7,) -> #N/A
A86: W-9A | B86: ARANDELA CUADRADA PLANA DE 2" X 2" PARA TORNILLO DE 1/2" | C86: Und. | D86: HERRAJES | G86: ITC-22 | H86: RECONECTADOR AUTOMATICO DE CIRCUITO | I86: Und. | J86: RECONECTADOR | K86: RECONECTADOR | L86: =VLOOKUP(Tabla12[[#This Row],[Código Material]],'BASE DE CALCULO'!$C$2:$G$379,7,) -> #N/A
A87: W-9B | B87: ARANDELA CUAD.2 1/4" X 2 1/4" ESP.3/16'' (TORN.5/8"-3/4") | C87: Und. | D87: HERRAJES | G87: ITC-22A | H87: RECONECTADOR AUTOMATICO DE CIRCUITO RE | I87: Und. | J87: RECONECTADOR | K87: #N/A | L87: =VLOOKUP(Tabla12[[#This Row],[Código Material]],'BASE DE CALCULO'!$C$2:$G$379,7,) -> #N/A
A88: W-9C | B88: ARANDELA CUADRADA PLANA DE 2 1/4" X 2 1/4" PARA TORNILLO DE 5/8" | C88: Und. | D88: HERRAJES | G88: ITC-22R1 | H88: RECONECTADOR AUTOMATICO DE CIRCUITO RE | I88: Und. | J88: RECONECTADOR | K88: RECONECTADOR | L88: =VLOOKUP(Tabla12[[#This Row],[Código Material]],'BASE DE CALCULO'!$C$2:$G$379,7,) -> #N/A
A89: W-9d | B89: Arandela cuadrada plana de 3” x 3” para tornillo de 3/4" | C89: Und. | D89: HERRAJES | G89: ITC-22S1 | H89: RECONECTADOR AUTOMATICO DE CIRCUITO SW ROJO | I89: Und. | J89: RECONECTADOR | K89: RECONECTADOR | L89: =VLOOKUP(Tabla12[[#This Row],[Código Material]],'BASE DE CALCULO'!$C$2:$G$379,7,) -> #N/A
A90: AD-4E | B90: PARARRAYO 10KV OXIDO METÁLICO | C90: Und. | D90: PROTECCIONES DE MT | G90: ITC-22B | H90: RECONECTADOR AUTOMATICO DE CIRCUITO SW | I90: Und. | J90: RECONECTADOR | K90: #N/A | L90: =VLOOKUP(Tabla12[[#This Row],[Código Material]],'BASE DE CALCULO'!$C$2:$G$379,7,) -> #N/A
A91: B-10A | B91: FLEJE VERTICAL DE ACERO GALV. 1-1/2" X 1-1/2" X 3/16"; LONGITUD 39" | C91: Und. | D91: HERRAJES | G91: CD-11B | H91: CUCHILLAS SECCIONADORA 15KV 600A | I91: Und. | J91: SECCIONADORES | K91: #N/A | L91: =VLOOKUP(Tabla12[[#This Row],[Código Material]],'BASE DE CALCULO'!$C$2:$G$379,7,) -> #N/A
A92: B-10B | B92: FLEJE VERTICAL DE ACERO GALV. 1-1/2" X 1-1/2" X 3/16"; LONGITUD 75" | C92: Und. | D92: HERRAJES | G92: CF-11A | H92: SECCIONADORES UNIPOLARES DE 100 A; 15 KV | I92: Und. | J92: SECCIONADORES | K92: #N/A | L92: =VLOOKUP(Tabla12[[#This Row],[Código Material]],'BASE DE CALCULO'!$C$2:$G$379,7,) -> #N/A
A93: B-13 | B93: TERMINAL DEL CABLE PARA USO EXTERIOR (URD) | C93: Und. | D93: HERRAJES | G93: SF-11A | H93: Seccionador fusible de 100 A; 15 kV | I93: Und. | J93: SECCIONADORES | K93: SECCIONADORES | L93: =VLOOKUP(Tabla12[[#This Row],[Código Material]],'BASE DE CALCULO'!$C$2:$G$379,7,) -> #N/A
A94: B-7A | B94: FLEJE DIAGONAL DE ACERO GALV. 1-3/4" X 1-3/4" X 3/16"; LONGITUD 60" | C94: Und. | D94: HERRAJES | G94: B-9 | H94: Soporte en poste simple unidad; perno 1/2" x 1-1/2" (seccionador) | I94: Und. | J94: SOPORTES | K94: SOPORTES | L94: =VLOOKUP(Tabla12[[#This Row],[Código Material]],'BASE DE CALCULO'!$C$2:$G$379,7,) -> #N/A
A95: B-7Z | B95: FLEJE PARA SUJECION 20 mm x 0.7 mm | C95: Und. | D95: HERRAJES | G95: P-1B | H95: Soporte para tubo de anclaje de 2" | I95: Und. | J95: SOPORTES | K95: SOPORTES | L95: =VLOOKUP(Tabla12[[#This Row],[Código Material]],'BASE DE CALCULO'!$C$2:$G$379,7,) -> #REF!
A96: C-15A | B96: GRAPA DE RETENCIÓN PARA CONDUCTORES #6 AWG - #2/0 AWG | C96: Und. | D96: HERRAJES | G96: S-4 | H96: Soporte en poste doble unidad; perno 1/2" x 2" (pararrayos-seccionador) | I96: Und. | J96: SOPORTES | K96: SOPORTES | L96: =VLOOKUP(Tabla12[[#This Row],[Código Material]],'BASE DE CALCULO'!$C$2:$G$379,7,) -> #N/A
A97: C-15B | B97: GRAPA DE RETENCIÓN PARA CONDUCTORES #2/0 AWG - #312.8 MCM | C97: Und. | D97: HERRAJES | G97: G-1B | H97: TERMINAL PREFORMADO PARA CABLE RETENIDA DE 7/16" | I97: Und. | J97: TERMINAL PREFORMADO | K97: TERMINAL PREFORMADO | L97: =VLOOKUP(Tabla12[[#This Row],[Código Material]],'BASE DE CALCULO'!$C$2:$G$379,7,) -> #REF!
A98: C-17A | B98: SOPORTE TERMINAR DE CABLE 3Ø (BAJADA SOTERRADA) | C98: Und. | D98: HERRAJES | G98: G-1C | H98: TERMINAL PREFORMADO PARA CABLE DE RETENIDA 3/8" | I98: Und. | J98: TERMINAL PREFORMADO | K98: #N/A | L98: =VLOOKUP(Tabla12[[#This Row],[Código Material]],'BASE DE CALCULO'!$C$2:$G$379,7,) -> #N/A
A99: C-20C | B99: CRUCETA DE ACERO GALVANIZADO, PERFIL "L", DE 3"X 3"X 1/4" X 6' | C99: Und. | D99: CRUCETAS | G99: G-2B | H99: TORNILLO GUARDACABO RECTO 5/8" X 12” | I99: Und. | J99: TORNILLERIA | K99: #N/A | L99: =VLOOKUP(Tabla12[[#This Row],[Código Material]],'BASE DE CALCULO'!$C$2:$G$379,7,) -> #N/A
A100: C-20H | B100: CRUCETA DE ACERO GALVANIZADO, PERFIL L, DE 3" X 3" X 1/4" X 8` (C/SOPORTES A 45°) | C100: Und. | D100: CRUCETAS | G100: B-1C | H100: Tornillo de espaciamiento acero galvanizado 5/8” x 12” | I100: Und. | J100: TORNILLERIA | K100: TORNILLERIA | L100: =VLOOKUP(Tabla12[[#This Row],[Código Material]],'BASE DE CALCULO'!$C$2:$G$379,7,) -> #REF!
...
